{
  "gameId": 232700249,
  "drives": {},
  "plays": [],
  "scoringPlays": [],
  "winprobability": [],
  "boxscore": {
    "teams": [
      {
        "team": {
          "shortDisplayName": "Ragin' Cajuns",
          "uid": "s:20~l:23~t:309",
          "color": "ce2842",
          "displayName": "Louisiana Ragin' Cajuns",
          "name": "Ragin' Cajuns",
          "logo": "https://a.espncdn.com/i/teamlogos/ncaa/500/309.png",
          "location": "Louisiana",
          "id": "309",
          "abbreviation": "ULL",
          "slug": "louisiana-ragin-cajuns"
        },
        "statistics": []
      },
      {
        "team": {
          "shortDisplayName": "Mean Green",
          "uid": "s:20~l:23~t:249",
          "alternateColor": "000000",
          "color": "00853D",
          "displayName": "North Texas Mean Green",
          "name": "Mean Green",
          "logo": "https://a.espncdn.com/i/teamlogos/ncaa/500/249.png",
          "location": "North Texas",
          "id": "249",
          "abbreviation": "UNT",
          "slug": "north-texas-mean-green"
        },
        "statistics": []
      }
    ],
    "players": [
      {
        "team": {
          "shortDisplayName": "Ragin' Cajuns",
          "uid": "s:20~l:23~t:309",
          "color": "ce2842",
          "displayName": "Louisiana Ragin' Cajuns",
          "name": "Ragin' Cajuns",
          "logo": "https://a.espncdn.com/i/teamlogos/ncaa/500/309.png",
          "location": "Louisiana",
          "id": "309",
          "abbreviation": "ULL",
          "slug": "louisiana-ragin-cajuns"
        },
        "statistics": []
      },
      {
        "team": {
          "shortDisplayName": "Mean Green",
          "uid": "s:20~l:23~t:249",
          "alternateColor": "000000",
          "color": "00853D",
          "displayName": "North Texas Mean Green",
          "name": "Mean Green",
          "logo": "https://a.espncdn.com/i/teamlogos/ncaa/500/249.png",
          "location": "North Texas",
          "id": "249",
          "abbreviation": "UNT",
          "slug": "north-texas-mean-green"
        },
        "statistics": []
      }
    ]
  },
  "header": {
    "uid": "s:20~l:23~e:232700249",
    "week": 6,
    "timeValid": true,
    "league": {
      "uid": "s:20~l:23",
      "midsizeName": "NCAA Football",
      "name": "NCAA - Football",
      "links": [
        {
          "rel": [
            "index",
            "desktop",
            "league"
          ],
          "href": "https://www.espn.com/college-football/",
          "text": "Index"
        },
        {
          "rel": [
            "index",
            "sportscenter",
            "app",
            "league"
          ],
          "href": "sportscenter://x-callback-url/showClubhouse?uid=s:20~l:23",
          "text": "Index"
        },
        {
          "rel": [
            "schedule",
            "desktop",
            "league"
          ],
          "href": "https://www.espn.com/college-football/schedule",
          "text": "Schedule"
        },
        {
          "rel": [
            "schedule",
            "sportscenter",
            "app",
            "league"
          ],
          "href": "sportscenter://x-callback-url/showClubhouse?uid=s:20~l:23&section=scores",
          "text": "Schedule"
        },
        {
          "rel": [
            "standings",
            "desktop",
            "league"
          ],
          "href": "http://www.espn.com/college-football/standings",
          "text": "Standings"
        },
        {
          "rel": [
            "standings",
            "sportscenter",
            "app",
            "league"
          ],
          "href": "sportscenter://x-callback-url/showClubhouse?uid=s:20~l:23&section=standings",
          "text": "Standings"
        },
        {
          "rel": [
            "rankings",
            "desktop",
            "league"
          ],
          "href": "https://www.espn.com/college-football/rankings",
          "text": "Rankings"
        },
        {
          "rel": [
            "scores",
            "desktop",
            "league"
          ],
          "href": "http://www.espn.com/college-football/scoreboard",
          "text": "Scores"
        },
        {
          "rel": [
            "scores",
            "sportscenter",
            "app",
            "league"
          ],
          "href": "sportscenter://x-callback-url/showClubhouse?uid=s:20~l:23&section=scores",
          "text": "Scores"
        },
        {
          "rel": [
            "stats",
            "desktop",
            "league"
          ],
          "href": "http://www.espn.com/college-football/stats",
          "text": "Stats"
        },
        {
          "rel": [
            "teams",
            "desktop",
            "league"
          ],
          "href": "http://www.espn.com/college-football/teams",
          "text": "Teams"
        },
        {
          "rel": [
            "athletes",
            "desktop",
            "league"
          ],
          "href": "http://www.espn.com/college-football/players",
          "text": "Players"
        },
        {
          "rel": [
            "injuries",
            "desktop",
            "league"
          ],
          "href": "https://www.espn.com/college-football/injuries",
          "text": "Injuries"
        }
      ],
      "id": "23",
      "abbreviation": "NCAAF",
      "slug": "college-football",
      "isTournament": false
    },
    "competitions": [
      {
        "date": "2003-09-28T00:05Z",
        "commentaryAvailable": false,
        "conferenceCompetition": true,
        "liveAvailable": false,
        "broadcasts": [],
        "groups": {
          "midsizeName": "Sun Belt",
          "name": "Sun Belt Conference",
          "id": "37",
          "abbreviation": "belt",
          "shortName": "Sun Belt"
        },
        "playByPlaySource": "none",
        "uid": "s:20~l:23~e:232700249~c:232700249",
        "competitors": [
          {
            "uid": "s:20~l:23~t:249",
            "homeAway": "home",
            "score": "44",
            "winner": true,
            "record": [
              {
                "summary": "2-3",
                "displayValue": "2-3",
                "type": "total"
              },
              {
                "summary": "2-0",
                "displayValue": "2-0",
                "type": "home"
              },
              {
                "summary": "1-0",
                "displayValue": "1-0",
                "type": "vsconf"
              }
            ],
            "possession": false,
            "id": "249",
            "team": {
              "uid": "s:20~l:23~t:249",
              "alternateColor": "000000",
              "color": "00853D",
              "displayName": "North Texas Mean Green",
              "name": "Mean Green",
              "nickname": "North Texas",
              "location": "North Texas",
              "links": [
                {
                  "rel": [
                    "clubhouse",
                    "desktop",
                    "team"
                  ],
                  "href": "https://www.espn.com/college-football/team/_/id/249/north-texas-mean-green",
                  "text": "Clubhouse"
                }
              ],
              "id": "249",
              "abbreviation": "UNT",
              "logos": [
                {
                  "width": 500,
                  "alt": "",
                  "rel": [
                    "full",
                    "default"
                  ],
                  "href": "https://a.espncdn.com/i/teamlogos/ncaa/500/249.png",
                  "height": 500
                },
                {
                  "width": 500,
                  "alt": "",
                  "rel": [
                    "full",
                    "dark"
                  ],
                  "href": "https://a.espncdn.com/i/teamlogos/ncaa/500-dark/249.png",
                  "height": 500
                }
              ]
            },
            "linescores": [
              {
                "displayValue": "16"
              },
              {
                "displayValue": "10"
              },
              {
                "displayValue": "4"
              },
              {
                "displayValue": "14"
              }
            ],
            "order": 0
          },
          {
            "uid": "s:20~l:23~t:309",
            "homeAway": "away",
            "score": "23",
            "winner": false,
            "record": [
              {
                "summary": "0-5",
                "displayValue": "0-5",
                "type": "total"
              },
              {
                "summary": "0-3",
                "displayValue": "0-3",
                "type": "road"
              },
              {
                "summary": "0-2",
                "displayValue": "0-2",
                "type": "vsconf"
              }
            ],
            "possession": false,
            "id": "309",
            "team": {
              "uid": "s:20~l:23~t:309",
              "color": "ce2842",
              "displayName": "Louisiana Ragin' Cajuns",
              "name": "Ragin' Cajuns",
              "nickname": "Louisiana",
              "location": "Louisiana",
              "links": [
                {
                  "rel": [
                    "clubhouse",
                    "desktop",
                    "team"
                  ],
                  "href": "https://www.espn.com/college-football/team/_/id/309/louisiana-ragin-cajuns",
                  "text": "Clubhouse"
                }
              ],
              "id": "309",
              "abbreviation": "ULL",
              "logos": [
                {
                  "width": 500,
                  "alt": "",
                  "rel": [
                    "full",
                    "default"
                  ],
                  "href": "https://a.espncdn.com/i/teamlogos/ncaa/500/309.png",
                  "height": 500
                },
                {
                  "width": 500,
                  "alt": "",
                  "rel": [
                    "full",
                    "dark"
                  ],
                  "href": "https://a.espncdn.com/i/teamlogos/ncaa/500-dark/309.png",
                  "height": 500
                }
              ]
            },
            "linescores": [
              {
                "displayValue": "7"
              },
              {
                "displayValue": "6"
              },
              {
                "displayValue": "10"
              },
              {
                "displayValue": "0"
              }
            ],
            "order": 1
          }
        ],
        "onWatchESPN": false,
        "boxscoreAvailable": true,
        "id": "232700249",
        "neutralSite": false,
        "recent": false,
        "boxscoreSource": "full",
        "status": {
          "type": {
            "name": "STATUS_FINAL",
            "description": "Final",
            "id": "3",
            "state": "post",
            "completed": true,
            "detail": "Final",
            "shortDetail": "Final"
          }
        }
      }
    ],
    "season": {
      "year": 2003,
      "type": 2
    },
    "links": [
      {
        "isExternal": false,
        "shortText": "Summary",
        "rel": [
          "summary",
          "desktop",
          "event"
        ],
        "href": "https://www.espn.com/college-football/game/_/gameId/232700249",
        "text": "Gamecast",
        "isPremium": false
      },
      {
        "isExternal": false,
        "shortText": "Box Score",
        "rel": [
          "boxscore",
          "desktop",
          "event"
        ],
        "href": "http://www.espn.com/college-football/boxscore/_/gameId/232700249",
        "text": "Box Score",
        "isPremium": false
      },
      {
        "isExternal": false,
        "shortText": "Team Stats",
        "rel": [
          "teamstats",
          "desktop",
          "event"
        ],
        "href": "https://www.espn.com/college-football/matchup?gameId=232700249",
        "text": "Team Stats",
        "isPremium": false
      }
    ],
    "id": "232700249",
    "gameNote": ""
  },
  "broadcasts": [],
  "videos": [],
  "standings": {
    "fullViewLink": {
      "text": "Full Standings",
      "href": "http://www.espn.com/college-football/standings"
    },
    "groups": [
      {
        "header": "2020 Conference USA Standings",
        "href": "https://www.espn.com/college-football/standings/_/group/12/view/fbs-i-a",
        "divisions": [
          {
            "header": "Conference USA - East",
            "standings": {
              "entries": []
            }
          },
          {
            "header": "Conference USA - West",
            "standings": {
              "entries": []
            }
          }
        ]
      }
    ]
  },
  "timeouts": {},
  "pickcenter": [],
  "againstTheSpread": [
    {
      "team": {
        "id": "309",
        "uid": "s:20~l:23~t:309",
        "displayName": "Louisiana Ragin' Cajuns",
        "abbreviation": "ULL",
        "links": [
          {
            "href": "https://www.espn.com/college-football/team/_/id/309/louisiana-ragin-cajuns",
            "text": "Clubhouse"
          },
          {
            "href": "http://www.espn.com/college-football/team/schedule/_/id/309",
            "text": "Schedule"
          }
        ],
        "logo": "https://a.espncdn.com/i/teamlogos/ncaa/500/309.png"
      },
      "records": []
    },
    {
      "team": {
        "id": "249",
        "uid": "s:20~l:23~t:249",
        "displayName": "North Texas Mean Green",
        "abbreviation": "UNT",
        "links": [
          {
            "href": "https://www.espn.com/college-football/team/_/id/249/north-texas-mean-green",
            "text": "Clubhouse"
          },
          {
            "href": "http://www.espn.com/college-football/team/schedule/_/id/249",
            "text": "Schedule"
          }
        ],
        "logo": "https://a.espncdn.com/i/teamlogos/ncaa/500/249.png"
      },
      "records": []
    }
  ],
  "odds": [],
  "predictor": {},
  "espnWP": [],
  "gameInfo": {
    "date": "2003-09-28T00:05Z",
    "commentaryAvailable": false,
    "conferenceCompetition": true,
    "liveAvailable": false,
    "broadcasts": [],
    "groups": {
      "midsizeName": "Sun Belt",
      "name": "Sun Belt Conference",
      "id": "37",
      "abbreviation": "belt",
      "shortName": "Sun Belt"
    },
    "playByPlaySource": "none",
    "uid": "s:20~l:23~e:232700249~c:232700249",
    "competitors": [
      {
        "uid": "s:20~l:23~t:249",
        "homeAway": "home",
        "score": "44",
        "winner": true,
        "record": [
          {
            "summary": "2-3",
            "displayValue": "2-3",
            "type": "total"
          },
          {
            "summary": "2-0",
            "displayValue": "2-0",
            "type": "home"
          },
          {
            "summary": "1-0",
            "displayValue": "1-0",
            "type": "vsconf"
          }
        ],
        "possession": false,
        "id": "249",
        "team": {
          "uid": "s:20~l:23~t:249",
          "alternateColor": "000000",
          "color": "00853D",
          "displayName": "North Texas Mean Green",
          "name": "Mean Green",
          "nickname": "North Texas",
          "location": "North Texas",
          "links": [
            {
              "rel": [
                "clubhouse",
                "desktop",
                "team"
              ],
              "href": "https://www.espn.com/college-football/team/_/id/249/north-texas-mean-green",
              "text": "Clubhouse"
            }
          ],
          "id": "249",
          "abbreviation": "UNT",
          "logos": [
            {
              "width": 500,
              "alt": "",
              "rel": [
                "full",
                "default"
              ],
              "href": "https://a.espncdn.com/i/teamlogos/ncaa/500/249.png",
              "height": 500
            },
            {
              "width": 500,
              "alt": "",
              "rel": [
                "full",
                "dark"
              ],
              "href": "https://a.espncdn.com/i/teamlogos/ncaa/500-dark/249.png",
              "height": 500
            }
          ]
        },
        "linescores": [
          {
            "displayValue": "16"
          },
          {
            "displayValue": "10"
          },
          {
            "displayValue": "4"
          },
          {
            "displayValue": "14"
          }
        ],
        "order": 0
      },
      {
        "uid": "s:20~l:23~t:309",
        "homeAway": "away",
        "score": "23",
        "winner": false,
        "record": [
          {
            "summary": "0-5",
            "displayValue": "0-5",
            "type": "total"
          },
          {
            "summary": "0-3",
            "displayValue": "0-3",
            "type": "road"
          },
          {
            "summary": "0-2",
            "displayValue": "0-2",
            "type": "vsconf"
          }
        ],
        "possession": false,
        "id": "309",
        "team": {
          "uid": "s:20~l:23~t:309",
          "color": "ce2842",
          "displayName": "Louisiana Ragin' Cajuns",
          "name": "Ragin' Cajuns",
          "nickname": "Louisiana",
          "location": "Louisiana",
          "links": [
            {
              "rel": [
                "clubhouse",
                "desktop",
                "team"
              ],
              "href": "https://www.espn.com/college-football/team/_/id/309/louisiana-ragin-cajuns",
              "text": "Clubhouse"
            }
          ],
          "id": "309",
          "abbreviation": "ULL",
          "logos": [
            {
              "width": 500,
              "alt": "",
              "rel": [
                "full",
                "default"
              ],
              "href": "https://a.espncdn.com/i/teamlogos/ncaa/500/309.png",
              "height": 500
            },
            {
              "width": 500,
              "alt": "",
              "rel": [
                "full",
                "dark"
              ],
              "href": "https://a.espncdn.com/i/teamlogos/ncaa/500-dark/309.png",
              "height": 500
            }
          ]
        },
        "linescores": [
          {
            "displayValue": "7"
          },
          {
            "displayValue": "6"
          },
          {
            "displayValue": "10"
          },
          {
            "displayValue": "0"
          }
        ],
        "order": 1
      }
    ],
    "onWatchESPN": false,
    "boxscoreAvailable": true,
    "id": "232700249",
    "neutralSite": false,
    "recent": false,
    "boxscoreSource": "full",
    "status": {
      "type": {
        "name": "STATUS_FINAL",
        "description": "Final",
        "id": "3",
        "state": "post",
        "completed": true,
        "detail": "Final",
        "shortDetail": "Final"
      }
    }
  },
  "season": {
    "year": 2003,
    "type": 2
  }
}