{
"boxscore": {
"teams": [
{
"team": {
"id": "62",
"uid": "s:20~l:23~t:62",
"slug": "hawaii-rainbow-warriors",
"location": "Hawai'i",
"name": "Rainbow Warriors",
"abbreviation": "HAW",
"displayName": "Hawai'i Rainbow Warriors",
"shortDisplayName": "Rainbow Warriors",
"color": "003420",
"alternateColor": "ffffff",
"logo": "https://a.espncdn.com/i/teamlogos/ncaa/500/62.png"
},
"statistics": [
{
"name": "firstDowns",
"displayValue": "32",
"label": "1st Downs"
},
{
"name": "thirdDownEff",
"displayValue": "5-11",
"label": "3rd down efficiency"
},
{
"name": "fourthDownEff",
"displayValue": "0-1",
"label": "4th down efficiency"
},
{
"name": "totalYards",
"displayValue": "519",
"label": "Total Yards"
},
{
"name": "netPassingYards",
"displayValue": "470",
"label": "Passing"
},
{
"name": "completionAttempts",
"displayValue": "36-48",
"label": "Comp-Att"
},
{
"name": "yardsPerPass",
"displayValue": "9.5",
"label": "Yards per pass"
},
{
"name": "rushingYards",
"displayValue": "62",
"label": "Rushing"
},
{
"name": "rushingAttempts",
"displayValue": "28",
"label": "Rushing Attempts"
},
{
"name": "yardsPerRushAttempt",
"displayValue": "2.2",
"label": "Yards per rush"
},
{
"name": "totalPenaltiesYards",
"displayValue": "0-0",
"label": "Penalties"
},
{
"name": "turnovers",
"displayValue": "2",
"label": "Turnovers"
},
{
"name": "fumblesLost",
"displayValue": "0",
"label": "Fumbles lost"
},
{
"name": "interceptions",
"displayValue": "2",
"label": "Interceptions thrown"
},
{
"name": "possessionTime",
"displayValue": "21:24",
"label": "Possession"
}
]
},
{
"team": {
"id": "23",
"uid": "s:20~l:23~t:23",
"slug": "san-jose-state-spartans",
"location": "San Jose State",
"name": "Spartans",
"abbreviation": "SJSU",
"displayName": "San Jose State Spartans",
"shortDisplayName": "Spartans",
"color": "005893",
"alternateColor": "fdba31",
"logo": "https://a.espncdn.com/i/teamlogos/ncaa/500/23.png"
},
"statistics": [
{
"name": "firstDowns",
"displayValue": "25",
"label": "1st Downs"
},
{
"name": "thirdDownEff",
"displayValue": "6-14",
"label": "3rd down efficiency"
},
{
"name": "fourthDownEff",
"displayValue": "2-2",
"label": "4th down efficiency"
},
{
"name": "totalYards",
"displayValue": "432",
"label": "Total Yards"
},
{
"name": "netPassingYards",
"displayValue": "262",
"label": "Passing"
},
{
"name": "completionAttempts",
"displayValue": "22-35",
"label": "Comp-Att"
},
{
"name": "yardsPerPass",
"displayValue": "7.5",
"label": "Yards per pass"
},
{
"name": "rushingYards",
"displayValue": "170",
"label": "Rushing"
},
{
"name": "rushingAttempts",
"displayValue": "35",
"label": "Rushing Attempts"
},
{
"name": "yardsPerRushAttempt",
"displayValue": "4.9",
"label": "Yards per rush"
},
{
"name": "totalPenaltiesYards",
"displayValue": "0-0",
"label": "Penalties"
},
{
"name": "turnovers",
"displayValue": "4",
"label": "Turnovers"
},
{
"name": "fumblesLost",
"displayValue": "2",
"label": "Fumbles lost"
},
{
"name": "interceptions",
"displayValue": "2",
"label": "Interceptions thrown"
},
{
"name": "possessionTime",
"displayValue": "15:16",
"label": "Possession"
}
]
}
],
"players": [
{
"team": {
"id": "62",
"uid": "s:20~l:23~t:62",
"slug": "hawaii-rainbow-warriors",
"location": "Hawai'i",
"name": "Rainbow Warriors",
"abbreviation": "HAW",
"displayName": "Hawai'i Rainbow Warriors",
"shortDisplayName": "Rainbow Warriors",
"color": "003420",
"alternateColor": "ffffff",
"logo": "https://a.espncdn.com/i/teamlogos/ncaa/500/62.png"
},
"statistics": [
{
"name": "passing",
"keys": [
"completions/passingAttempts",
"passingYards",
"yardsPerPassAttempt",
"passingTouchdowns",
"interceptions",
"adjQBR"
],
"text": "Hawai'i Passing",
"labels": [
"C/ATT",
"YDS",
"AVG",
"TD",
"INT",
"QBR"
],
"descriptions": [
"Completions/Attempts",
"Yards",
"Yards Per Pass Attempt",
"Touchdowns",
"Interceptions",
"Adjusted QBR"
],
"athletes": [
{
"athlete": {
"id": "145275",
"uid": "s:20~l:23~a:145275",
"guid": "ad326006f10fbaa668f31e6a4eefda8d",
"firstName": "Colt",
"lastName": "Brennan",
"displayName": "Colt Brennan",
"links": [
{
"rel": [
"playercard",
"desktop",
"athlete"
],
"href": "http://www.espn.com/college-football/player/_/id/145275/colt-brennan",
"text": "Player Card"
},
{
"rel": [
"stats",
"desktop",
"athlete"
],
"href": "http://www.espn.com/college-football/player/stats/_/id/145275/colt-brennan",
"text": "Stats"
},
{
"rel": [
"splits",
"desktop",
"athlete"
],
"href": "http://www.espn.com/college-football/player/splits/_/id/145275/colt-brennan",
"text": "Splits"
},
{
"rel": [
"gamelog",
"desktop",
"athlete"
],
"href": "http://www.espn.com/college-football/player/gamelog/_/id/145275/colt-brennan",
"text": "Game Log"
},
{
"rel": [
"news",
"desktop",
"athlete"
],
"href": "http://www.espn.com/college-football/player/news/_/id/145275/colt-brennan",
"text": "News"
},
{
"rel": [
"bio",
"desktop",
"athlete"
],
"href": "http://www.espn.com/college-football/player/bio/_/id/145275/colt-brennan",
"text": "Bio"
},
{
"rel": [
"overview",
"desktop",
"athlete"
],
"href": "http://www.espn.com/college-football/player/_/id/145275/colt-brennan",
"text": "Overview"
}
]
},
"stats": [
"36/48",
"457",
"9.5",
"3",
"2",
"67.8"
]
}
],
"totals": [
"36/48",
"470",
"9.5",
"3",
"2",
"--"
]
},
{
"name": "rushing",
"keys": [
"rushingAttempts",
"rushingYards",
"yardsPerRushAttempt",
"rushingTouchdowns",
"longRushing"
],
"text": "Hawai'i Rushing",
"labels": [
"CAR",
"YDS",
"AVG",
"TD",
"LONG"
],
"descriptions": [
"Rushing Attempts",
"Yards",
"Yards Per Rushing Attempt",
"Touchdowns",
"Longest Run"
],
"athletes": [
{
"athlete": {
"id": "128893",
"uid": "s:20~l:23~a:128893",
"guid": "f2f83cdf6c1498867beb1c43eb1f8055",
"firstName": "Nate",
"lastName": "Ilaoa",
"displayName": "Nate Ilaoa",
"links": [
{
"rel": [
"playercard",
"desktop",
"athlete"
],
"href": "http://www.espn.com/college-football/player/_/id/128893/nate-ilaoa",
"text": "Player Card"
},
{
"rel": [
"stats",
"desktop",
"athlete"
],
"href": "http://www.espn.com/college-football/player/stats/_/id/128893/nate-ilaoa",
"text": "Stats"
},
{
"rel": [
"splits",
"desktop",
"athlete"
],
"href": "http://www.espn.com/college-football/player/splits/_/id/128893/nate-ilaoa",
"text": "Splits"
},
{
"rel": [
"gamelog",
"desktop",
"athlete"
],
"href": "http://www.espn.com/college-football/player/gamelog/_/id/128893/nate-ilaoa",
"text": "Game Log"
},
{
"rel": [
"news",
"desktop",
"athlete"
],
"href": "http://www.espn.com/college-football/player/news/_/id/128893/nate-ilaoa",
"text": "News"
},
{
"rel": [
"bio",
"desktop",
"athlete"
],
"href": "http://www.espn.com/college-football/player/bio/_/id/128893/nate-ilaoa",
"text": "Bio"
},
{
"rel": [
"overview",
"desktop",
"athlete"
],
"href": "http://www.espn.com/college-football/player/_/id/128893/nate-ilaoa",
"text": "Overview"
}
]
},
"stats": [
"13",
"39",
"3.0",
"1",
"8"
]
},
{
"athlete": {
"id": "245364",
"uid": "s:20~l:23~a:245364",
"guid": "fcd56ad61f5f5bec335ae218b0ab13b7",
"firstName": "Mario",
"lastName": "Cox",
"displayName": "Mario Cox",
"links": [
{
"rel": [
"playercard",
"desktop",
"athlete"
],
"href": "http://www.espn.com/college-football/player/_/id/245364/mario-cox",
"text": "Player Card"
},
{
"rel": [
"stats",
"desktop",
"athlete"
],
"href": "http://www.espn.com/college-football/player/stats/_/id/245364/mario-cox",
"text": "Stats"
},
{
"rel": [
"splits",
"desktop",
"athlete"
],
"href": "http://www.espn.com/college-football/player/splits/_/id/245364/mario-cox",
"text": "Splits"
},
{
"rel": [
"gamelog",
"desktop",
"athlete"
],
"href": "http://www.espn.com/college-football/player/gamelog/_/id/245364/mario-cox",
"text": "Game Log"
},
{
"rel": [
"news",
"desktop",
"athlete"
],
"href": "http://www.espn.com/college-football/player/news/_/id/245364/mario-cox",
"text": "News"
},
{
"rel": [
"bio",
"desktop",
"athlete"
],
"href": "http://www.espn.com/college-football/player/bio/_/id/245364/mario-cox",
"text": "Bio"
},
{
"rel": [
"overview",
"desktop",
"athlete"
],
"href": "http://www.espn.com/college-football/player/_/id/245364/mario-cox",
"text": "Overview"
}
]
},
"stats": [
"2",
"11",
"5.5",
"0",
"8"
]
},
{
"athlete": {
"id": "170038",
"uid": "s:20~l:23~a:170038",
"guid": "facac2cd0fa52357f9b4852fb64db232",
"firstName": "Davone",
"lastName": "Bess",
"displayName": "Davone Bess",
"links": [
{
"rel": [
"playercard",
"desktop",
"athlete"
],
"href": "http://www.espn.com/college-football/player/_/id/170038/davone-bess",
"text": "Player Card"
},
{
"rel": [
"stats",
"desktop",
"athlete"
],
"href": "http://www.espn.com/college-football/player/stats/_/id/170038/davone-bess",
"text": "Stats"
},
{
"rel": [
"splits",
"desktop",
"athlete"
],
"href": "http://www.espn.com/college-football/player/splits/_/id/170038/davone-bess",
"text": "Splits"
},
{
"rel": [
"gamelog",
"desktop",
"athlete"
],
"href": "http://www.espn.com/college-football/player/gamelog/_/id/170038/davone-bess",
"text": "Game Log"
},
{
"rel": [
"news",
"desktop",
"athlete"
],
"href": "http://www.espn.com/college-football/player/news/_/id/170038/davone-bess",
"text": "News"
},
{
"rel": [
"bio",
"desktop",
"athlete"
],
"href": "http://www.espn.com/college-football/player/bio/_/id/170038/davone-bess",
"text": "Bio"
},
{
"rel": [
"overview",
"desktop",
"athlete"
],
"href": "http://www.espn.com/college-football/player/_/id/170038/davone-bess",
"text": "Overview"
}
]
},
"stats": [
"1",
"6",
"6.0",
"0",
"6"
]
},
{
"athlete": {
"id": "145275",
"uid": "s:20~l:23~a:145275",
"guid": "ad326006f10fbaa668f31e6a4eefda8d",
"firstName": "Colt",
"lastName": "Brennan",
"displayName": "Colt Brennan",
"links": [
{
"rel": [
"playercard",
"desktop",
"athlete"
],
"href": "http://www.espn.com/college-football/player/_/id/145275/colt-brennan",
"text": "Player Card"
},
{
"rel": [
"stats",
"desktop",
"athlete"
],
"href": "http://www.espn.com/college-football/player/stats/_/id/145275/colt-brennan",
"text": "Stats"
},
{
"rel": [
"splits",
"desktop",
"athlete"
],
"href": "http://www.espn.com/college-football/player/splits/_/id/145275/colt-brennan",
"text": "Splits"
},
{
"rel": [
"gamelog",
"desktop",
"athlete"
],
"href": "http://www.espn.com/college-football/player/gamelog/_/id/145275/colt-brennan",
"text": "Game Log"
},
{
"rel": [
"news",
"desktop",
"athlete"
],
"href": "http://www.espn.com/college-football/player/news/_/id/145275/colt-brennan",
"text": "News"
},
{
"rel": [
"bio",
"desktop",
"athlete"
],
"href": "http://www.espn.com/college-football/player/bio/_/id/145275/colt-brennan",
"text": "Bio"
},
{
"rel": [
"overview",
"desktop",
"athlete"
],
"href": "http://www.espn.com/college-football/player/_/id/145275/colt-brennan",
"text": "Overview"
}
]
},
"stats": [
"7",
"-4",
"-0.6",
"1",
"6"
]
}
],
"totals": [
"28",
"62",
"2.2",
"2",
"8"
]
},
{
"name": "receiving",
"keys": [
"receptions",
"receivingYards",
"yardsPerReception",
"receivingTouchdowns",
"longReception"
],
"text": "Hawai'i Receiving",
"labels": [
"REC",
"YDS",
"AVG",
"TD",
"LONG"
],
"descriptions": [
"Receptions",
"Yards",
"Yards Per Reception",
"Touchdowns",
"Longest Reception"
],
"athletes": [
{
"athlete": {
"id": "170058",
"uid": "s:20~l:23~a:170058",
"guid": "aa46ce22b93837c317a9696261ad4060",
"firstName": "Chad",
"lastName": "Mock",
"displayName": "Chad Mock",
"links": [
{
"rel": [
"playercard",
"desktop",
"athlete"
],
"href": "http://www.espn.com/college-football/player/_/id/170058/chad-mock",
"text": "Player Card"
},
{
"rel": [
"stats",
"desktop",
"athlete"
],
"href": "http://www.espn.com/college-football/player/stats/_/id/170058/chad-mock",
"text": "Stats"
},
{
"rel": [
"splits",
"desktop",
"athlete"
],
"href": "http://www.espn.com/college-football/player/splits/_/id/170058/chad-mock",
"text": "Splits"
},
{
"rel": [
"gamelog",
"desktop",
"athlete"
],
"href": "http://www.espn.com/college-football/player/gamelog/_/id/170058/chad-mock",
"text": "Game Log"
},
{
"rel": [
"news",
"desktop",
"athlete"
],
"href": "http://www.espn.com/college-football/player/news/_/id/170058/chad-mock",
"text": "News"
},
{
"rel": [
"bio",
"desktop",
"athlete"
],
"href": "http://www.espn.com/college-football/player/bio/_/id/170058/chad-mock",
"text": "Bio"
},
{
"rel": [
"overview",
"desktop",
"athlete"
],
"href": "http://www.espn.com/college-football/player/_/id/170058/chad-mock",
"text": "Overview"
}
]
},
"stats": [
"11",
"104",
"9.5",
"0",
"27"
]
},
{
"athlete": {
"id": "170038",
"uid": "s:20~l:23~a:170038",
"guid": "facac2cd0fa52357f9b4852fb64db232",
"firstName": "Davone",
"lastName": "Bess",
"displayName": "Davone Bess",
"links": [
{
"rel": [
"playercard",
"desktop",
"athlete"
],
"href": "http://www.espn.com/college-football/player/_/id/170038/davone-bess",
"text": "Player Card"
},
{
"rel": [
"stats",
"desktop",
"athlete"
],
"href": "http://www.espn.com/college-football/player/stats/_/id/170038/davone-bess",
"text": "Stats"
},
{
"rel": [
"splits",
"desktop",
"athlete"
],
"href": "http://www.espn.com/college-football/player/splits/_/id/170038/davone-bess",
"text": "Splits"
},
{
"rel": [
"gamelog",
"desktop",
"athlete"
],
"href": "http://www.espn.com/college-football/player/gamelog/_/id/170038/davone-bess",
"text": "Game Log"
},
{
"rel": [
"news",
"desktop",
"athlete"
],
"href": "http://www.espn.com/college-football/player/news/_/id/170038/davone-bess",
"text": "News"
},
{
"rel": [
"bio",
"desktop",
"athlete"
],
"href": "http://www.espn.com/college-football/player/bio/_/id/170038/davone-bess",
"text": "Bio"
},
{
"rel": [
"overview",
"desktop",
"athlete"
],
"href": "http://www.espn.com/college-football/player/_/id/170038/davone-bess",
"text": "Overview"
}
]
},
"stats": [
"9",
"102",
"11.3",
"2",
"19"
]
},
{
"athlete": {
"id": "136454",
"uid": "s:20~l:23~a:136454",
"guid": "28c5771d22560e15d4a915de173d0dae",
"firstName": "Ross",
"lastName": "Dickerson",
"displayName": "Ross Dickerson",
"links": [
{
"rel": [
"playercard",
"desktop",
"athlete"
],
"href": "http://www.espn.com/college-football/player/_/id/136454/ross-dickerson",
"text": "Player Card"
},
{
"rel": [
"stats",
"desktop",
"athlete"
],
"href": "http://www.espn.com/college-football/player/stats/_/id/136454/ross-dickerson",
"text": "Stats"
},
{
"rel": [
"splits",
"desktop",
"athlete"
],
"href": "http://www.espn.com/college-football/player/splits/_/id/136454/ross-dickerson",
"text": "Splits"
},
{
"rel": [
"gamelog",
"desktop",
"athlete"
],
"href": "http://www.espn.com/college-football/player/gamelog/_/id/136454/ross-dickerson",
"text": "Game Log"
},
{
"rel": [
"news",
"desktop",
"athlete"
],
"href": "http://www.espn.com/college-football/player/news/_/id/136454/ross-dickerson",
"text": "News"
},
{
"rel": [
"bio",
"desktop",
"athlete"
],
"href": "http://www.espn.com/college-football/player/bio/_/id/136454/ross-dickerson",
"text": "Bio"
},
{
"rel": [
"overview",
"desktop",
"athlete"
],
"href": "http://www.espn.com/college-football/player/_/id/136454/ross-dickerson",
"text": "Overview"
}
]
},
"stats": [
"5",
"79",
"15.8",
"0",
"25"
]
},
{
"athlete": {
"id": "128893",
"uid": "s:20~l:23~a:128893",
"guid": "f2f83cdf6c1498867beb1c43eb1f8055",
"firstName": "Nate",
"lastName": "Ilaoa",
"displayName": "Nate Ilaoa",
"links": [
{
"rel": [
"playercard",
"desktop",
"athlete"
],
"href": "http://www.espn.com/college-football/player/_/id/128893/nate-ilaoa",
"text": "Player Card"
},
{
"rel": [
"stats",
"desktop",
"athlete"
],
"href": "http://www.espn.com/college-football/player/stats/_/id/128893/nate-ilaoa",
"text": "Stats"
},
{
"rel": [
"splits",
"desktop",
"athlete"
],
"href": "http://www.espn.com/college-football/player/splits/_/id/128893/nate-ilaoa",
"text": "Splits"
},
{
"rel": [
"gamelog",
"desktop",
"athlete"
],
"href": "http://www.espn.com/college-football/player/gamelog/_/id/128893/nate-ilaoa",
"text": "Game Log"
},
{
"rel": [
"news",
"desktop",
"athlete"
],
"href": "http://www.espn.com/college-football/player/news/_/id/128893/nate-ilaoa",
"text": "News"
},
{
"rel": [
"bio",
"desktop",
"athlete"
],
"href": "http://www.espn.com/college-football/player/bio/_/id/128893/nate-ilaoa",
"text": "Bio"
},
{
"rel": [
"overview",
"desktop",
"athlete"
],
"href": "http://www.espn.com/college-football/player/_/id/128893/nate-ilaoa",
"text": "Overview"
}
]
},
"stats": [
"6",
"47",
"7.8",
"0",
"15"
]
}
],
"totals": [
"31",
"332",
"10.7",
"2",
"27"
]
},
{
"name": "interceptions",
"keys": [
"interceptions",
"interceptionYards",
"interceptionTouchdowns"
],
"text": "Hawai'i Interceptions",
"labels": [
"INT",
"YDS",
"TD"
],
"descriptions": [
"Interceptions",
"Yards",
"Touchdowns"
],
"athletes": [
{
"athlete": {
"id": "170060",
"uid": "s:20~l:23~a:170060",
"guid": "d5a362a3a7aa60a2799744c629709b5d",
"firstName": "Dane",
"lastName": "Porlas",
"displayName": "Dane Porlas",
"links": [
{
"rel": [
"playercard",
"desktop",
"athlete"
],
"href": "http://www.espn.com/college-football/player/_/id/170060/dane-porlas",
"text": "Player Card"
},
{
"rel": [
"stats",
"desktop",
"athlete"
],
"href": "http://www.espn.com/college-football/player/stats/_/id/170060/dane-porlas",
"text": "Stats"
},
{
"rel": [
"splits",
"desktop",
"athlete"
],
"href": "http://www.espn.com/college-football/player/splits/_/id/170060/dane-porlas",
"text": "Splits"
},
{
"rel": [
"gamelog",
"desktop",
"athlete"
],
"href": "http://www.espn.com/college-football/player/gamelog/_/id/170060/dane-porlas",
"text": "Game Log"
},
{
"rel": [
"news",
"desktop",
"athlete"
],
"href": "http://www.espn.com/college-football/player/news/_/id/170060/dane-porlas",
"text": "News"
},
{
"rel": [
"bio",
"desktop",
"athlete"
],
"href": "http://www.espn.com/college-football/player/bio/_/id/170060/dane-porlas",
"text": "Bio"
},
{
"rel": [
"overview",
"desktop",
"athlete"
],
"href": "http://www.espn.com/college-football/player/_/id/170060/dane-porlas",
"text": "Overview"
}
]
},
"stats": [
"1",
"22",
"0"
]
},
{
"athlete": {
"id": "177939",
"uid": "s:20~l:23~a:177939",
"guid": "7d33716ff4e7fa08029210c4cbbdee40",
"firstName": "Tumarian",
"lastName": "Moreland",
"displayName": "Tumarian Moreland",
"links": [
{
"rel": [
"playercard",
"desktop",
"athlete"
],
"href": "http://www.espn.com/college-football/player/_/id/177939/tumarian-moreland",
"text": "Player Card"
},
{
"rel": [
"stats",
"desktop",
"athlete"
],
"href": "http://www.espn.com/college-football/player/stats/_/id/177939/tumarian-moreland",
"text": "Stats"
},
{
"rel": [
"splits",
"desktop",
"athlete"
],
"href": "http://www.espn.com/college-football/player/splits/_/id/177939/tumarian-moreland",
"text": "Splits"
},
{
"rel": [
"gamelog",
"desktop",
"athlete"
],
"href": "http://www.espn.com/college-football/player/gamelog/_/id/177939/tumarian-moreland",
"text": "Game Log"
},
{
"rel": [
"news",
"desktop",
"athlete"
],
"href": "http://www.espn.com/college-football/player/news/_/id/177939/tumarian-moreland",
"text": "News"
},
{
"rel": [
"bio",
"desktop",
"athlete"
],
"href": "http://www.espn.com/college-football/player/bio/_/id/177939/tumarian-moreland",
"text": "Bio"
},
{
"rel": [
"overview",
"desktop",
"athlete"
],
"href": "http://www.espn.com/college-football/player/_/id/177939/tumarian-moreland",
"text": "Overview"
}
]
},
"stats": [
"1",
"0",
"0"
]
}
],
"totals": [
"2",
"22",
"0"
]
},
{
"name": "kickReturns",
"keys": [
"kickReturns",
"kickReturnYards",
"yardsPerKickReturn",
"longKickReturn",
"kickReturnTouchdowns"
],
"text": "Hawai'i Kick Returns",
"labels": [
"NO",
"YDS",
"AVG",
"LONG",
"TD"
],
"descriptions": [
"Kick Returns",
"Yards",
"Yards Per Kick Return",
"Longest Kick Return",
"Touchdowns"
],
"athletes": [],
"totals": []
},
{
"name": "puntReturns",
"keys": [
"puntReturns",
"puntReturnYards",
"yardsPerPuntReturn",
"longPuntReturn",
"puntReturnTouchdowns"
],
"text": "Hawai'i Punt Returns",
"labels": [
"NO",
"YDS",
"AVG",
"LONG",
"TD"
],
"descriptions": [
"Punt Returns",
"Yards",
"Yards Per Punt Return",
"Longest Punt Return",
"Touchdowns"
],
"athletes": [
{
"athlete": {
"id": "177945",
"uid": "s:20~l:23~a:177945",
"guid": "d319fe802ec6a7f92c14ad9dc47e10b0",
"firstName": "Andre",
"lastName": "Taylor",
"displayName": "Andre Taylor",
"links": [
{
"rel": [
"playercard",
"desktop",
"athlete"
],
"href": "http://www.espn.com/college-football/player/_/id/177945/andre-taylor",
"text": "Player Card"
},
{
"rel": [
"stats",
"desktop",
"athlete"
],
"href": "http://www.espn.com/college-football/player/stats/_/id/177945/andre-taylor",
"text": "Stats"
},
{
"rel": [
"splits",
"desktop",
"athlete"
],
"href": "http://www.espn.com/college-football/player/splits/_/id/177945/andre-taylor",
"text": "Splits"
},
{
"rel": [
"gamelog",
"desktop",
"athlete"
],
"href": "http://www.espn.com/college-football/player/gamelog/_/id/177945/andre-taylor",
"text": "Game Log"
},
{
"rel": [
"news",
"desktop",
"athlete"
],
"href": "http://www.espn.com/college-football/player/news/_/id/177945/andre-taylor",
"text": "News"
},
{
"rel": [
"bio",
"desktop",
"athlete"
],
"href": "http://www.espn.com/college-football/player/bio/_/id/177945/andre-taylor",
"text": "Bio"
},
{
"rel": [
"overview",
"desktop",
"athlete"
],
"href": "http://www.espn.com/college-football/player/_/id/177945/andre-taylor",
"text": "Overview"
}
]
},
"stats": [
"1",
"0",
"0.0",
"0",
"0"
]
}
],
"totals": [
"1",
"0",
"0.0",
"0",
"0"
]
},
{
"name": "kicking",
"keys": [
"fieldGoalsMade/fieldGoalAttempts",
"fieldGoalPct",
"longFieldGoalMade",
"extraPointsMade/extraPointAttempts",
"totalKickingPoints"
],
"text": "Hawai'i Kicking",
"labels": [
"FG",
"PCT",
"LONG",
"XP",
"PTS"
],
"descriptions": [
"Field Goals Made/Attempts",
"Field Goal Percentage",
"Longest Field Goal Made",
"Extra Points Made/Attempts",
"Kicking Points"
],
"athletes": [
{
"athlete": {
"id": "177933",
"uid": "s:20~l:23~a:177933",
"guid": "ecc0e298fba45d057e285fd41766c8a6",
"firstName": "Daniel",
"lastName": "Kelly",
"displayName": "Daniel Kelly",
"links": [
{
"rel": [
"playercard",
"desktop",
"athlete"
],
"href": "http://www.espn.com/college-football/player/_/id/177933/daniel-kelly",
"text": "Player Card"
},
{
"rel": [
"stats",
"desktop",
"athlete"
],
"href": "http://www.espn.com/college-football/player/stats/_/id/177933/daniel-kelly",
"text": "Stats"
},
{
"rel": [
"splits",
"desktop",
"athlete"
],
"href": "http://www.espn.com/college-football/player/splits/_/id/177933/daniel-kelly",
"text": "Splits"
},
{
"rel": [
"gamelog",
"desktop",
"athlete"
],
"href": "http://www.espn.com/college-football/player/gamelog/_/id/177933/daniel-kelly",
"text": "Game Log"
},
{
"rel": [
"news",
"desktop",
"athlete"
],
"href": "http://www.espn.com/college-football/player/news/_/id/177933/daniel-kelly",
"text": "News"
},
{
"rel": [
"bio",
"desktop",
"athlete"
],
"href": "http://www.espn.com/college-football/player/bio/_/id/177933/daniel-kelly",
"text": "Bio"
},
{
"rel": [
"overview",
"desktop",
"athlete"
],
"href": "http://www.espn.com/college-football/player/_/id/177933/daniel-kelly",
"text": "Overview"
}
]
},
"stats": [
"1/1",
"100.0",
"20",
"6/6",
"9"
]
}
],
"totals": [
"1/1",
"100.0",
"46",
"6/6",
"9"
]
},
{
"name": "punting",
"keys": [
"punts",
"puntYards",
"grossAvgPuntYards",
"touchbacks",
"puntsInside20",
"longPunt"
],
"text": "Hawai'i Punting",
"labels": [
"NO",
"YDS",
"AVG",
"TB",
"In 20",
"LONG"
],
"descriptions": [
"Punts",
"Yards",
"Average Punt Yards",
"Touchbacks",
"Punts Inside 20",
"Longest Punt"
],
"athletes": [
{
"athlete": {
"id": "148646",
"uid": "s:20~l:23~a:148646",
"guid": "0f5bdb67d0923362556a9cd3c888fd90",
"firstName": "Kurt",
"lastName": "Milne",
"displayName": "Kurt Milne",
"links": [
{
"rel": [
"playercard",
"desktop",
"athlete"
],
"href": "http://www.espn.com/college-football/player/_/id/148646/kurt-milne",
"text": "Player Card"
},
{
"rel": [
"stats",
"desktop",
"athlete"
],
"href": "http://www.espn.com/college-football/player/stats/_/id/148646/kurt-milne",
"text": "Stats"
},
{
"rel": [
"splits",
"desktop",
"athlete"
],
"href": "http://www.espn.com/college-football/player/splits/_/id/148646/kurt-milne",
"text": "Splits"
},
{
"rel": [
"gamelog",
"desktop",
"athlete"
],
"href": "http://www.espn.com/college-football/player/gamelog/_/id/148646/kurt-milne",
"text": "Game Log"
},
{
"rel": [
"news",
"desktop",
"athlete"
],
"href": "http://www.espn.com/college-football/player/news/_/id/148646/kurt-milne",
"text": "News"
},
{
"rel": [
"bio",
"desktop",
"athlete"
],
"href": "http://www.espn.com/college-football/player/bio/_/id/148646/kurt-milne",
"text": "Bio"
},
{
"rel": [
"overview",
"desktop",
"athlete"
],
"href": "http://www.espn.com/college-football/player/_/id/148646/kurt-milne",
"text": "Overview"
}
]
},
"stats": [
"3",
"115",
"38.3",
"0",
"0",
"46"
]
}
],
"totals": [
"3",
"115",
"38.3",
"0",
"0",
"46"
]
}
]
},
{
"team": {
"id": "23",
"uid": "s:20~l:23~t:23",
"slug": "san-jose-state-spartans",
"location": "San Jose State",
"name": "Spartans",
"abbreviation": "SJSU",
"displayName": "San Jose State Spartans",
"shortDisplayName": "Spartans",
"color": "005893",
"alternateColor": "fdba31",
"logo": "https://a.espncdn.com/i/teamlogos/ncaa/500/23.png"
},
"statistics": [
{
"name": "passing",
"keys": [
"completions/passingAttempts",
"passingYards",
"yardsPerPassAttempt",
"passingTouchdowns",
"interceptions",
"adjQBR"
],
"text": "San Jose State Passing",
"labels": [
"C/ATT",
"YDS",
"AVG",
"TD",
"INT",
"QBR"
],
"descriptions": [
"Completions/Attempts",
"Yards",
"Yards Per Pass Attempt",
"Touchdowns",
"Interceptions",
"Adjusted QBR"
],
"athletes": [
{
"athlete": {
"id": "148370",
"uid": "s:20~l:23~a:148370",
"guid": "ed73815ed5c18d38f2b8126ce427175e",
"firstName": "Adam",
"lastName": "Tafralis",
"displayName": "Adam Tafralis",
"links": [
{
"rel": [
"playercard",
"desktop",
"athlete"
],
"href": "http://www.espn.com/college-football/player/_/id/148370/adam-tafralis",
"text": "Player Card"
},
{
"rel": [
"stats",
"desktop",
"athlete"
],
"href": "http://www.espn.com/college-football/player/stats/_/id/148370/adam-tafralis",
"text": "Stats"
},
{
"rel": [
"splits",
"desktop",
"athlete"
],
"href": "http://www.espn.com/college-football/player/splits/_/id/148370/adam-tafralis",
"text": "Splits"
},
{
"rel": [
"gamelog",
"desktop",
"athlete"
],
"href": "http://www.espn.com/college-football/player/gamelog/_/id/148370/adam-tafralis",
"text": "Game Log"
},
{
"rel": [
"news",
"desktop",
"athlete"
],
"href": "http://www.espn.com/college-football/player/news/_/id/148370/adam-tafralis",
"text": "News"
},
{
"rel": [
"bio",
"desktop",
"athlete"
],
"href": "http://www.espn.com/college-football/player/bio/_/id/148370/adam-tafralis",
"text": "Bio"
},
{
"rel": [
"overview",
"desktop",
"athlete"
],
"href": "http://www.espn.com/college-football/player/_/id/148370/adam-tafralis",
"text": "Overview"
}
]
},
"stats": [
"22/35",
"262",
"7.5",
"2",
"2",
"35.4"
]
}
],
"totals": [
"22/35",
"262",
"7.5",
"2",
"2",
"--"
]
},
{
"name": "rushing",
"keys": [
"rushingAttempts",
"rushingYards",
"yardsPerRushAttempt",
"rushingTouchdowns",
"longRushing"
],
"text": "San Jose State Rushing",
"labels": [
"CAR",
"YDS",
"AVG",
"TD",
"LONG"
],
"descriptions": [
"Rushing Attempts",
"Yards",
"Yards Per Rushing Attempt",
"Touchdowns",
"Longest Run"
],
"athletes": [
{
"athlete": {
"id": "148325",
"uid": "s:20~l:23~a:148325",
"guid": "9c57a95c9656ba9172a9b66436ee7619",
"firstName": "Yonus",
"lastName": "Davis",
"displayName": "Yonus Davis",
"links": [
{
"rel": [
"playercard",
"desktop",
"athlete"
],
"href": "http://www.espn.com/college-football/player/_/id/148325/yonus-davis",
"text": "Player Card"
},
{
"rel": [
"stats",
"desktop",
"athlete"
],
"href": "http://www.espn.com/college-football/player/stats/_/id/148325/yonus-davis",
"text": "Stats"
},
{
"rel": [
"splits",
"desktop",
"athlete"
],
"href": "http://www.espn.com/college-football/player/splits/_/id/148325/yonus-davis",
"text": "Splits"
},
{
"rel": [
"gamelog",
"desktop",
"athlete"
],
"href": "http://www.espn.com/college-football/player/gamelog/_/id/148325/yonus-davis",
"text": "Game Log"
},
{
"rel": [
"news",
"desktop",
"athlete"
],
"href": "http://www.espn.com/college-football/player/news/_/id/148325/yonus-davis",
"text": "News"
},
{
"rel": [
"bio",
"desktop",
"athlete"
],
"href": "http://www.espn.com/college-football/player/bio/_/id/148325/yonus-davis",
"text": "Bio"
},
{
"rel": [
"overview",
"desktop",
"athlete"
],
"href": "http://www.espn.com/college-football/player/_/id/148325/yonus-davis",
"text": "Overview"
}
]
},
"stats": [
"11",
"66",
"6.0",
"1",
"20"
]
},
{
"athlete": {
"id": "162064",
"uid": "s:20~l:23~a:162064",
"guid": "877c366a6bc48ec184974e2719d4becf",
"firstName": "James T.",
"lastName": "Callier",
"displayName": "James T. Callier",
"links": [
{
"rel": [
"playercard",
"desktop",
"athlete"
],
"href": "http://www.espn.com/college-football/player/_/id/162064/james-t-callier",
"text": "Player Card"
},
{
"rel": [
"stats",
"desktop",
"athlete"
],
"href": "http://www.espn.com/college-football/player/stats/_/id/162064/james-t-callier",
"text": "Stats"
},
{
"rel": [
"splits",
"desktop",
"athlete"
],
"href": "http://www.espn.com/college-football/player/splits/_/id/162064/james-t-callier",
"text": "Splits"
},
{
"rel": [
"gamelog",
"desktop",
"athlete"
],
"href": "http://www.espn.com/college-football/player/gamelog/_/id/162064/james-t-callier",
"text": "Game Log"
},
{
"rel": [
"news",
"desktop",
"athlete"
],
"href": "http://www.espn.com/college-football/player/news/_/id/162064/james-t-callier",
"text": "News"
},
{
"rel": [
"bio",
"desktop",
"athlete"
],
"href": "http://www.espn.com/college-football/player/bio/_/id/162064/james-t-callier",
"text": "Bio"
},
{
"rel": [
"overview",
"desktop",
"athlete"
],
"href": "http://www.espn.com/college-football/player/_/id/162064/james-t-callier",
"text": "Overview"
}
]
},
"stats": [
"6",
"34",
"5.7",
"0",
"13"
]
},
{
"athlete": {
"id": "176762",
"uid": "s:20~l:23~a:176762",
"guid": "2889697545269b9e626fb37b31b631a1",
"firstName": "Al",
"lastName": "Guidry",
"displayName": "Al Guidry",
"links": [
{
"rel": [
"playercard",
"desktop",
"athlete"
],
"href": "http://www.espn.com/college-football/player/_/id/176762/al-guidry",
"text": "Player Card"
},
{
"rel": [
"stats",
"desktop",
"athlete"
],
"href": "http://www.espn.com/college-football/player/stats/_/id/176762/al-guidry",
"text": "Stats"
},
{
"rel": [
"splits",
"desktop",
"athlete"
],
"href": "http://www.espn.com/college-football/player/splits/_/id/176762/al-guidry",
"text": "Splits"
},
{
"rel": [
"gamelog",
"desktop",
"athlete"
],
"href": "http://www.espn.com/college-football/player/gamelog/_/id/176762/al-guidry",
"text": "Game Log"
},
{
"rel": [
"news",
"desktop",
"athlete"
],
"href": "http://www.espn.com/college-football/player/news/_/id/176762/al-guidry",
"text": "News"
},
{
"rel": [
"bio",
"desktop",
"athlete"
],
"href": "http://www.espn.com/college-football/player/bio/_/id/176762/al-guidry",
"text": "Bio"
},
{
"rel": [
"overview",
"desktop",
"athlete"
],
"href": "http://www.espn.com/college-football/player/_/id/176762/al-guidry",
"text": "Overview"
}
]
},
"stats": [
"3",
"33",
"11.0",
"1",
"25"
]
},
{
"athlete": {
"id": "148370",
"uid": "s:20~l:23~a:148370",
"guid": "ed73815ed5c18d38f2b8126ce427175e",
"firstName": "Adam",
"lastName": "Tafralis",
"displayName": "Adam Tafralis",
"links": [
{
"rel": [
"playercard",
"desktop",
"athlete"
],
"href": "http://www.espn.com/college-football/player/_/id/148370/adam-tafralis",
"text": "Player Card"
},
{
"rel": [
"stats",
"desktop",
"athlete"
],
"href": "http://www.espn.com/college-football/player/stats/_/id/148370/adam-tafralis",
"text": "Stats"
},
{
"rel": [
"splits",
"desktop",
"athlete"
],
"href": "http://www.espn.com/college-football/player/splits/_/id/148370/adam-tafralis",
"text": "Splits"
},
{
"rel": [
"gamelog",
"desktop",
"athlete"
],
"href": "http://www.espn.com/college-football/player/gamelog/_/id/148370/adam-tafralis",
"text": "Game Log"
},
{
"rel": [
"news",
"desktop",
"athlete"
],
"href": "http://www.espn.com/college-football/player/news/_/id/148370/adam-tafralis",
"text": "News"
},
{
"rel": [
"bio",
"desktop",
"athlete"
],
"href": "http://www.espn.com/college-football/player/bio/_/id/148370/adam-tafralis",
"text": "Bio"
},
{
"rel": [
"overview",
"desktop",
"athlete"
],
"href": "http://www.espn.com/college-football/player/_/id/148370/adam-tafralis",
"text": "Overview"
}
]
},
"stats": [
"6",
"24",
"4.0",
"0",
"11"
]
},
{
"athlete": {
"id": "120919",
"uid": "s:20~l:23~a:120919",
"guid": "691d7a947f014b716962af0891cce445",
"firstName": "Lamar",
"lastName": "Ferguson",
"displayName": "Lamar Ferguson",
"links": [
{
"rel": [
"playercard",
"desktop",
"athlete"
],
"href": "http://www.espn.com/college-football/player/_/id/120919/lamar-ferguson",
"text": "Player Card"
},
{
"rel": [
"stats",
"desktop",
"athlete"
],
"href": "http://www.espn.com/college-football/player/stats/_/id/120919/lamar-ferguson",
"text": "Stats"
},
{
"rel": [
"splits",
"desktop",
"athlete"
],
"href": "http://www.espn.com/college-football/player/splits/_/id/120919/lamar-ferguson",
"text": "Splits"
},
{
"rel": [
"gamelog",
"desktop",
"athlete"
],
"href": "http://www.espn.com/college-football/player/gamelog/_/id/120919/lamar-ferguson",
"text": "Game Log"
},
{
"rel": [
"news",
"desktop",
"athlete"
],
"href": "http://www.espn.com/college-football/player/news/_/id/120919/lamar-ferguson",
"text": "News"
},
{
"rel": [
"bio",
"desktop",
"athlete"
],
"href": "http://www.espn.com/college-football/player/bio/_/id/120919/lamar-ferguson",
"text": "Bio"
},
{
"rel": [
"overview",
"desktop",
"athlete"
],
"href": "http://www.espn.com/college-football/player/_/id/120919/lamar-ferguson",
"text": "Overview"
}
]
},
"stats": [
"8",
"12",
"1.5",
"1",
"7"
]
},
{
"athlete": {
"id": "162269",
"uid": "s:20~l:23~a:162269",
"guid": "62d451a5ad57b54f67736ddae9dbff7d",
"firstName": "Patrick",
"lastName": "Perry",
"displayName": "Patrick Perry",
"links": [
{
"rel": [
"playercard",
"desktop",
"athlete"
],
"href": "http://www.espn.com/college-football/player/_/id/162269/patrick-perry",
"text": "Player Card"
},
{
"rel": [
"stats",
"desktop",
"athlete"
],
"href": "http://www.espn.com/college-football/player/stats/_/id/162269/patrick-perry",
"text": "Stats"
},
{
"rel": [
"splits",
"desktop",
"athlete"
],
"href": "http://www.espn.com/college-football/player/splits/_/id/162269/patrick-perry",
"text": "Splits"
},
{
"rel": [
"gamelog",
"desktop",
"athlete"
],
"href": "http://www.espn.com/college-football/player/gamelog/_/id/162269/patrick-perry",
"text": "Game Log"
},
{
"rel": [
"news",
"desktop",
"athlete"
],
"href": "http://www.espn.com/college-football/player/news/_/id/162269/patrick-perry",
"text": "News"
},
{
"rel": [
"bio",
"desktop",
"athlete"
],
"href": "http://www.espn.com/college-football/player/bio/_/id/162269/patrick-perry",
"text": "Bio"
},
{
"rel": [
"overview",
"desktop",
"athlete"
],
"href": "http://www.espn.com/college-football/player/_/id/162269/patrick-perry",
"text": "Overview"
}
]
},
"stats": [
"1",
"1",
"1.0",
"0",
"1"
]
}
],
"totals": [
"35",
"170",
"4.9",
"3",
"25"
]
},
{
"name": "receiving",
"keys": [
"receptions",
"receivingYards",
"yardsPerReception",
"receivingTouchdowns",
"longReception"
],
"text": "San Jose State Receiving",
"labels": [
"REC",
"YDS",
"AVG",
"TD",
"LONG"
],
"descriptions": [
"Receptions",
"Yards",
"Yards Per Reception",
"Touchdowns",
"Longest Reception"
],
"athletes": [
{
"athlete": {
"id": "162272",
"uid": "s:20~l:23~a:162272",
"guid": "a43f1f125ff0e42ce0eec7ef119cd4e9",
"firstName": "Bryan",
"lastName": "Watje",
"displayName": "Bryan Watje",
"links": [
{
"rel": [
"playercard",
"desktop",
"athlete"
],
"href": "http://www.espn.com/college-football/player/_/id/162272/bryan-watje",
"text": "Player Card"
},
{
"rel": [
"stats",
"desktop",
"athlete"
],
"href": "http://www.espn.com/college-football/player/stats/_/id/162272/bryan-watje",
"text": "Stats"
},
{
"rel": [
"splits",
"desktop",
"athlete"
],
"href": "http://www.espn.com/college-football/player/splits/_/id/162272/bryan-watje",
"text": "Splits"
},
{
"rel": [
"gamelog",
"desktop",
"athlete"
],
"href": "http://www.espn.com/college-football/player/gamelog/_/id/162272/bryan-watje",
"text": "Game Log"
},
{
"rel": [
"news",
"desktop",
"athlete"
],
"href": "http://www.espn.com/college-football/player/news/_/id/162272/bryan-watje",
"text": "News"
},
{
"rel": [
"bio",
"desktop",
"athlete"
],
"href": "http://www.espn.com/college-football/player/bio/_/id/162272/bryan-watje",
"text": "Bio"
},
{
"rel": [
"overview",
"desktop",
"athlete"
],
"href": "http://www.espn.com/college-football/player/_/id/162272/bryan-watje",
"text": "Overview"
}
]
},
"stats": [
"6",
"93",
"15.5",
"0",
"23"
]
},
{
"athlete": {
"id": "120959",
"uid": "s:20~l:23~a:120959",
"guid": "456bd01eb4888bf3a4e8477cb20990eb",
"firstName": "Rufus",
"lastName": "Skillern",
"displayName": "Rufus Skillern",
"links": [
{
"rel": [
"playercard",
"desktop",
"athlete"
],
"href": "http://www.espn.com/college-football/player/_/id/120959/rufus-skillern",
"text": "Player Card"
},
{
"rel": [
"stats",
"desktop",
"athlete"
],
"href": "http://www.espn.com/college-football/player/stats/_/id/120959/rufus-skillern",
"text": "Stats"
},
{
"rel": [
"splits",
"desktop",
"athlete"
],
"href": "http://www.espn.com/college-football/player/splits/_/id/120959/rufus-skillern",
"text": "Splits"
},
{
"rel": [
"gamelog",
"desktop",
"athlete"
],
"href": "http://www.espn.com/college-football/player/gamelog/_/id/120959/rufus-skillern",
"text": "Game Log"
},
{
"rel": [
"news",
"desktop",
"athlete"
],
"href": "http://www.espn.com/college-football/player/news/_/id/120959/rufus-skillern",
"text": "News"
},
{
"rel": [
"bio",
"desktop",
"athlete"
],
"href": "http://www.espn.com/college-football/player/bio/_/id/120959/rufus-skillern",
"text": "Bio"
},
{
"rel": [
"overview",
"desktop",
"athlete"
],
"href": "http://www.espn.com/college-football/player/_/id/120959/rufus-skillern",
"text": "Overview"
}
]
},
"stats": [
"3",
"63",
"21.0",
"1",
"25"
]
},
{
"athlete": {
"id": "148323",
"uid": "s:20~l:23~a:148323",
"guid": "953c489ddf1471d982a0899d5417437e",
"firstName": "Chester",
"lastName": "Coleman",
"displayName": "Chester Coleman",
"links": [
{
"rel": [
"playercard",
"desktop",
"athlete"
],
"href": "http://www.espn.com/college-football/player/_/id/148323/chester-coleman",
"text": "Player Card"
},
{
"rel": [
"stats",
"desktop",
"athlete"
],
"href": "http://www.espn.com/college-football/player/stats/_/id/148323/chester-coleman",
"text": "Stats"
},
{
"rel": [
"splits",
"desktop",
"athlete"
],
"href": "http://www.espn.com/college-football/player/splits/_/id/148323/chester-coleman",
"text": "Splits"
},
{
"rel": [
"gamelog",
"desktop",
"athlete"
],
"href": "http://www.espn.com/college-football/player/gamelog/_/id/148323/chester-coleman",
"text": "Game Log"
},
{
"rel": [
"news",
"desktop",
"athlete"
],
"href": "http://www.espn.com/college-football/player/news/_/id/148323/chester-coleman",
"text": "News"
},
{
"rel": [
"bio",
"desktop",
"athlete"
],
"href": "http://www.espn.com/college-football/player/bio/_/id/148323/chester-coleman",
"text": "Bio"
},
{
"rel": [
"overview",
"desktop",
"athlete"
],
"href": "http://www.espn.com/college-football/player/_/id/148323/chester-coleman",
"text": "Overview"
}
]
},
"stats": [
"2",
"26",
"13.0",
"0",
"23"
]
},
{
"athlete": {
"id": "148320",
"uid": "s:20~l:23~a:148320",
"guid": "74f35fb23c8a8da955c465afee964d44",
"firstName": "John",
"lastName": "Broussard",
"displayName": "John Broussard",
"links": [
{
"rel": [
"playercard",
"desktop",
"athlete"
],
"href": "http://www.espn.com/college-football/player/_/id/148320/john-broussard",
"text": "Player Card"
},
{
"rel": [
"stats",
"desktop",
"athlete"
],
"href": "http://www.espn.com/college-football/player/stats/_/id/148320/john-broussard",
"text": "Stats"
},
{
"rel": [
"splits",
"desktop",
"athlete"
],
"href": "http://www.espn.com/college-football/player/splits/_/id/148320/john-broussard",
"text": "Splits"
},
{
"rel": [
"gamelog",
"desktop",
"athlete"
],
"href": "http://www.espn.com/college-football/player/gamelog/_/id/148320/john-broussard",
"text": "Game Log"
},
{
"rel": [
"news",
"desktop",
"athlete"
],
"href": "http://www.espn.com/college-football/player/news/_/id/148320/john-broussard",
"text": "News"
},
{
"rel": [
"bio",
"desktop",
"athlete"
],
"href": "http://www.espn.com/college-football/player/bio/_/id/148320/john-broussard",
"text": "Bio"
},
{
"rel": [
"overview",
"desktop",
"athlete"
],
"href": "http://www.espn.com/college-football/player/_/id/148320/john-broussard",
"text": "Overview"
}
]
},
"stats": [
"3",
"26",
"8.7",
"0",
"12"
]
},
{
"athlete": {
"id": "148325",
"uid": "s:20~l:23~a:148325",
"guid": "9c57a95c9656ba9172a9b66436ee7619",
"firstName": "Yonus",
"lastName": "Davis",
"displayName": "Yonus Davis",
"links": [
{
"rel": [
"playercard",
"desktop",
"athlete"
],
"href": "http://www.espn.com/college-football/player/_/id/148325/yonus-davis",
"text": "Player Card"
},
{
"rel": [
"stats",
"desktop",
"athlete"
],
"href": "http://www.espn.com/college-football/player/stats/_/id/148325/yonus-davis",
"text": "Stats"
},
{
"rel": [
"splits",
"desktop",
"athlete"
],
"href": "http://www.espn.com/college-football/player/splits/_/id/148325/yonus-davis",
"text": "Splits"
},
{
"rel": [
"gamelog",
"desktop",
"athlete"
],
"href": "http://www.espn.com/college-football/player/gamelog/_/id/148325/yonus-davis",
"text": "Game Log"
},
{
"rel": [
"news",
"desktop",
"athlete"
],
"href": "http://www.espn.com/college-football/player/news/_/id/148325/yonus-davis",
"text": "News"
},
{
"rel": [
"bio",
"desktop",
"athlete"
],
"href": "http://www.espn.com/college-football/player/bio/_/id/148325/yonus-davis",
"text": "Bio"
},
{
"rel": [
"overview",
"desktop",
"athlete"
],
"href": "http://www.espn.com/college-football/player/_/id/148325/yonus-davis",
"text": "Overview"
}
]
},
"stats": [
"1",
"25",
"25.0",
"0",
"25"
]
},
{
"athlete": {
"id": "136035",
"uid": "s:20~l:23~a:136035",
"guid": "26fb00b010c58ba119460c42bc256ff9",
"firstName": "James",
"lastName": "Jones",
"displayName": "James Jones",
"links": [
{
"rel": [
"playercard",
"desktop",
"athlete"
],
"href": "http://www.espn.com/college-football/player/_/id/136035/james-jones",
"text": "Player Card"
},
{
"rel": [
"stats",
"desktop",
"athlete"
],
"href": "http://www.espn.com/college-football/player/stats/_/id/136035/james-jones",
"text": "Stats"
},
{
"rel": [
"splits",
"desktop",
"athlete"
],
"href": "http://www.espn.com/college-football/player/splits/_/id/136035/james-jones",
"text": "Splits"
},
{
"rel": [
"gamelog",
"desktop",
"athlete"
],
"href": "http://www.espn.com/college-football/player/gamelog/_/id/136035/james-jones",
"text": "Game Log"
},
{
"rel": [
"news",
"desktop",
"athlete"
],
"href": "http://www.espn.com/college-football/player/news/_/id/136035/james-jones",
"text": "News"
},
{
"rel": [
"bio",
"desktop",
"athlete"
],
"href": "http://www.espn.com/college-football/player/bio/_/id/136035/james-jones",
"text": "Bio"
},
{
"rel": [
"overview",
"desktop",
"athlete"
],
"href": "http://www.espn.com/college-football/player/_/id/136035/james-jones",
"text": "Overview"
}
]
},
"stats": [
"4",
"17",
"4.3",
"1",
"7"
]
},
{
"athlete": {
"id": "148330",
"uid": "s:20~l:23~a:148330",
"guid": "7fceacda347facf15c5e49d0f5d783b5",
"firstName": "Michael",
"lastName": "Hooper",
"displayName": "Michael Hooper",
"links": [
{
"rel": [
"playercard",
"desktop",
"athlete"
],
"href": "http://www.espn.com/college-football/player/_/id/148330/michael-hooper",
"text": "Player Card"
},
{
"rel": [
"stats",
"desktop",
"athlete"
],
"href": "http://www.espn.com/college-football/player/stats/_/id/148330/michael-hooper",
"text": "Stats"
},
{
"rel": [
"splits",
"desktop",
"athlete"
],
"href": "http://www.espn.com/college-football/player/splits/_/id/148330/michael-hooper",
"text": "Splits"
},
{
"rel": [
"gamelog",
"desktop",
"athlete"
],
"href": "http://www.espn.com/college-football/player/gamelog/_/id/148330/michael-hooper",
"text": "Game Log"
},
{
"rel": [
"news",
"desktop",
"athlete"
],
"href": "http://www.espn.com/college-football/player/news/_/id/148330/michael-hooper",
"text": "News"
},
{
"rel": [
"bio",
"desktop",
"athlete"
],
"href": "http://www.espn.com/college-football/player/bio/_/id/148330/michael-hooper",
"text": "Bio"
},
{
"rel": [
"overview",
"desktop",
"athlete"
],
"href": "http://www.espn.com/college-football/player/_/id/148330/michael-hooper",
"text": "Overview"
}
]
},
"stats": [
"1",
"6",
"6.0",
"0",
"6"
]
},
{
"athlete": {
"id": "180018",
"uid": "s:20~l:23~a:180018",
"guid": "3bb6ee7941483905ef560b72e41a01a5",
"firstName": "Jason",
"lastName": "Lance",
"displayName": "Jason Lance",
"links": [
{
"rel": [
"playercard",
"desktop",
"athlete"
],
"href": "http://www.espn.com/college-football/player/_/id/180018/jason-lance",
"text": "Player Card"
},
{
"rel": [
"stats",
"desktop",
"athlete"
],
"href": "http://www.espn.com/college-football/player/stats/_/id/180018/jason-lance",
"text": "Stats"
},
{
"rel": [
"splits",
"desktop",
"athlete"
],
"href": "http://www.espn.com/college-football/player/splits/_/id/180018/jason-lance",
"text": "Splits"
},
{
"rel": [
"gamelog",
"desktop",
"athlete"
],
"href": "http://www.espn.com/college-football/player/gamelog/_/id/180018/jason-lance",
"text": "Game Log"
},
{
"rel": [
"news",
"desktop",
"athlete"
],
"href": "http://www.espn.com/college-football/player/news/_/id/180018/jason-lance",
"text": "News"
},
{
"rel": [
"bio",
"desktop",
"athlete"
],
"href": "http://www.espn.com/college-football/player/bio/_/id/180018/jason-lance",
"text": "Bio"
},
{
"rel": [
"overview",
"desktop",
"athlete"
],
"href": "http://www.espn.com/college-football/player/_/id/180018/jason-lance",
"text": "Overview"
}
]
},
"stats": [
"1",
"4",
"4.0",
"0",
"4"
]
},
{
"athlete": {
"id": "162064",
"uid": "s:20~l:23~a:162064",
"guid": "877c366a6bc48ec184974e2719d4becf",
"firstName": "James T.",
"lastName": "Callier",
"displayName": "James T. Callier",
"links": [
{
"rel": [
"playercard",
"desktop",
"athlete"
],
"href": "http://www.espn.com/college-football/player/_/id/162064/james-t-callier",
"text": "Player Card"
},
{
"rel": [
"stats",
"desktop",
"athlete"
],
"href": "http://www.espn.com/college-football/player/stats/_/id/162064/james-t-callier",
"text": "Stats"
},
{
"rel": [
"splits",
"desktop",
"athlete"
],
"href": "http://www.espn.com/college-football/player/splits/_/id/162064/james-t-callier",
"text": "Splits"
},
{
"rel": [
"gamelog",
"desktop",
"athlete"
],
"href": "http://www.espn.com/college-football/player/gamelog/_/id/162064/james-t-callier",
"text": "Game Log"
},
{
"rel": [
"news",
"desktop",
"athlete"
],
"href": "http://www.espn.com/college-football/player/news/_/id/162064/james-t-callier",
"text": "News"
},
{
"rel": [
"bio",
"desktop",
"athlete"
],
"href": "http://www.espn.com/college-football/player/bio/_/id/162064/james-t-callier",
"text": "Bio"
},
{
"rel": [
"overview",
"desktop",
"athlete"
],
"href": "http://www.espn.com/college-football/player/_/id/162064/james-t-callier",
"text": "Overview"
}
]
},
"stats": [
"1",
"2",
"2.0",
"0",
"2"
]
}
],
"totals": [
"22",
"262",
"11.9",
"2",
"25"
]
},
{
"name": "interceptions",
"keys": [
"interceptions",
"interceptionYards",
"interceptionTouchdowns"
],
"text": "San Jose State Interceptions",
"labels": [
"INT",
"YDS",
"TD"
],
"descriptions": [
"Interceptions",
"Yards",
"Touchdowns"
],
"athletes": [
{
"athlete": {
"id": "136026",
"uid": "s:20~l:23~a:136026",
"guid": "e073d163f82fa33ac08602b8df90e9cf",
"firstName": "Trestin",
"lastName": "George",
"displayName": "Trestin George",
"links": [
{
"rel": [
"playercard",
"desktop",
"athlete"
],
"href": "http://www.espn.com/college-football/player/_/id/136026/trestin-george",
"text": "Player Card"
},
{
"rel": [
"stats",
"desktop",
"athlete"
],
"href": "http://www.espn.com/college-football/player/stats/_/id/136026/trestin-george",
"text": "Stats"
},
{
"rel": [
"splits",
"desktop",
"athlete"
],
"href": "http://www.espn.com/college-football/player/splits/_/id/136026/trestin-george",
"text": "Splits"
},
{
"rel": [
"gamelog",
"desktop",
"athlete"
],
"href": "http://www.espn.com/college-football/player/gamelog/_/id/136026/trestin-george",
"text": "Game Log"
},
{
"rel": [
"news",
"desktop",
"athlete"
],
"href": "http://www.espn.com/college-football/player/news/_/id/136026/trestin-george",
"text": "News"
},
{
"rel": [
"bio",
"desktop",
"athlete"
],
"href": "http://www.espn.com/college-football/player/bio/_/id/136026/trestin-george",
"text": "Bio"
},
{
"rel": [
"overview",
"desktop",
"athlete"
],
"href": "http://www.espn.com/college-football/player/_/id/136026/trestin-george",
"text": "Overview"
}
]
},
"stats": [
"1",
"24",
"0"
]
},
{
"athlete": {
"id": "120926",
"uid": "s:20~l:23~a:120926",
"guid": "e0c6ff6c948e40277e6a6ca95578d8da",
"firstName": "Josh",
"lastName": "Powell",
"displayName": "Josh Powell",
"links": [
{
"rel": [
"playercard",
"desktop",
"athlete"
],
"href": "http://www.espn.com/college-football/player/_/id/120926/josh-powell",
"text": "Player Card"
},
{
"rel": [
"stats",
"desktop",
"athlete"
],
"href": "http://www.espn.com/college-football/player/stats/_/id/120926/josh-powell",
"text": "Stats"
},
{
"rel": [
"splits",
"desktop",
"athlete"
],
"href": "http://www.espn.com/college-football/player/splits/_/id/120926/josh-powell",
"text": "Splits"
},
{
"rel": [
"gamelog",
"desktop",
"athlete"
],
"href": "http://www.espn.com/college-football/player/gamelog/_/id/120926/josh-powell",
"text": "Game Log"
},
{
"rel": [
"news",
"desktop",
"athlete"
],
"href": "http://www.espn.com/college-football/player/news/_/id/120926/josh-powell",
"text": "News"
},
{
"rel": [
"bio",
"desktop",
"athlete"
],
"href": "http://www.espn.com/college-football/player/bio/_/id/120926/josh-powell",
"text": "Bio"
},
{
"rel": [
"overview",
"desktop",
"athlete"
],
"href": "http://www.espn.com/college-football/player/_/id/120926/josh-powell",
"text": "Overview"
}
]
},
"stats": [
"1",
"0",
"0"
]
}
],
"totals": [
"2",
"24",
"0"
]
},
{
"name": "kickReturns",
"keys": [
"kickReturns",
"kickReturnYards",
"yardsPerKickReturn",
"longKickReturn",
"kickReturnTouchdowns"
],
"text": "San Jose State Kick Returns",
"labels": [
"NO",
"YDS",
"AVG",
"LONG",
"TD"
],
"descriptions": [
"Kick Returns",
"Yards",
"Yards Per Kick Return",
"Longest Kick Return",
"Touchdowns"
],
"athletes": [],
"totals": []
},
{
"name": "puntReturns",
"keys": [
"puntReturns",
"puntReturnYards",
"yardsPerPuntReturn",
"longPuntReturn",
"puntReturnTouchdowns"
],
"text": "San Jose State Punt Returns",
"labels": [
"NO",
"YDS",
"AVG",
"LONG",
"TD"
],
"descriptions": [
"Punt Returns",
"Yards",
"Yards Per Punt Return",
"Longest Punt Return",
"Touchdowns"
],
"athletes": [
{
"athlete": {
"id": "136035",
"uid": "s:20~l:23~a:136035",
"guid": "26fb00b010c58ba119460c42bc256ff9",
"firstName": "James",
"lastName": "Jones",
"displayName": "James Jones",
"links": [
{
"rel": [
"playercard",
"desktop",
"athlete"
],
"href": "http://www.espn.com/college-football/player/_/id/136035/james-jones",
"text": "Player Card"
},
{
"rel": [
"stats",
"desktop",
"athlete"
],
"href": "http://www.espn.com/college-football/player/stats/_/id/136035/james-jones",
"text": "Stats"
},
{
"rel": [
"splits",
"desktop",
"athlete"
],
"href": "http://www.espn.com/college-football/player/splits/_/id/136035/james-jones",
"text": "Splits"
},
{
"rel": [
"gamelog",
"desktop",
"athlete"
],
"href": "http://www.espn.com/college-football/player/gamelog/_/id/136035/james-jones",
"text": "Game Log"
},
{
"rel": [
"news",
"desktop",
"athlete"
],
"href": "http://www.espn.com/college-football/player/news/_/id/136035/james-jones",
"text": "News"
},
{
"rel": [
"bio",
"desktop",
"athlete"
],
"href": "http://www.espn.com/college-football/player/bio/_/id/136035/james-jones",
"text": "Bio"
},
{
"rel": [
"overview",
"desktop",
"athlete"
],
"href": "http://www.espn.com/college-football/player/_/id/136035/james-jones",
"text": "Overview"
}
]
},
"stats": [
"2",
"9",
"4.5",
"9",
"0"
]
}
],
"totals": [
"2",
"9",
"4.5",
"9",
"0"
]
},
{
"name": "kicking",
"keys": [
"fieldGoalsMade/fieldGoalAttempts",
"fieldGoalPct",
"longFieldGoalMade",
"extraPointsMade/extraPointAttempts",
"totalKickingPoints"
],
"text": "San Jose State Kicking",
"labels": [
"FG",
"PCT",
"LONG",
"XP",
"PTS"
],
"descriptions": [
"Field Goals Made/Attempts",
"Field Goal Percentage",
"Longest Field Goal Made",
"Extra Points Made/Attempts",
"Kicking Points"
],
"athletes": [
{
"athlete": {
"id": "176776",
"uid": "s:20~l:23~a:176776",
"guid": "f6c4f3d09315e8b4c63b3375bd313ce9",
"firstName": "Jared",
"lastName": "Strubeck",
"displayName": "Jared Strubeck",
"links": [
{
"rel": [
"playercard",
"desktop",
"athlete"
],
"href": "http://www.espn.com/college-football/player/_/id/176776/jared-strubeck",
"text": "Player Card"
},
{
"rel": [
"stats",
"desktop",
"athlete"
],
"href": "http://www.espn.com/college-football/player/stats/_/id/176776/jared-strubeck",
"text": "Stats"
},
{
"rel": [
"splits",
"desktop",
"athlete"
],
"href": "http://www.espn.com/college-football/player/splits/_/id/176776/jared-strubeck",
"text": "Splits"
},
{
"rel": [
"gamelog",
"desktop",
"athlete"
],
"href": "http://www.espn.com/college-football/player/gamelog/_/id/176776/jared-strubeck",
"text": "Game Log"
},
{
"rel": [
"news",
"desktop",
"athlete"
],
"href": "http://www.espn.com/college-football/player/news/_/id/176776/jared-strubeck",
"text": "News"
},
{
"rel": [
"bio",
"desktop",
"athlete"
],
"href": "http://www.espn.com/college-football/player/bio/_/id/176776/jared-strubeck",
"text": "Bio"
},
{
"rel": [
"overview",
"desktop",
"athlete"
],
"href": "http://www.espn.com/college-football/player/_/id/176776/jared-strubeck",
"text": "Overview"
}
]
},
"stats": [
"1/1",
"100.0",
"44",
"5/5",
"8"
]
}
],
"totals": [
"1/1",
"100.0",
"46",
"5/5",
"8"
]
},
{
"name": "punting",
"keys": [
"punts",
"puntYards",
"grossAvgPuntYards",
"touchbacks",
"puntsInside20",
"longPunt"
],
"text": "San Jose State Punting",
"labels": [
"NO",
"YDS",
"AVG",
"TB",
"In 20",
"LONG"
],
"descriptions": [
"Punts",
"Yards",
"Average Punt Yards",
"Touchbacks",
"Punts Inside 20",
"Longest Punt"
],
"athletes": [
{
"athlete": {
"id": "162270",
"uid": "s:20~l:23~a:162270",
"guid": "20e9aea0f62c65970332f5612b99cf9c",
"firstName": "Waylon",
"lastName": "Prather",
"displayName": "Waylon Prather",
"links": [
{
"rel": [
"playercard",
"desktop",
"athlete"
],
"href": "http://www.espn.com/college-football/player/_/id/162270/waylon-prather",
"text": "Player Card"
},
{
"rel": [
"stats",
"desktop",
"athlete"
],
"href": "http://www.espn.com/college-football/player/stats/_/id/162270/waylon-prather",
"text": "Stats"
},
{
"rel": [
"splits",
"desktop",
"athlete"
],
"href": "http://www.espn.com/college-football/player/splits/_/id/162270/waylon-prather",
"text": "Splits"
},
{
"rel": [
"gamelog",
"desktop",
"athlete"
],
"href": "http://www.espn.com/college-football/player/gamelog/_/id/162270/waylon-prather",
"text": "Game Log"
},
{
"rel": [
"news",
"desktop",
"athlete"
],
"href": "http://www.espn.com/college-football/player/news/_/id/162270/waylon-prather",
"text": "News"
},
{
"rel": [
"bio",
"desktop",
"athlete"
],
"href": "http://www.espn.com/college-football/player/bio/_/id/162270/waylon-prather",
"text": "Bio"
},
{
"rel": [
"overview",
"desktop",
"athlete"
],
"href": "http://www.espn.com/college-football/player/_/id/162270/waylon-prather",
"text": "Overview"
}
]
},
"stats": [
"3",
"141",
"47.0",
"0",
"0",
"53"
]
}
],
"totals": [
"3",
"141",
"47.0",
"0",
"0",
"53"
]
}
]
}
]
},
"format": {
"regulation": {
"periods": 4,
"displayName": "Quarter",
"slug": "quarter",
"clock": 900.0
}
},
"gameInfo": {
"venue": {
"id": "3935",
"fullName": "CEFCU Stadium",
"address": {
"city": "San Jose",
"state": "CA",
"zipCode": "95112"
},
"capacity": 30456,
"grass": false,
"images": [
{
"href": "https://a.espncdn.com/i/venues/college-football/day/interior/3935.jpg",
"width": 2000,
"height": 1125,
"alt": "",
"rel": [
"full",
"day",
"interior"
]
}
]
},
"attendance": 0
},
"drives": {},
"leaders": [
{
"team": {
"id": "23",
"uid": "s:20~l:23~t:23",
"displayName": "San Jose State Spartans",
"abbreviation": "SJSU",
"links": [
{
"href": "https://www.espn.com/college-football/team/_/id/23/san-jose-state-spartans",
"text": "Clubhouse"
},
{
"href": "http://www.espn.com/college-football/team/schedule/_/id/23",
"text": "Schedule"
}
],
"logo": "https://a.espncdn.com/i/teamlogos/ncaa/500/23.png"
},
"leaders": [
{
"name": "passingYards",
"displayName": "Passing Yards",
"leaders": [
{
"displayValue": "22-35, 262 YDS, 2 TD, 2 INT",
"athlete": {
"id": "148370",
"uid": "s:20~l:23~a:148370",
"guid": "ed73815ed5c18d38f2b8126ce427175e",
"lastName": "Tafralis",
"fullName": "Adam Tafralis",
"displayName": "Adam Tafralis",
"shortName": "A. Tafralis",
"links": [
{
"rel": [
"playercard",
"desktop",
"athlete"
],
"href": "http://www.espn.com/college-football/player/_/id/148370/adam-tafralis",
"text": "Player Card"
}
],
"jersey": "15 ",
"position": {
"abbreviation": "QB"
}
}
}
]
},
{
"name": "rushingYards",
"displayName": "Rushing Yards",
"leaders": [
{
"displayValue": "11 CAR, 66 YDS, 1 TD",
"athlete": {
"id": "148325",
"uid": "s:20~l:23~a:148325",
"guid": "9c57a95c9656ba9172a9b66436ee7619",
"lastName": "Davis",
"fullName": "Yonus Davis",
"displayName": "Yonus Davis",
"shortName": "Y. Davis",
"links": [
{
"rel": [
"playercard",
"desktop",
"athlete"
],
"href": "http://www.espn.com/college-football/player/_/id/148325/yonus-davis",
"text": "Player Card"
}
],
"jersey": "34 ",
"position": {
"abbreviation": "RB"
}
}
}
]
},
{
"name": "receivingYards",
"displayName": "Receiving Yards",
"leaders": [
{
"displayValue": "6 REC, 93 YDS",
"athlete": {
"id": "162272",
"uid": "s:20~l:23~a:162272",
"guid": "a43f1f125ff0e42ce0eec7ef119cd4e9",
"lastName": "Watje",
"fullName": "Bryan Watje",
"displayName": "Bryan Watje",
"shortName": "B. Watje",
"links": [
{
"rel": [
"playercard",
"desktop",
"athlete"
],
"href": "http://www.espn.com/college-football/player/_/id/162272/bryan-watje",
"text": "Player Card"
}
],
"jersey": "82 ",
"position": {
"abbreviation": "TE"
}
}
}
]
}
]
},
{
"team": {
"id": "62",
"uid": "s:20~l:23~t:62",
"displayName": "Hawai'i Rainbow Warriors",
"abbreviation": "HAW",
"links": [
{
"href": "https://www.espn.com/college-football/team/_/id/62/hawaii-rainbow-warriors",
"text": "Clubhouse"
},
{
"href": "http://www.espn.com/college-football/team/schedule/_/id/62",
"text": "Schedule"
}
],
"logo": "https://a.espncdn.com/i/teamlogos/ncaa/500/62.png"
},
"leaders": [
{
"name": "passingYards",
"displayName": "Passing Yards",
"leaders": [
{
"displayValue": "36-48, 457 YDS, 3 TD, 2 INT",
"athlete": {
"id": "145275",
"uid": "s:20~l:23~a:145275",
"guid": "ad326006f10fbaa668f31e6a4eefda8d",
"lastName": "Brennan",
"fullName": "Colt Brennan",
"displayName": "Colt Brennan",
"shortName": "C. Brennan",
"links": [
{
"rel": [
"playercard",
"desktop",
"athlete"
],
"href": "http://www.espn.com/college-football/player/_/id/145275/colt-brennan",
"text": "Player Card"
}
],
"jersey": "5  ",
"position": {
"abbreviation": "QB"
}
}
}
]
},
{
"name": "rushingYards",
"displayName": "Rushing Yards",
"leaders": [
{
"displayValue": "13 CAR, 39 YDS, 1 TD",
"athlete": {
"id": "128893",
"uid": "s:20~l:23~a:128893",
"guid": "f2f83cdf6c1498867beb1c43eb1f8055",
"lastName": "Ilaoa",
"fullName": "Nate Ilaoa",
"displayName": "Nate Ilaoa",
"shortName": "N. Ilaoa",
"links": [
{
"rel": [
"playercard",
"desktop",
"athlete"
],
"href": "http://www.espn.com/college-football/player/_/id/128893/nate-ilaoa",
"text": "Player Card"
}
],
"jersey": "10 ",
"position": {
"abbreviation": "FB"
}
}
}
]
},
{
"name": "receivingYards",
"displayName": "Receiving Yards",
"leaders": [
{
"displayValue": "11 REC, 104 YDS",
"athlete": {
"id": "170058",
"uid": "s:20~l:23~a:170058",
"guid": "aa46ce22b93837c317a9696261ad4060",
"lastName": "Mock",
"fullName": "Chad Mock",
"displayName": "Chad Mock",
"shortName": "C. Mock",
"links": [
{
"rel": [
"playercard",
"desktop",
"athlete"
],
"href": "http://www.espn.com/college-football/player/_/id/170058/chad-mock",
"text": "Player Card"
}
],
"jersey": "88 ",
"position": {
"abbreviation": "WR"
}
}
}
]
}
]
}
],
"broadcasts": [],
"predictor": {
"header": "Matchup Predictor",
"homeTeam": {
"id": "23"
},
"awayTeam": {
"id": "62"
}
},
"pickcenter": [],
"againstTheSpread": [
{
"team": {
"id": "62",
"uid": "s:20~l:23~t:62",
"displayName": "Hawai'i Rainbow Warriors",
"abbreviation": "HAW",
"links": [
{
"href": "https://www.espn.com/college-football/team/_/id/62/hawaii-rainbow-warriors",
"text": "Clubhouse"
},
{
"href": "http://www.espn.com/college-football/team/schedule/_/id/62",
"text": "Schedule"
}
],
"logo": "https://a.espncdn.com/i/teamlogos/ncaa/500/62.png"
},
"records": []
},
{
"team": {
"id": "23",
"uid": "s:20~l:23~t:23",
"displayName": "San Jose State Spartans",
"abbreviation": "SJSU",
"links": [
{
"href": "https://www.espn.com/college-football/team/_/id/23/san-jose-state-spartans",
"text": "Clubhouse"
},
{
"href": "http://www.espn.com/college-football/team/schedule/_/id/23",
"text": "Schedule"
}
],
"logo": "https://a.espncdn.com/i/teamlogos/ncaa/500/23.png"
},
"records": []
}
],
"odds": [],
"winprobability": [],
"header": {
"id": "252950023",
"uid": "s:20~l:23~e:252950023",
"season": {
"year": 2005,
"type": 2
},
"timeValid": true,
"competitions": [
{
"id": "252950023",
"uid": "s:20~l:23~e:252950023~c:252950023",
"date": "2005-10-22T22:00Z",
"neutralSite": false,
"conferenceCompetition": true,
"boxscoreAvailable": true,
"commentaryAvailable": false,
"liveAvailable": false,
"onWatchESPN": false,
"recent": false,
"boxscoreSource": "full",
"playByPlaySource": "none",
"competitors": [
{
"id": "23",
"uid": "s:20~l:23~t:23",
"order": 0,
"homeAway": "home",
"winner": false,
"team": {
"id": "23",
"uid": "s:20~l:23~t:23",
"location": "San Jose State",
"name": "Spartans",
"nickname": "San Jose State",
"abbreviation": "SJSU",
"displayName": "San Jose State Spartans",
"color": "005893",
"alternateColor": "fdba31",
"logos": [
{
"href": "https://a.espncdn.com/i/teamlogos/ncaa/500/23.png",
"width": 500,
"height": 500,
"alt": "",
"rel": [
"full",
"default"
],
"lastUpdated": "2020-12-16T15:33Z"
},
{
"href": "https://a.espncdn.com/i/teamlogos/ncaa/500-dark/23.png",
"width": 500,
"height": 500,
"alt": "",
"rel": [
"full",
"dark"
],
"lastUpdated": "2020-12-16T15:33Z"
}
],
"links": [
{
"rel": [
"clubhouse",
"desktop",
"team"
],
"href": "https://www.espn.com/college-football/team/_/id/23/san-jose-state-spartans",
"text": "Clubhouse"
}
]
},
"score": "38",
"linescores": [
{
"displayValue": "7"
},
{
"displayValue": "14"
},
{
"displayValue": "7"
},
{
"displayValue": "10"
}
],
"record": [
{
"type": "total",
"summary": "1-6",
"displayValue": "1-6"
},
{
"type": "home",
"summary": "1-2",
"displayValue": "1-2"
},
{
"type": "vsconf",
"summary": "0-4",
"displayValue": "0-4"
}
],
"possession": false
},
{
"id": "62",
"uid": "s:20~l:23~t:62",
"order": 1,
"homeAway": "away",
"winner": true,
"team": {
"id": "62",
"uid": "s:20~l:23~t:62",
"location": "Hawai'i",
"name": "Rainbow Warriors",
"nickname": "Hawaii",
"abbreviation": "HAW",
"displayName": "Hawai'i Rainbow Warriors",
"color": "003420",
"alternateColor": "ffffff",
"logos": [
{
"href": "https://a.espncdn.com/i/teamlogos/ncaa/500/62.png",
"width": 500,
"height": 500,
"alt": "",
"rel": [
"full",
"default"
],
"lastUpdated": "2018-06-05T12:08Z"
},
{
"href": "https://a.espncdn.com/i/teamlogos/ncaa/500-dark/62.png",
"width": 500,
"height": 500,
"alt": "",
"rel": [
"full",
"dark"
],
"lastUpdated": "2018-06-05T12:08Z"
}
],
"links": [
{
"rel": [
"clubhouse",
"desktop",
"team"
],
"href": "https://www.espn.com/college-football/team/_/id/62/hawaii-rainbow-warriors",
"text": "Clubhouse"
}
]
},
"score": "45",
"linescores": [
{
"displayValue": "10"
},
{
"displayValue": "21"
},
{
"displayValue": "7"
},
{
"displayValue": "7"
}
],
"record": [
{
"type": "total",
"summary": "3-4",
"displayValue": "3-4"
},
{
"type": "road",
"summary": "2-2",
"displayValue": "2-2"
},
{
"type": "vsconf",
"summary": "3-2",
"displayValue": "3-2"
}
],
"possession": false
}
],
"status": {
"type": {
"id": "3",
"name": "STATUS_FINAL",
"state": "post",
"completed": true,
"description": "Final",
"detail": "Final",
"shortDetail": "Final"
}
},
"broadcasts": [],
"groups": {
"id": "16",
"name": "Western Athletic Conference",
"abbreviation": "wac",
"shortName": "WAC",
"midsizeName": "WAC"
}
}
],
"links": [
{
"rel": [
"summary",
"desktop",
"event"
],
"href": "https://www.espn.com/college-football/game/_/gameId/252950023",
"text": "Gamecast",
"shortText": "Summary",
"isExternal": false,
"isPremium": false
},
{
"rel": [
"recap",
"desktop",
"event"
],
"href": "https://www.espn.com/college-football/recap?gameId=252950023",
"text": "Recap",
"shortText": "Recap",
"isExternal": false,
"isPremium": false
},
{
"rel": [
"boxscore",
"desktop",
"event"
],
"href": "http://www.espn.com/college-football/boxscore/_/gameId/252950023",
"text": "Box Score",
"shortText": "Box Score",
"isExternal": false,
"isPremium": false
},
{
"rel": [
"teamstats",
"desktop",
"event"
],
"href": "https://www.espn.com/college-football/matchup?gameId=252950023",
"text": "Team Stats",
"shortText": "Team Stats",
"isExternal": false,
"isPremium": false
}
],
"week": 8,
"league": {
"id": "23",
"uid": "s:20~l:23",
"name": "NCAA - Football",
"abbreviation": "NCAAF",
"midsizeName": "NCAA Football",
"slug": "college-football",
"isTournament": false,
"links": [
{
"rel": [
"index",
"desktop",
"league"
],
"href": "https://www.espn.com/college-football/",
"text": "Index"
},
{
"rel": [
"index",
"sportscenter",
"app",
"league"
],
"href": "sportscenter://x-callback-url/showClubhouse?uid=s:20~l:23",
"text": "Index"
},
{
"rel": [
"schedule",
"desktop",
"league"
],
"href": "https://www.espn.com/college-football/schedule",
"text": "Schedule"
},
{
"rel": [
"schedule",
"sportscenter",
"app",
"league"
],
"href": "sportscenter://x-callback-url/showClubhouse?uid=s:20~l:23&section=scores",
"text": "Schedule"
},
{
"rel": [
"standings",
"desktop",
"league"
],
"href": "http://www.espn.com/college-football/standings",
"text": "Standings"
},
{
"rel": [
"standings",
"sportscenter",
"app",
"league"
],
"href": "sportscenter://x-callback-url/showClubhouse?uid=s:20~l:23&section=standings",
"text": "Standings"
},
{
"rel": [
"rankings",
"desktop",
"league"
],
"href": "https://www.espn.com/college-football/rankings",
"text": "Rankings"
},
{
"rel": [
"scores",
"desktop",
"league"
],
"href": "http://www.espn.com/college-football/scoreboard",
"text": "Scores"
},
{
"rel": [
"scores",
"sportscenter",
"app",
"league"
],
"href": "sportscenter://x-callback-url/showClubhouse?uid=s:20~l:23&section=scores",
"text": "Scores"
},
{
"rel": [
"stats",
"desktop",
"league"
],
"href": "http://www.espn.com/college-football/stats",
"text": "Stats"
},
{
"rel": [
"teams",
"desktop",
"league"
],
"href": "http://www.espn.com/college-football/teams",
"text": "Teams"
},
{
"rel": [
"athletes",
"desktop",
"league"
],
"href": "http://www.espn.com/college-football/players",
"text": "Players"
},
{
"rel": [
"injuries",
"desktop",
"league"
],
"href": "https://www.espn.com/college-football/injuries",
"text": "Injuries"
}
]
}
},
"scoringPlays": [],
"videos": [],
"standings": {
"fullViewLink": {
"text": "Full Standings",
"href": "http://www.espn.com/college-football/standings"
},
"groups": [
{
"divisions": [
{
"header": "Mountain West - Mountain",
"standings": {
"entries": [
{
"team": "Utah State",
"link": "https://www.espn.com/college-football/team/_/id/328/utah-state-aggies",
"id": "328",
"uid": "s:20~l:23~t:328",
"stats": [
{
"id": "0",
"name": "overall",
"abbreviation": "overall",
"displayName": "Overall",
"shortDisplayName": "OVER",
"description": "Overall Record",
"type": "total",
"summary": "11-3",
"displayValue": "11-3"
},
{
"id": "9",
"name": "vsConf",
"abbreviation": "CONF",
"displayName": "vs. Conference",
"shortDisplayName": "CONF",
"description": "Conference Record",
"type": "vsconf",
"summary": "6-2",
"displayValue": "6-2"
}
],
"logo": [
{
"href": "https://a.espncdn.com/i/teamlogos/ncaa/500/328.png",
"width": 500,
"height": 500,
"alt": "",
"rel": [
"full",
"default"
],
"lastUpdated": "2018-06-05T12:08Z"
}
]
},
{
"team": "Air Force",
"link": "https://www.espn.com/college-football/team/_/id/2005/air-force-falcons",
"id": "2005",
"uid": "s:20~l:23~t:2005",
"stats": [
{
"id": "0",
"name": "overall",
"abbreviation": "overall",
"displayName": "Overall",
"shortDisplayName": "OVER",
"description": "Overall Record",
"type": "total",
"summary": "10-3",
"displayValue": "10-3"
},
{
"id": "9",
"name": "vsConf",
"abbreviation": "CONF",
"displayName": "vs. Conference",
"shortDisplayName": "CONF",
"description": "Conference Record",
"type": "vsconf",
"summary": "6-2",
"displayValue": "6-2"
}
],
"logo": [
{
"href": "https://a.espncdn.com/i/teamlogos/ncaa/500/2005.png",
"width": 500,
"height": 500,
"alt": "",
"rel": [
"full",
"default"
],
"lastUpdated": "2019-07-31T20:01Z"
}
]
},
{
"team": "Boise State",
"link": "https://www.espn.com/college-football/team/_/id/68/boise-state-broncos",
"id": "68",
"uid": "s:20~l:23~t:68",
"stats": [
{
"id": "0",
"name": "overall",
"abbreviation": "overall",
"displayName": "Overall",
"shortDisplayName": "OVER",
"description": "Overall Record",
"type": "total",
"summary": "7-5",
"displayValue": "7-5"
},
{
"id": "9",
"name": "vsConf",
"abbreviation": "CONF",
"displayName": "vs. Conference",
"shortDisplayName": "CONF",
"description": "Conference Record",
"type": "vsconf",
"summary": "5-3",
"displayValue": "5-3"
}
],
"logo": [
{
"href": "https://a.espncdn.com/i/teamlogos/ncaa/500/68.png",
"width": 500,
"height": 500,
"alt": "",
"rel": [
"full",
"default"
],
"lastUpdated": "2018-06-05T12:08Z"
}
]
},
{
"team": "Wyoming",
"link": "https://www.espn.com/college-football/team/_/id/2751/wyoming-cowboys",
"id": "2751",
"uid": "s:20~l:23~t:2751",
"stats": [
{
"id": "0",
"name": "overall",
"abbreviation": "overall",
"displayName": "Overall",
"shortDisplayName": "OVER",
"description": "Overall Record",
"type": "total",
"summary": "7-6",
"displayValue": "7-6"
},
{
"id": "9",
"name": "vsConf",
"abbreviation": "CONF",
"displayName": "vs. Conference",
"shortDisplayName": "CONF",
"description": "Conference Record",
"type": "vsconf",
"summary": "2-6",
"displayValue": "2-6"
}
],
"logo": [
{
"href": "https://a.espncdn.com/i/teamlogos/ncaa/500/2751.png",
"width": 500,
"height": 500,
"alt": "",
"rel": [
"full",
"default"
],
"lastUpdated": "2019-08-01T15:22Z"
}
]
},
{
"team": "Colorado State",
"link": "https://www.espn.com/college-football/team/_/id/36/colorado-state-rams",
"id": "36",
"uid": "s:20~l:23~t:36",
"stats": [
{
"id": "0",
"name": "overall",
"abbreviation": "overall",
"displayName": "Overall",
"shortDisplayName": "OVER",
"description": "Overall Record",
"type": "total",
"summary": "3-9",
"displayValue": "3-9"
},
{
"id": "9",
"name": "vsConf",
"abbreviation": "CONF",
"displayName": "vs. Conference",
"shortDisplayName": "CONF",
"description": "Conference Record",
"type": "vsconf",
"summary": "2-6",
"displayValue": "2-6"
}
],
"logo": [
{
"href": "https://a.espncdn.com/i/teamlogos/ncaa/500/36.png",
"width": 500,
"height": 500,
"alt": "",
"rel": [
"full",
"default"
],
"lastUpdated": "2018-06-05T12:08Z"
}
]
},
{
"team": "New Mexico",
"link": "https://www.espn.com/college-football/team/_/id/167/new-mexico-lobos",
"id": "167",
"uid": "s:20~l:23~t:167",
"stats": [
{
"id": "0",
"name": "overall",
"abbreviation": "overall",
"displayName": "Overall",
"shortDisplayName": "OVER",
"description": "Overall Record",
"type": "total",
"summary": "3-9",
"displayValue": "3-9"
},
{
"id": "9",
"name": "vsConf",
"abbreviation": "CONF",
"displayName": "vs. Conference",
"shortDisplayName": "CONF",
"description": "Conference Record",
"type": "vsconf",
"summary": "1-7",
"displayValue": "1-7"
}
],
"logo": [
{
"href": "https://a.espncdn.com/i/teamlogos/ncaa/500/167.png",
"width": 500,
"height": 500,
"alt": "",
"rel": [
"full",
"default"
],
"lastUpdated": "2018-06-05T12:08Z"
}
]
}
]
}
},
{
"header": "Mountain West - West",
"standings": {
"entries": [
{
"team": "San Diego State",
"link": "https://www.espn.com/college-football/team/_/id/21/san-diego-state-aztecs",
"id": "21",
"uid": "s:20~l:23~t:21",
"stats": [
{
"id": "0",
"name": "overall",
"abbreviation": "overall",
"displayName": "Overall",
"shortDisplayName": "OVER",
"description": "Overall Record",
"type": "total",
"summary": "12-2",
"displayValue": "12-2"
},
{
"id": "9",
"name": "vsConf",
"abbreviation": "CONF",
"displayName": "vs. Conference",
"shortDisplayName": "CONF",
"description": "Conference Record",
"type": "vsconf",
"summary": "7-1",
"displayValue": "7-1"
}
],
"logo": [
{
"href": "https://a.espncdn.com/i/teamlogos/ncaa/500/21.png",
"width": 500,
"height": 500,
"alt": "",
"rel": [
"full",
"default"
],
"lastUpdated": "2018-06-05T12:08Z"
}
]
},
{
"team": "Fresno State",
"link": "https://www.espn.com/college-football/team/_/id/278/fresno-state-bulldogs",
"id": "278",
"uid": "s:20~l:23~t:278",
"stats": [
{
"id": "0",
"name": "overall",
"abbreviation": "overall",
"displayName": "Overall",
"shortDisplayName": "OVER",
"description": "Overall Record",
"type": "total",
"summary": "10-3",
"displayValue": "10-3"
},
{
"id": "9",
"name": "vsConf",
"abbreviation": "CONF",
"displayName": "vs. Conference",
"shortDisplayName": "CONF",
"description": "Conference Record",
"type": "vsconf",
"summary": "6-2",
"displayValue": "6-2"
}
],
"logo": [
{
"href": "https://a.espncdn.com/i/teamlogos/ncaa/500/278.png",
"width": 500,
"height": 500,
"alt": "",
"rel": [
"full",
"default"
],
"lastUpdated": "2018-06-05T12:08Z"
}
]
},
{
"team": "Nevada",
"link": "https://www.espn.com/college-football/team/_/id/2440/nevada-wolf-pack",
"id": "2440",
"uid": "s:20~l:23~t:2440",
"stats": [
{
"id": "0",
"name": "overall",
"abbreviation": "overall",
"displayName": "Overall",
"shortDisplayName": "OVER",
"description": "Overall Record",
"type": "total",
"summary": "8-5",
"displayValue": "8-5"
},
{
"id": "9",
"name": "vsConf",
"abbreviation": "CONF",
"displayName": "vs. Conference",
"shortDisplayName": "CONF",
"description": "Conference Record",
"type": "vsconf",
"summary": "5-3",
"displayValue": "5-3"
}
],
"logo": [
{
"href": "https://a.espncdn.com/i/teamlogos/ncaa/500/2440.png",
"width": 500,
"height": 500,
"alt": "",
"rel": [
"full",
"default"
],
"lastUpdated": "2018-06-05T12:08Z"
}
]
},
{
"team": "San Jos\u00e9 State",
"link": "https://www.espn.com/college-football/team/_/id/23/san-jose-state-spartans",
"id": "23",
"uid": "s:20~l:23~t:23",
"stats": [
{
"id": "0",
"name": "overall",
"abbreviation": "overall",
"displayName": "Overall",
"shortDisplayName": "OVER",
"description": "Overall Record",
"type": "total",
"summary": "5-7",
"displayValue": "5-7"
},
{
"id": "9",
"name": "vsConf",
"abbreviation": "CONF",
"displayName": "vs. Conference",
"shortDisplayName": "CONF",
"description": "Conference Record",
"type": "vsconf",
"summary": "3-5",
"displayValue": "3-5"
}
],
"logo": [
{
"href": "https://a.espncdn.com/i/teamlogos/ncaa/500/23.png",
"width": 500,
"height": 500,
"alt": "",
"rel": [
"full",
"default"
],
"lastUpdated": "2020-12-16T15:33Z"
}
]
},
{
"team": "Hawai'i",
"link": "https://www.espn.com/college-football/team/_/id/62/hawaii-rainbow-warriors",
"id": "62",
"uid": "s:20~l:23~t:62",
"stats": [
{
"id": "0",
"name": "overall",
"abbreviation": "overall",
"displayName": "Overall",
"shortDisplayName": "OVER",
"description": "Overall Record",
"type": "total",
"summary": "6-7",
"displayValue": "6-7"
},
{
"id": "9",
"name": "vsConf",
"abbreviation": "CONF",
"displayName": "vs. Conference",
"shortDisplayName": "CONF",
"description": "Conference Record",
"type": "vsconf",
"summary": "3-5",
"displayValue": "3-5"
}
],
"logo": [
{
"href": "https://a.espncdn.com/i/teamlogos/ncaa/500/62.png",
"width": 500,
"height": 500,
"alt": "",
"rel": [
"full",
"default"
],
"lastUpdated": "2018-06-05T12:08Z"
}
]
},
{
"team": "UNLV",
"link": "https://www.espn.com/college-football/team/_/id/2439/unlv-rebels",
"id": "2439",
"uid": "s:20~l:23~t:2439",
"stats": [
{
"id": "0",
"name": "overall",
"abbreviation": "overall",
"displayName": "Overall",
"shortDisplayName": "OVER",
"description": "Overall Record",
"type": "total",
"summary": "2-10",
"displayValue": "2-10"
},
{
"id": "9",
"name": "vsConf",
"abbreviation": "CONF",
"displayName": "vs. Conference",
"shortDisplayName": "CONF",
"description": "Conference Record",
"type": "vsconf",
"summary": "2-6",
"displayValue": "2-6"
}
],
"logo": [
{
"href": "https://a.espncdn.com/i/teamlogos/ncaa/500/2439.png",
"width": 500,
"height": 500,
"alt": "",
"rel": [
"full",
"default"
],
"lastUpdated": "2018-06-05T12:08Z"
}
]
}
]
}
}
],
"header": "2021 Mountain West Conference Standings",
"href": "https://www.espn.com/college-football/standings/_/group/17/view/fbs-i-a"
}
]
}
}