{
"boxscore": {
"teams": [
{
"team": {
"id": "2241",
"uid": "s:20~l:23~t:2241",
"slug": "gardner-webb-bulldogs",
"location": "Gardner-Webb",
"name": "Bulldogs",
"abbreviation": "WEBB",
"displayName": "Gardner-Webb Bulldogs",
"shortDisplayName": "Bulldogs",
"color": "c12535",
"alternateColor": "909090",
"logo": "https://a.espncdn.com/i/teamlogos/ncaa/500/2241.png"
},
"statistics": [
{
"name": "firstDowns",
"displayValue": "12",
"label": "1st Downs"
},
{
"name": "thirdDownEff",
"displayValue": "4-14",
"label": "3rd down efficiency"
},
{
"name": "fourthDownEff",
"displayValue": "0-2",
"label": "4th down efficiency"
},
{
"name": "totalYards",
"displayValue": "215",
"label": "Total Yards"
},
{
"name": "netPassingYards",
"displayValue": "179",
"label": "Passing"
},
{
"name": "completionAttempts",
"displayValue": "17-31",
"label": "Comp-Att"
},
{
"name": "yardsPerPass",
"displayValue": "5.3",
"label": "Yards per pass"
},
{
"name": "rushingYards",
"displayValue": "51",
"label": "Rushing"
},
{
"name": "rushingAttempts",
"displayValue": "25",
"label": "Rushing Attempts"
},
{
"name": "yardsPerRushAttempt",
"displayValue": "2.0",
"label": "Yards per rush"
},
{
"name": "totalPenaltiesYards",
"displayValue": "8-60",
"label": "Penalties"
},
{
"name": "turnovers",
"displayValue": "1",
"label": "Turnovers"
},
{
"name": "fumblesLost",
"displayValue": "1",
"label": "Fumbles lost"
},
{
"name": "interceptions",
"displayValue": "0",
"label": "Interceptions thrown"
},
{
"name": "possessionTime",
"displayValue": "16:20",
"label": "Possession"
}
]
},
{
"team": {
"id": "2084",
"uid": "s:20~l:23~t:2084",
"slug": "buffalo-bulls",
"location": "Buffalo",
"name": "Bulls",
"abbreviation": "BUFF",
"displayName": "Buffalo Bulls",
"shortDisplayName": "Bulls",
"color": "041A9B",
"alternateColor": "ebebeb",
"logo": "https://a.espncdn.com/i/teamlogos/ncaa/500/2084.png"
},
"statistics": [
{
"name": "firstDowns",
"displayValue": "29",
"label": "1st Downs"
},
{
"name": "thirdDownEff",
"displayValue": "9-13",
"label": "3rd down efficiency"
},
{
"name": "fourthDownEff",
"displayValue": "1-2",
"label": "4th down efficiency"
},
{
"name": "totalYards",
"displayValue": "508",
"label": "Total Yards"
},
{
"name": "netPassingYards",
"displayValue": "269",
"label": "Passing"
},
{
"name": "completionAttempts",
"displayValue": "19-26",
"label": "Comp-Att"
},
{
"name": "yardsPerPass",
"displayValue": "9.9",
"label": "Yards per pass"
},
{
"name": "rushingYards",
"displayValue": "250",
"label": "Rushing"
},
{
"name": "rushingAttempts",
"displayValue": "47",
"label": "Rushing Attempts"
},
{
"name": "yardsPerRushAttempt",
"displayValue": "5.3",
"label": "Yards per rush"
},
{
"name": "totalPenaltiesYards",
"displayValue": "5-63",
"label": "Penalties"
},
{
"name": "turnovers",
"displayValue": "0",
"label": "Turnovers"
},
{
"name": "fumblesLost",
"displayValue": "0",
"label": "Fumbles lost"
},
{
"name": "interceptions",
"displayValue": "0",
"label": "Interceptions thrown"
},
{
"name": "possessionTime",
"displayValue": "20:13",
"label": "Possession"
}
]
}
],
"players": [
{
"team": {
"id": "2241",
"uid": "s:20~l:23~t:2241",
"slug": "gardner-webb-bulldogs",
"location": "Gardner-Webb",
"name": "Bulldogs",
"abbreviation": "WEBB",
"displayName": "Gardner-Webb Bulldogs",
"shortDisplayName": "Bulldogs",
"color": "c12535",
"alternateColor": "909090",
"logo": "https://a.espncdn.com/i/teamlogos/ncaa/500/2241.png"
},
"statistics": [
{
"name": "passing",
"keys": [
"completions/passingAttempts",
"passingYards",
"yardsPerPassAttempt",
"passingTouchdowns",
"interceptions",
"adjQBR"
],
"text": "Gardner-Webb Passing",
"labels": [
"C/ATT",
"YDS",
"AVG",
"TD",
"INT",
"QBR"
],
"descriptions": [
"Completions/Attempts",
"Yards",
"Yards Per Pass Attempt",
"Touchdowns",
"Interceptions",
"Adjusted QBR"
],
"athletes": [
{
"athlete": {
"id": "186410",
"uid": "s:20~l:23~a:186410",
"guid": "88e458a5745a7e264c1ae083705da423",
"firstName": "Stan",
"lastName": "Doolittle",
"displayName": "Stan Doolittle",
"links": [
{
"rel": [
"playercard",
"desktop",
"athlete"
],
"href": "http://www.espn.com/college-football/player/_/id/186410/stan-doolittle",
"text": "Player Card"
},
{
"rel": [
"stats",
"desktop",
"athlete"
],
"href": "http://www.espn.com/college-football/player/stats/_/id/186410/stan-doolittle",
"text": "Stats"
},
{
"rel": [
"splits",
"desktop",
"athlete"
],
"href": "http://www.espn.com/college-football/player/splits/_/id/186410/stan-doolittle",
"text": "Splits"
},
{
"rel": [
"gamelog",
"desktop",
"athlete"
],
"href": "http://www.espn.com/college-football/player/gamelog/_/id/186410/stan-doolittle",
"text": "Game Log"
},
{
"rel": [
"news",
"desktop",
"athlete"
],
"href": "http://www.espn.com/college-football/player/news/_/id/186410/stan-doolittle",
"text": "News"
},
{
"rel": [
"bio",
"desktop",
"athlete"
],
"href": "http://www.espn.com/college-football/player/bio/_/id/186410/stan-doolittle",
"text": "Bio"
},
{
"rel": [
"overview",
"desktop",
"athlete"
],
"href": "http://www.espn.com/college-football/player/_/id/186410/stan-doolittle",
"text": "Overview"
}
]
},
"stats": [
"16/29",
"159",
"5.5",
"0",
"0",
"--"
]
},
{
"athlete": {
"id": "476862",
"uid": "s:20~l:23~a:476862",
"guid": "abe1af56149e2a20abbd2a706de946c5",
"firstName": "John",
"lastName": "Rock",
"displayName": "John Rock",
"links": [
{
"rel": [
"playercard",
"desktop",
"athlete"
],
"href": "http://www.espn.com/college-football/player/_/id/476862/john-rock",
"text": "Player Card"
},
{
"rel": [
"stats",
"desktop",
"athlete"
],
"href": "http://www.espn.com/college-football/player/stats/_/id/476862/john-rock",
"text": "Stats"
},
{
"rel": [
"splits",
"desktop",
"athlete"
],
"href": "http://www.espn.com/college-football/player/splits/_/id/476862/john-rock",
"text": "Splits"
},
{
"rel": [
"gamelog",
"desktop",
"athlete"
],
"href": "http://www.espn.com/college-football/player/gamelog/_/id/476862/john-rock",
"text": "Game Log"
},
{
"rel": [
"news",
"desktop",
"athlete"
],
"href": "http://www.espn.com/college-football/player/news/_/id/476862/john-rock",
"text": "News"
},
{
"rel": [
"bio",
"desktop",
"athlete"
],
"href": "http://www.espn.com/college-football/player/bio/_/id/476862/john-rock",
"text": "Bio"
},
{
"rel": [
"overview",
"desktop",
"athlete"
],
"href": "http://www.espn.com/college-football/player/_/id/476862/john-rock",
"text": "Overview"
}
]
},
"stats": [
"1/2",
"5",
"2.5",
"0",
"0",
"--"
]
}
],
"totals": [
"17/31",
"179",
"5.3",
"0",
"0",
"--"
]
},
{
"name": "rushing",
"keys": [
"rushingAttempts",
"rushingYards",
"yardsPerRushAttempt",
"rushingTouchdowns",
"longRushing"
],
"text": "Gardner-Webb Rushing",
"labels": [
"CAR",
"YDS",
"AVG",
"TD",
"LONG"
],
"descriptions": [
"Rushing Attempts",
"Yards",
"Yards Per Rushing Attempt",
"Touchdowns",
"Longest Run"
],
"athletes": [
{
"athlete": {
"id": "186410",
"uid": "s:20~l:23~a:186410",
"guid": "88e458a5745a7e264c1ae083705da423",
"firstName": "Stan",
"lastName": "Doolittle",
"displayName": "Stan Doolittle",
"links": [
{
"rel": [
"playercard",
"desktop",
"athlete"
],
"href": "http://www.espn.com/college-football/player/_/id/186410/stan-doolittle",
"text": "Player Card"
},
{
"rel": [
"stats",
"desktop",
"athlete"
],
"href": "http://www.espn.com/college-football/player/stats/_/id/186410/stan-doolittle",
"text": "Stats"
},
{
"rel": [
"splits",
"desktop",
"athlete"
],
"href": "http://www.espn.com/college-football/player/splits/_/id/186410/stan-doolittle",
"text": "Splits"
},
{
"rel": [
"gamelog",
"desktop",
"athlete"
],
"href": "http://www.espn.com/college-football/player/gamelog/_/id/186410/stan-doolittle",
"text": "Game Log"
},
{
"rel": [
"news",
"desktop",
"athlete"
],
"href": "http://www.espn.com/college-football/player/news/_/id/186410/stan-doolittle",
"text": "News"
},
{
"rel": [
"bio",
"desktop",
"athlete"
],
"href": "http://www.espn.com/college-football/player/bio/_/id/186410/stan-doolittle",
"text": "Bio"
},
{
"rel": [
"overview",
"desktop",
"athlete"
],
"href": "http://www.espn.com/college-football/player/_/id/186410/stan-doolittle",
"text": "Overview"
}
]
},
"stats": [
"12",
"18",
"1.5",
"0",
"14"
]
},
{
"athlete": {
"id": "186411",
"uid": "s:20~l:23~a:186411",
"guid": "4e0c7bc606ee8b09679ee7529db15822",
"firstName": "Phillip",
"lastName": "Peoples",
"displayName": "Phillip Peoples",
"links": [
{
"rel": [
"playercard",
"desktop",
"athlete"
],
"href": "http://www.espn.com/college-football/player/_/id/186411/phillip-peoples",
"text": "Player Card"
},
{
"rel": [
"stats",
"desktop",
"athlete"
],
"href": "http://www.espn.com/college-football/player/stats/_/id/186411/phillip-peoples",
"text": "Stats"
},
{
"rel": [
"splits",
"desktop",
"athlete"
],
"href": "http://www.espn.com/college-football/player/splits/_/id/186411/phillip-peoples",
"text": "Splits"
},
{
"rel": [
"gamelog",
"desktop",
"athlete"
],
"href": "http://www.espn.com/college-football/player/gamelog/_/id/186411/phillip-peoples",
"text": "Game Log"
},
{
"rel": [
"news",
"desktop",
"athlete"
],
"href": "http://www.espn.com/college-football/player/news/_/id/186411/phillip-peoples",
"text": "News"
},
{
"rel": [
"bio",
"desktop",
"athlete"
],
"href": "http://www.espn.com/college-football/player/bio/_/id/186411/phillip-peoples",
"text": "Bio"
},
{
"rel": [
"overview",
"desktop",
"athlete"
],
"href": "http://www.espn.com/college-football/player/_/id/186411/phillip-peoples",
"text": "Overview"
}
]
},
"stats": [
"7",
"15",
"2.1",
"0",
"7"
]
},
{
"athlete": {
"id": "233452",
"uid": "s:20~l:23~a:233452",
"guid": "006900211259e173c1d14ea6b0abc58f",
"firstName": "Patrick",
"lastName": "Hall",
"displayName": "Patrick Hall",
"links": [
{
"rel": [
"playercard",
"desktop",
"athlete"
],
"href": "http://www.espn.com/college-football/player/_/id/233452/patrick-hall",
"text": "Player Card"
},
{
"rel": [
"stats",
"desktop",
"athlete"
],
"href": "http://www.espn.com/college-football/player/stats/_/id/233452/patrick-hall",
"text": "Stats"
},
{
"rel": [
"splits",
"desktop",
"athlete"
],
"href": "http://www.espn.com/college-football/player/splits/_/id/233452/patrick-hall",
"text": "Splits"
},
{
"rel": [
"gamelog",
"desktop",
"athlete"
],
"href": "http://www.espn.com/college-football/player/gamelog/_/id/233452/patrick-hall",
"text": "Game Log"
},
{
"rel": [
"news",
"desktop",
"athlete"
],
"href": "http://www.espn.com/college-football/player/news/_/id/233452/patrick-hall",
"text": "News"
},
{
"rel": [
"bio",
"desktop",
"athlete"
],
"href": "http://www.espn.com/college-football/player/bio/_/id/233452/patrick-hall",
"text": "Bio"
},
{
"rel": [
"overview",
"desktop",
"athlete"
],
"href": "http://www.espn.com/college-football/player/_/id/233452/patrick-hall",
"text": "Overview"
}
]
},
"stats": [
"2",
"13",
"6.5",
"0",
"9"
]
},
{
"athlete": {
"id": "186417",
"uid": "s:20~l:23~a:186417",
"guid": "faf15124a5011abfc47213c645164bb1",
"firstName": "Brandon",
"lastName": "Jackson",
"displayName": "Brandon Jackson",
"links": [
{
"rel": [
"playercard",
"desktop",
"athlete"
],
"href": "http://www.espn.com/college-football/player/_/id/186417/brandon-jackson",
"text": "Player Card"
},
{
"rel": [
"stats",
"desktop",
"athlete"
],
"href": "http://www.espn.com/college-football/player/stats/_/id/186417/brandon-jackson",
"text": "Stats"
},
{
"rel": [
"splits",
"desktop",
"athlete"
],
"href": "http://www.espn.com/college-football/player/splits/_/id/186417/brandon-jackson",
"text": "Splits"
},
{
"rel": [
"gamelog",
"desktop",
"athlete"
],
"href": "http://www.espn.com/college-football/player/gamelog/_/id/186417/brandon-jackson",
"text": "Game Log"
},
{
"rel": [
"news",
"desktop",
"athlete"
],
"href": "http://www.espn.com/college-football/player/news/_/id/186417/brandon-jackson",
"text": "News"
},
{
"rel": [
"bio",
"desktop",
"athlete"
],
"href": "http://www.espn.com/college-football/player/bio/_/id/186417/brandon-jackson",
"text": "Bio"
},
{
"rel": [
"overview",
"desktop",
"athlete"
],
"href": "http://www.espn.com/college-football/player/_/id/186417/brandon-jackson",
"text": "Overview"
}
]
},
"stats": [
"1",
"4",
"4.0",
"0",
"4"
]
},
{
"athlete": {
"id": "476862",
"uid": "s:20~l:23~a:476862",
"guid": "abe1af56149e2a20abbd2a706de946c5",
"firstName": "John",
"lastName": "Rock",
"displayName": "John Rock",
"links": [
{
"rel": [
"playercard",
"desktop",
"athlete"
],
"href": "http://www.espn.com/college-football/player/_/id/476862/john-rock",
"text": "Player Card"
},
{
"rel": [
"stats",
"desktop",
"athlete"
],
"href": "http://www.espn.com/college-football/player/stats/_/id/476862/john-rock",
"text": "Stats"
},
{
"rel": [
"splits",
"desktop",
"athlete"
],
"href": "http://www.espn.com/college-football/player/splits/_/id/476862/john-rock",
"text": "Splits"
},
{
"rel": [
"gamelog",
"desktop",
"athlete"
],
"href": "http://www.espn.com/college-football/player/gamelog/_/id/476862/john-rock",
"text": "Game Log"
},
{
"rel": [
"news",
"desktop",
"athlete"
],
"href": "http://www.espn.com/college-football/player/news/_/id/476862/john-rock",
"text": "News"
},
{
"rel": [
"bio",
"desktop",
"athlete"
],
"href": "http://www.espn.com/college-football/player/bio/_/id/476862/john-rock",
"text": "Bio"
},
{
"rel": [
"overview",
"desktop",
"athlete"
],
"href": "http://www.espn.com/college-football/player/_/id/476862/john-rock",
"text": "Overview"
}
]
},
"stats": [
"1",
"3",
"3.0",
"0",
"3"
]
},
{
"athlete": {
"id": "476856",
"uid": "s:20~l:23~a:476856",
"guid": "e9222d6f076fd9816cf696064f323f8d",
"firstName": "Kenny",
"lastName": "Little",
"displayName": "Kenny Little",
"links": [
{
"rel": [
"playercard",
"desktop",
"athlete"
],
"href": "http://www.espn.com/college-football/player/_/id/476856/kenny-little",
"text": "Player Card"
},
{
"rel": [
"stats",
"desktop",
"athlete"
],
"href": "http://www.espn.com/college-football/player/stats/_/id/476856/kenny-little",
"text": "Stats"
},
{
"rel": [
"splits",
"desktop",
"athlete"
],
"href": "http://www.espn.com/college-football/player/splits/_/id/476856/kenny-little",
"text": "Splits"
},
{
"rel": [
"gamelog",
"desktop",
"athlete"
],
"href": "http://www.espn.com/college-football/player/gamelog/_/id/476856/kenny-little",
"text": "Game Log"
},
{
"rel": [
"news",
"desktop",
"athlete"
],
"href": "http://www.espn.com/college-football/player/news/_/id/476856/kenny-little",
"text": "News"
},
{
"rel": [
"bio",
"desktop",
"athlete"
],
"href": "http://www.espn.com/college-football/player/bio/_/id/476856/kenny-little",
"text": "Bio"
},
{
"rel": [
"overview",
"desktop",
"athlete"
],
"href": "http://www.espn.com/college-football/player/_/id/476856/kenny-little",
"text": "Overview"
}
]
},
"stats": [
"2",
"-2",
"-1.0",
"0",
"0"
]
}
],
"totals": [
"25",
"51",
"2.0",
"0",
"14"
]
},
{
"name": "receiving",
"keys": [
"receptions",
"receivingYards",
"yardsPerReception",
"receivingTouchdowns",
"longReception"
],
"text": "Gardner-Webb Receiving",
"labels": [
"REC",
"YDS",
"AVG",
"TD",
"LONG"
],
"descriptions": [
"Receptions",
"Yards",
"Yards Per Reception",
"Touchdowns",
"Longest Reception"
],
"athletes": [
{
"athlete": {
"id": "233464",
"uid": "s:20~l:23~a:233464",
"guid": "9fde99a6026597f7b80a0baf7ff6fac3",
"firstName": "Marquis",
"lastName": "Sanders",
"displayName": "Marquis Sanders",
"links": [
{
"rel": [
"playercard",
"desktop",
"athlete"
],
"href": "http://www.espn.com/college-football/player/_/id/233464/marquis-sanders",
"text": "Player Card"
},
{
"rel": [
"stats",
"desktop",
"athlete"
],
"href": "http://www.espn.com/college-football/player/stats/_/id/233464/marquis-sanders",
"text": "Stats"
},
{
"rel": [
"splits",
"desktop",
"athlete"
],
"href": "http://www.espn.com/college-football/player/splits/_/id/233464/marquis-sanders",
"text": "Splits"
},
{
"rel": [
"gamelog",
"desktop",
"athlete"
],
"href": "http://www.espn.com/college-football/player/gamelog/_/id/233464/marquis-sanders",
"text": "Game Log"
},
{
"rel": [
"news",
"desktop",
"athlete"
],
"href": "http://www.espn.com/college-football/player/news/_/id/233464/marquis-sanders",
"text": "News"
},
{
"rel": [
"bio",
"desktop",
"athlete"
],
"href": "http://www.espn.com/college-football/player/bio/_/id/233464/marquis-sanders",
"text": "Bio"
},
{
"rel": [
"overview",
"desktop",
"athlete"
],
"href": "http://www.espn.com/college-football/player/_/id/233464/marquis-sanders",
"text": "Overview"
}
]
},
"stats": [
"5",
"74",
"14.8",
"0",
"23"
]
},
{
"athlete": {
"id": "187912",
"uid": "s:20~l:23~a:187912",
"guid": "0f25457a6c2d3bf068a3d46e380bf1f7",
"firstName": "Nick",
"lastName": "Melton",
"displayName": "Nick Melton",
"links": [
{
"rel": [
"playercard",
"desktop",
"athlete"
],
"href": "http://www.espn.com/college-football/player/_/id/187912/nick-melton",
"text": "Player Card"
},
{
"rel": [
"stats",
"desktop",
"athlete"
],
"href": "http://www.espn.com/college-football/player/stats/_/id/187912/nick-melton",
"text": "Stats"
},
{
"rel": [
"splits",
"desktop",
"athlete"
],
"href": "http://www.espn.com/college-football/player/splits/_/id/187912/nick-melton",
"text": "Splits"
},
{
"rel": [
"gamelog",
"desktop",
"athlete"
],
"href": "http://www.espn.com/college-football/player/gamelog/_/id/187912/nick-melton",
"text": "Game Log"
},
{
"rel": [
"news",
"desktop",
"athlete"
],
"href": "http://www.espn.com/college-football/player/news/_/id/187912/nick-melton",
"text": "News"
},
{
"rel": [
"bio",
"desktop",
"athlete"
],
"href": "http://www.espn.com/college-football/player/bio/_/id/187912/nick-melton",
"text": "Bio"
},
{
"rel": [
"overview",
"desktop",
"athlete"
],
"href": "http://www.espn.com/college-football/player/_/id/187912/nick-melton",
"text": "Overview"
}
]
},
"stats": [
"4",
"31",
"7.8",
"0",
"12"
]
},
{
"athlete": {
"id": "233461",
"uid": "s:20~l:23~a:233461",
"guid": "209eba1071affff6b94a7a4c8aead3c5",
"firstName": "Tyson",
"lastName": "Petty",
"displayName": "Tyson Petty",
"links": [
{
"rel": [
"playercard",
"desktop",
"athlete"
],
"href": "http://www.espn.com/college-football/player/_/id/233461/tyson-petty",
"text": "Player Card"
},
{
"rel": [
"stats",
"desktop",
"athlete"
],
"href": "http://www.espn.com/college-football/player/stats/_/id/233461/tyson-petty",
"text": "Stats"
},
{
"rel": [
"splits",
"desktop",
"athlete"
],
"href": "http://www.espn.com/college-football/player/splits/_/id/233461/tyson-petty",
"text": "Splits"
},
{
"rel": [
"gamelog",
"desktop",
"athlete"
],
"href": "http://www.espn.com/college-football/player/gamelog/_/id/233461/tyson-petty",
"text": "Game Log"
},
{
"rel": [
"news",
"desktop",
"athlete"
],
"href": "http://www.espn.com/college-football/player/news/_/id/233461/tyson-petty",
"text": "News"
},
{
"rel": [
"bio",
"desktop",
"athlete"
],
"href": "http://www.espn.com/college-football/player/bio/_/id/233461/tyson-petty",
"text": "Bio"
},
{
"rel": [
"overview",
"desktop",
"athlete"
],
"href": "http://www.espn.com/college-football/player/_/id/233461/tyson-petty",
"text": "Overview"
}
]
},
"stats": [
"2",
"18",
"9.0",
"0",
"12"
]
},
{
"athlete": {
"id": "475442",
"uid": "s:20~l:23~a:475442",
"guid": "8a0c76b016bc7be6f5c55b5a74f5633c",
"firstName": "James",
"lastName": "Perry III",
"displayName": "James Perry III",
"links": [
{
"rel": [
"playercard",
"desktop",
"athlete"
],
"href": "http://www.espn.com/college-football/player/_/id/475442/james-perry-iii",
"text": "Player Card"
},
{
"rel": [
"stats",
"desktop",
"athlete"
],
"href": "http://www.espn.com/college-football/player/stats/_/id/475442/james-perry-iii",
"text": "Stats"
},
{
"rel": [
"splits",
"desktop",
"athlete"
],
"href": "http://www.espn.com/college-football/player/splits/_/id/475442/james-perry-iii",
"text": "Splits"
},
{
"rel": [
"gamelog",
"desktop",
"athlete"
],
"href": "http://www.espn.com/college-football/player/gamelog/_/id/475442/james-perry-iii",
"text": "Game Log"
},
{
"rel": [
"news",
"desktop",
"athlete"
],
"href": "http://www.espn.com/college-football/player/news/_/id/475442/james-perry-iii",
"text": "News"
},
{
"rel": [
"bio",
"desktop",
"athlete"
],
"href": "http://www.espn.com/college-football/player/bio/_/id/475442/james-perry-iii",
"text": "Bio"
},
{
"rel": [
"overview",
"desktop",
"athlete"
],
"href": "http://www.espn.com/college-football/player/_/id/475442/james-perry-iii",
"text": "Overview"
}
]
},
"stats": [
"2",
"18",
"9.0",
"0",
"13"
]
},
{
"athlete": {
"id": "186411",
"uid": "s:20~l:23~a:186411",
"guid": "4e0c7bc606ee8b09679ee7529db15822",
"firstName": "Phillip",
"lastName": "Peoples",
"displayName": "Phillip Peoples",
"links": [
{
"rel": [
"playercard",
"desktop",
"athlete"
],
"href": "http://www.espn.com/college-football/player/_/id/186411/phillip-peoples",
"text": "Player Card"
},
{
"rel": [
"stats",
"desktop",
"athlete"
],
"href": "http://www.espn.com/college-football/player/stats/_/id/186411/phillip-peoples",
"text": "Stats"
},
{
"rel": [
"splits",
"desktop",
"athlete"
],
"href": "http://www.espn.com/college-football/player/splits/_/id/186411/phillip-peoples",
"text": "Splits"
},
{
"rel": [
"gamelog",
"desktop",
"athlete"
],
"href": "http://www.espn.com/college-football/player/gamelog/_/id/186411/phillip-peoples",
"text": "Game Log"
},
{
"rel": [
"news",
"desktop",
"athlete"
],
"href": "http://www.espn.com/college-football/player/news/_/id/186411/phillip-peoples",
"text": "News"
},
{
"rel": [
"bio",
"desktop",
"athlete"
],
"href": "http://www.espn.com/college-football/player/bio/_/id/186411/phillip-peoples",
"text": "Bio"
},
{
"rel": [
"overview",
"desktop",
"athlete"
],
"href": "http://www.espn.com/college-football/player/_/id/186411/phillip-peoples",
"text": "Overview"
}
]
},
"stats": [
"2",
"13",
"6.5",
"0",
"7"
]
},
{
"athlete": {
"id": "233456",
"uid": "s:20~l:23~a:233456",
"guid": "a5ed2b45341b285e4ce4c515b9f89317",
"firstName": "Lyndon",
"lastName": "Leslie",
"displayName": "Lyndon Leslie",
"links": [
{
"rel": [
"playercard",
"desktop",
"athlete"
],
"href": "http://www.espn.com/college-football/player/_/id/233456/lyndon-leslie",
"text": "Player Card"
},
{
"rel": [
"stats",
"desktop",
"athlete"
],
"href": "http://www.espn.com/college-football/player/stats/_/id/233456/lyndon-leslie",
"text": "Stats"
},
{
"rel": [
"splits",
"desktop",
"athlete"
],
"href": "http://www.espn.com/college-football/player/splits/_/id/233456/lyndon-leslie",
"text": "Splits"
},
{
"rel": [
"gamelog",
"desktop",
"athlete"
],
"href": "http://www.espn.com/college-football/player/gamelog/_/id/233456/lyndon-leslie",
"text": "Game Log"
},
{
"rel": [
"news",
"desktop",
"athlete"
],
"href": "http://www.espn.com/college-football/player/news/_/id/233456/lyndon-leslie",
"text": "News"
},
{
"rel": [
"bio",
"desktop",
"athlete"
],
"href": "http://www.espn.com/college-football/player/bio/_/id/233456/lyndon-leslie",
"text": "Bio"
},
{
"rel": [
"overview",
"desktop",
"athlete"
],
"href": "http://www.espn.com/college-football/player/_/id/233456/lyndon-leslie",
"text": "Overview"
}
]
},
"stats": [
"1",
"11",
"11.0",
"0",
"11"
]
},
{
"athlete": {
"id": "186417",
"uid": "s:20~l:23~a:186417",
"guid": "faf15124a5011abfc47213c645164bb1",
"firstName": "Brandon",
"lastName": "Jackson",
"displayName": "Brandon Jackson",
"links": [
{
"rel": [
"playercard",
"desktop",
"athlete"
],
"href": "http://www.espn.com/college-football/player/_/id/186417/brandon-jackson",
"text": "Player Card"
},
{
"rel": [
"stats",
"desktop",
"athlete"
],
"href": "http://www.espn.com/college-football/player/stats/_/id/186417/brandon-jackson",
"text": "Stats"
},
{
"rel": [
"splits",
"desktop",
"athlete"
],
"href": "http://www.espn.com/college-football/player/splits/_/id/186417/brandon-jackson",
"text": "Splits"
},
{
"rel": [
"gamelog",
"desktop",
"athlete"
],
"href": "http://www.espn.com/college-football/player/gamelog/_/id/186417/brandon-jackson",
"text": "Game Log"
},
{
"rel": [
"news",
"desktop",
"athlete"
],
"href": "http://www.espn.com/college-football/player/news/_/id/186417/brandon-jackson",
"text": "News"
},
{
"rel": [
"bio",
"desktop",
"athlete"
],
"href": "http://www.espn.com/college-football/player/bio/_/id/186417/brandon-jackson",
"text": "Bio"
},
{
"rel": [
"overview",
"desktop",
"athlete"
],
"href": "http://www.espn.com/college-football/player/_/id/186417/brandon-jackson",
"text": "Overview"
}
]
},
"stats": [
"1",
"-1",
"-1.0",
"0",
"0"
]
}
],
"totals": [
"17",
"164",
"9.6",
"0",
"23"
]
},
{
"name": "interceptions",
"keys": [
"interceptions",
"interceptionYards",
"interceptionTouchdowns"
],
"text": "Gardner-Webb Interceptions",
"labels": [
"INT",
"YDS",
"TD"
],
"descriptions": [
"Interceptions",
"Yards",
"Touchdowns"
],
"athletes": [],
"totals": []
},
{
"name": "kickReturns",
"keys": [
"kickReturns",
"kickReturnYards",
"yardsPerKickReturn",
"longKickReturn",
"kickReturnTouchdowns"
],
"text": "Gardner-Webb Kick Returns",
"labels": [
"NO",
"YDS",
"AVG",
"LONG",
"TD"
],
"descriptions": [
"Kick Returns",
"Yards",
"Yards Per Kick Return",
"Longest Kick Return",
"Touchdowns"
],
"athletes": [
{
"athlete": {
"id": "186421",
"uid": "s:20~l:23~a:186421",
"guid": "486cbb438f4a6adc30fdda611f2dff1c",
"firstName": "David",
"lastName": "Montgomery",
"displayName": "David Montgomery",
"links": [
{
"rel": [
"playercard",
"desktop",
"athlete"
],
"href": "http://www.espn.com/college-football/player/_/id/186421/david-montgomery",
"text": "Player Card"
},
{
"rel": [
"stats",
"desktop",
"athlete"
],
"href": "http://www.espn.com/college-football/player/stats/_/id/186421/david-montgomery",
"text": "Stats"
},
{
"rel": [
"splits",
"desktop",
"athlete"
],
"href": "http://www.espn.com/college-football/player/splits/_/id/186421/david-montgomery",
"text": "Splits"
},
{
"rel": [
"gamelog",
"desktop",
"athlete"
],
"href": "http://www.espn.com/college-football/player/gamelog/_/id/186421/david-montgomery",
"text": "Game Log"
},
{
"rel": [
"news",
"desktop",
"athlete"
],
"href": "http://www.espn.com/college-football/player/news/_/id/186421/david-montgomery",
"text": "News"
},
{
"rel": [
"bio",
"desktop",
"athlete"
],
"href": "http://www.espn.com/college-football/player/bio/_/id/186421/david-montgomery",
"text": "Bio"
},
{
"rel": [
"overview",
"desktop",
"athlete"
],
"href": "http://www.espn.com/college-football/player/_/id/186421/david-montgomery",
"text": "Overview"
}
]
},
"stats": [
"4",
"82",
"20.5",
"39",
"0"
]
},
{
"athlete": {
"id": "186417",
"uid": "s:20~l:23~a:186417",
"guid": "faf15124a5011abfc47213c645164bb1",
"firstName": "Brandon",
"lastName": "Jackson",
"displayName": "Brandon Jackson",
"links": [
{
"rel": [
"playercard",
"desktop",
"athlete"
],
"href": "http://www.espn.com/college-football/player/_/id/186417/brandon-jackson",
"text": "Player Card"
},
{
"rel": [
"stats",
"desktop",
"athlete"
],
"href": "http://www.espn.com/college-football/player/stats/_/id/186417/brandon-jackson",
"text": "Stats"
},
{
"rel": [
"splits",
"desktop",
"athlete"
],
"href": "http://www.espn.com/college-football/player/splits/_/id/186417/brandon-jackson",
"text": "Splits"
},
{
"rel": [
"gamelog",
"desktop",
"athlete"
],
"href": "http://www.espn.com/college-football/player/gamelog/_/id/186417/brandon-jackson",
"text": "Game Log"
},
{
"rel": [
"news",
"desktop",
"athlete"
],
"href": "http://www.espn.com/college-football/player/news/_/id/186417/brandon-jackson",
"text": "News"
},
{
"rel": [
"bio",
"desktop",
"athlete"
],
"href": "http://www.espn.com/college-football/player/bio/_/id/186417/brandon-jackson",
"text": "Bio"
},
{
"rel": [
"overview",
"desktop",
"athlete"
],
"href": "http://www.espn.com/college-football/player/_/id/186417/brandon-jackson",
"text": "Overview"
}
]
},
"stats": [
"2",
"54",
"27.0",
"27",
"0"
]
}
],
"totals": [
"6",
"136",
"22.7",
"39",
"0"
]
},
{
"name": "puntReturns",
"keys": [
"puntReturns",
"puntReturnYards",
"yardsPerPuntReturn",
"longPuntReturn",
"puntReturnTouchdowns"
],
"text": "Gardner-Webb Punt Returns",
"labels": [
"NO",
"YDS",
"AVG",
"LONG",
"TD"
],
"descriptions": [
"Punt Returns",
"Yards",
"Yards Per Punt Return",
"Longest Punt Return",
"Touchdowns"
],
"athletes": [
{
"athlete": {
"id": "233461",
"uid": "s:20~l:23~a:233461",
"guid": "209eba1071affff6b94a7a4c8aead3c5",
"firstName": "Tyson",
"lastName": "Petty",
"displayName": "Tyson Petty",
"links": [
{
"rel": [
"playercard",
"desktop",
"athlete"
],
"href": "http://www.espn.com/college-football/player/_/id/233461/tyson-petty",
"text": "Player Card"
},
{
"rel": [
"stats",
"desktop",
"athlete"
],
"href": "http://www.espn.com/college-football/player/stats/_/id/233461/tyson-petty",
"text": "Stats"
},
{
"rel": [
"splits",
"desktop",
"athlete"
],
"href": "http://www.espn.com/college-football/player/splits/_/id/233461/tyson-petty",
"text": "Splits"
},
{
"rel": [
"gamelog",
"desktop",
"athlete"
],
"href": "http://www.espn.com/college-football/player/gamelog/_/id/233461/tyson-petty",
"text": "Game Log"
},
{
"rel": [
"news",
"desktop",
"athlete"
],
"href": "http://www.espn.com/college-football/player/news/_/id/233461/tyson-petty",
"text": "News"
},
{
"rel": [
"bio",
"desktop",
"athlete"
],
"href": "http://www.espn.com/college-football/player/bio/_/id/233461/tyson-petty",
"text": "Bio"
},
{
"rel": [
"overview",
"desktop",
"athlete"
],
"href": "http://www.espn.com/college-football/player/_/id/233461/tyson-petty",
"text": "Overview"
}
]
},
"stats": [
"1",
"0",
"0.0",
"0",
"0"
]
}
],
"totals": [
"1",
"0",
"0.0",
"0",
"0"
]
},
{
"name": "kicking",
"keys": [
"fieldGoalsMade/fieldGoalAttempts",
"fieldGoalPct",
"longFieldGoalMade",
"extraPointsMade/extraPointAttempts",
"totalKickingPoints"
],
"text": "Gardner-Webb Kicking",
"labels": [
"FG",
"PCT",
"LONG",
"XP",
"PTS"
],
"descriptions": [
"Field Goals Made/Attempts",
"Field Goal Percentage",
"Longest Field Goal Made",
"Extra Points Made/Attempts",
"Kicking Points"
],
"athletes": [
{
"athlete": {
"id": "384427",
"uid": "s:20~l:23~a:384427",
"guid": "c6a99533a573fef6c103eb86c9215571",
"firstName": "Ryan",
"lastName": "Gates",
"displayName": "Ryan Gates",
"links": [
{
"rel": [
"playercard",
"desktop",
"athlete"
],
"href": "http://www.espn.com/college-football/player/_/id/384427/ryan-gates",
"text": "Player Card"
},
{
"rel": [
"stats",
"desktop",
"athlete"
],
"href": "http://www.espn.com/college-football/player/stats/_/id/384427/ryan-gates",
"text": "Stats"
},
{
"rel": [
"splits",
"desktop",
"athlete"
],
"href": "http://www.espn.com/college-football/player/splits/_/id/384427/ryan-gates",
"text": "Splits"
},
{
"rel": [
"gamelog",
"desktop",
"athlete"
],
"href": "http://www.espn.com/college-football/player/gamelog/_/id/384427/ryan-gates",
"text": "Game Log"
},
{
"rel": [
"news",
"desktop",
"athlete"
],
"href": "http://www.espn.com/college-football/player/news/_/id/384427/ryan-gates",
"text": "News"
},
{
"rel": [
"bio",
"desktop",
"athlete"
],
"href": "http://www.espn.com/college-football/player/bio/_/id/384427/ryan-gates",
"text": "Bio"
},
{
"rel": [
"overview",
"desktop",
"athlete"
],
"href": "http://www.espn.com/college-football/player/_/id/384427/ryan-gates",
"text": "Overview"
}
]
},
"stats": [
"1/1",
"100.0",
"44",
"0/0",
"3"
]
}
],
"totals": [
"1/1",
"100.0",
"44",
"0/0",
"3"
]
},
{
"name": "punting",
"keys": [
"punts",
"puntYards",
"grossAvgPuntYards",
"touchbacks",
"puntsInside20",
"longPunt"
],
"text": "Gardner-Webb Punting",
"labels": [
"NO",
"YDS",
"AVG",
"TB",
"In 20",
"LONG"
],
"descriptions": [
"Punts",
"Yards",
"Average Punt Yards",
"Touchbacks",
"Punts Inside 20",
"Longest Punt"
],
"athletes": [
{
"athlete": {
"id": "476860",
"uid": "s:20~l:23~a:476860",
"guid": "8eb51abf4d8eed436e4254d9efe56aa0",
"firstName": "Graham",
"lastName": "Purvis",
"displayName": "Graham Purvis",
"links": [
{
"rel": [
"playercard",
"desktop",
"athlete"
],
"href": "http://www.espn.com/college-football/player/_/id/476860/graham-purvis",
"text": "Player Card"
},
{
"rel": [
"stats",
"desktop",
"athlete"
],
"href": "http://www.espn.com/college-football/player/stats/_/id/476860/graham-purvis",
"text": "Stats"
},
{
"rel": [
"splits",
"desktop",
"athlete"
],
"href": "http://www.espn.com/college-football/player/splits/_/id/476860/graham-purvis",
"text": "Splits"
},
{
"rel": [
"gamelog",
"desktop",
"athlete"
],
"href": "http://www.espn.com/college-football/player/gamelog/_/id/476860/graham-purvis",
"text": "Game Log"
},
{
"rel": [
"news",
"desktop",
"athlete"
],
"href": "http://www.espn.com/college-football/player/news/_/id/476860/graham-purvis",
"text": "News"
},
{
"rel": [
"bio",
"desktop",
"athlete"
],
"href": "http://www.espn.com/college-football/player/bio/_/id/476860/graham-purvis",
"text": "Bio"
},
{
"rel": [
"overview",
"desktop",
"athlete"
],
"href": "http://www.espn.com/college-football/player/_/id/476860/graham-purvis",
"text": "Overview"
}
]
},
"stats": [
"4",
"134",
"33.5",
"0",
"0",
"42"
]
},
{
"athlete": {
"id": "484326",
"uid": "s:20~l:23~a:484326",
"guid": "555a883736459b5efc69f90e00316d67",
"firstName": "Bo",
"lastName": "Lindsey",
"displayName": "Bo Lindsey",
"links": [
{
"rel": [
"playercard",
"desktop",
"athlete"
],
"href": "http://www.espn.com/college-football/player/_/id/484326/bo-lindsey",
"text": "Player Card"
},
{
"rel": [
"stats",
"desktop",
"athlete"
],
"href": "http://www.espn.com/college-football/player/stats/_/id/484326/bo-lindsey",
"text": "Stats"
},
{
"rel": [
"splits",
"desktop",
"athlete"
],
"href": "http://www.espn.com/college-football/player/splits/_/id/484326/bo-lindsey",
"text": "Splits"
},
{
"rel": [
"gamelog",
"desktop",
"athlete"
],
"href": "http://www.espn.com/college-football/player/gamelog/_/id/484326/bo-lindsey",
"text": "Game Log"
},
{
"rel": [
"news",
"desktop",
"athlete"
],
"href": "http://www.espn.com/college-football/player/news/_/id/484326/bo-lindsey",
"text": "News"
},
{
"rel": [
"bio",
"desktop",
"athlete"
],
"href": "http://www.espn.com/college-football/player/bio/_/id/484326/bo-lindsey",
"text": "Bio"
},
{
"rel": [
"overview",
"desktop",
"athlete"
],
"href": "http://www.espn.com/college-football/player/_/id/484326/bo-lindsey",
"text": "Overview"
}
]
},
"stats": [
"1",
"43",
"43.0",
"0",
"0",
"43"
]
}
],
"totals": [
"5",
"177",
"35.4",
"0",
"0",
"43"
]
}
]
},
{
"team": {
"id": "2084",
"uid": "s:20~l:23~t:2084",
"slug": "buffalo-bulls",
"location": "Buffalo",
"name": "Bulls",
"abbreviation": "BUFF",
"displayName": "Buffalo Bulls",
"shortDisplayName": "Bulls",
"color": "041A9B",
"alternateColor": "ebebeb",
"logo": "https://a.espncdn.com/i/teamlogos/ncaa/500/2084.png"
},
"statistics": [
{
"name": "passing",
"keys": [
"completions/passingAttempts",
"passingYards",
"yardsPerPassAttempt",
"passingTouchdowns",
"interceptions",
"adjQBR"
],
"text": "Buffalo Passing",
"labels": [
"C/ATT",
"YDS",
"AVG",
"TD",
"INT",
"QBR"
],
"descriptions": [
"Completions/Attempts",
"Yards",
"Yards Per Pass Attempt",
"Touchdowns",
"Interceptions",
"Adjusted QBR"
],
"athletes": [
{
"athlete": {
"id": "384118",
"uid": "s:20~l:23~a:384118",
"guid": "2ebe44fb3967004166da610578a10fe1",
"firstName": "Zach",
"lastName": "Maynard",
"displayName": "Zach Maynard",
"links": [
{
"rel": [
"playercard",
"desktop",
"athlete"
],
"href": "http://www.espn.com/college-football/player/_/id/384118/zach-maynard",
"text": "Player Card"
},
{
"rel": [
"stats",
"desktop",
"athlete"
],
"href": "http://www.espn.com/college-football/player/stats/_/id/384118/zach-maynard",
"text": "Stats"
},
{
"rel": [
"splits",
"desktop",
"athlete"
],
"href": "http://www.espn.com/college-football/player/splits/_/id/384118/zach-maynard",
"text": "Splits"
},
{
"rel": [
"gamelog",
"desktop",
"athlete"
],
"href": "http://www.espn.com/college-football/player/gamelog/_/id/384118/zach-maynard",
"text": "Game Log"
},
{
"rel": [
"news",
"desktop",
"athlete"
],
"href": "http://www.espn.com/college-football/player/news/_/id/384118/zach-maynard",
"text": "News"
},
{
"rel": [
"bio",
"desktop",
"athlete"
],
"href": "http://www.espn.com/college-football/player/bio/_/id/384118/zach-maynard",
"text": "Bio"
},
{
"rel": [
"overview",
"desktop",
"athlete"
],
"href": "http://www.espn.com/college-football/player/_/id/384118/zach-maynard",
"text": "Overview"
}
]
},
"stats": [
"16/20",
"232",
"11.6",
"3",
"0",
"94.1"
]
},
{
"athlete": {
"id": "383087",
"uid": "s:20~l:23~a:383087",
"guid": "012fe8a6fcfb5858b9a7b770acdd0b4e",
"firstName": "Jerry",
"lastName": "Davis",
"displayName": "Jerry Davis",
"links": [
{
"rel": [
"playercard",
"desktop",
"athlete"
],
"href": "http://www.espn.com/college-football/player/_/id/383087/jerry-davis",
"text": "Player Card"
},
{
"rel": [
"stats",
"desktop",
"athlete"
],
"href": "http://www.espn.com/college-football/player/stats/_/id/383087/jerry-davis",
"text": "Stats"
},
{
"rel": [
"splits",
"desktop",
"athlete"
],
"href": "http://www.espn.com/college-football/player/splits/_/id/383087/jerry-davis",
"text": "Splits"
},
{
"rel": [
"gamelog",
"desktop",
"athlete"
],
"href": "http://www.espn.com/college-football/player/gamelog/_/id/383087/jerry-davis",
"text": "Game Log"
},
{
"rel": [
"news",
"desktop",
"athlete"
],
"href": "http://www.espn.com/college-football/player/news/_/id/383087/jerry-davis",
"text": "News"
},
{
"rel": [
"bio",
"desktop",
"athlete"
],
"href": "http://www.espn.com/college-football/player/bio/_/id/383087/jerry-davis",
"text": "Bio"
},
{
"rel": [
"overview",
"desktop",
"athlete"
],
"href": "http://www.espn.com/college-football/player/_/id/383087/jerry-davis",
"text": "Overview"
}
]
},
"stats": [
"3/6",
"26",
"4.3",
"0",
"0",
"3.1"
]
}
],
"totals": [
"19/26",
"269",
"9.9",
"3",
"0",
"--"
]
},
{
"name": "rushing",
"keys": [
"rushingAttempts",
"rushingYards",
"yardsPerRushAttempt",
"rushingTouchdowns",
"longRushing"
],
"text": "Buffalo Rushing",
"labels": [
"CAR",
"YDS",
"AVG",
"TD",
"LONG"
],
"descriptions": [
"Rushing Attempts",
"Yards",
"Yards Per Rushing Attempt",
"Touchdowns",
"Longest Run"
],
"athletes": [
{
"athlete": {
"id": "170690",
"uid": "s:20~l:23~a:170690",
"guid": "32e8479edd7a9b5890d41ec516e54bdd",
"firstName": "Ike",
"lastName": "Nduka",
"displayName": "Ike Nduka",
"links": [
{
"rel": [
"playercard",
"desktop",
"athlete"
],
"href": "http://www.espn.com/college-football/player/_/id/170690/ike-nduka",
"text": "Player Card"
},
{
"rel": [
"stats",
"desktop",
"athlete"
],
"href": "http://www.espn.com/college-football/player/stats/_/id/170690/ike-nduka",
"text": "Stats"
},
{
"rel": [
"splits",
"desktop",
"athlete"
],
"href": "http://www.espn.com/college-football/player/splits/_/id/170690/ike-nduka",
"text": "Splits"
},
{
"rel": [
"gamelog",
"desktop",
"athlete"
],
"href": "http://www.espn.com/college-football/player/gamelog/_/id/170690/ike-nduka",
"text": "Game Log"
},
{
"rel": [
"news",
"desktop",
"athlete"
],
"href": "http://www.espn.com/college-football/player/news/_/id/170690/ike-nduka",
"text": "News"
},
{
"rel": [
"bio",
"desktop",
"athlete"
],
"href": "http://www.espn.com/college-football/player/bio/_/id/170690/ike-nduka",
"text": "Bio"
},
{
"rel": [
"overview",
"desktop",
"athlete"
],
"href": "http://www.espn.com/college-football/player/_/id/170690/ike-nduka",
"text": "Overview"
}
]
},
"stats": [
"24",
"131",
"5.5",
"2",
"38"
]
},
{
"athlete": {
"id": "188875",
"uid": "s:20~l:23~a:188875",
"guid": "3cf41befa37d510a7145dc391be695c0",
"firstName": "Brandon",
"lastName": "Thermilus",
"displayName": "Brandon Thermilus",
"links": [
{
"rel": [
"playercard",
"desktop",
"athlete"
],
"href": "http://www.espn.com/college-football/player/_/id/188875/brandon-thermilus",
"text": "Player Card"
},
{
"rel": [
"stats",
"desktop",
"athlete"
],
"href": "http://www.espn.com/college-football/player/stats/_/id/188875/brandon-thermilus",
"text": "Stats"
},
{
"rel": [
"splits",
"desktop",
"athlete"
],
"href": "http://www.espn.com/college-football/player/splits/_/id/188875/brandon-thermilus",
"text": "Splits"
},
{
"rel": [
"gamelog",
"desktop",
"athlete"
],
"href": "http://www.espn.com/college-football/player/gamelog/_/id/188875/brandon-thermilus",
"text": "Game Log"
},
{
"rel": [
"news",
"desktop",
"athlete"
],
"href": "http://www.espn.com/college-football/player/news/_/id/188875/brandon-thermilus",
"text": "News"
},
{
"rel": [
"bio",
"desktop",
"athlete"
],
"href": "http://www.espn.com/college-football/player/bio/_/id/188875/brandon-thermilus",
"text": "Bio"
},
{
"rel": [
"overview",
"desktop",
"athlete"
],
"href": "http://www.espn.com/college-football/player/_/id/188875/brandon-thermilus",
"text": "Overview"
}
]
},
"stats": [
"10",
"82",
"8.2",
"1",
"23"
]
},
{
"athlete": {
"id": "482257",
"uid": "s:20~l:23~a:482257",
"guid": "d0ab48ad384fec3dc547ac3ae41c09a0",
"firstName": "Jeffvon",
"lastName": "Gill",
"displayName": "Jeffvon Gill",
"links": [
{
"rel": [
"playercard",
"desktop",
"athlete"
],
"href": "http://www.espn.com/college-football/player/_/id/482257/jeffvon-gill",
"text": "Player Card"
},
{
"rel": [
"stats",
"desktop",
"athlete"
],
"href": "http://www.espn.com/college-football/player/stats/_/id/482257/jeffvon-gill",
"text": "Stats"
},
{
"rel": [
"splits",
"desktop",
"athlete"
],
"href": "http://www.espn.com/college-football/player/splits/_/id/482257/jeffvon-gill",
"text": "Splits"
},
{
"rel": [
"gamelog",
"desktop",
"athlete"
],
"href": "http://www.espn.com/college-football/player/gamelog/_/id/482257/jeffvon-gill",
"text": "Game Log"
},
{
"rel": [
"news",
"desktop",
"athlete"
],
"href": "http://www.espn.com/college-football/player/news/_/id/482257/jeffvon-gill",
"text": "News"
},
{
"rel": [
"bio",
"desktop",
"athlete"
],
"href": "http://www.espn.com/college-football/player/bio/_/id/482257/jeffvon-gill",
"text": "Bio"
},
{
"rel": [
"overview",
"desktop",
"athlete"
],
"href": "http://www.espn.com/college-football/player/_/id/482257/jeffvon-gill",
"text": "Overview"
}
]
},
"stats": [
"3",
"17",
"5.7",
"0",
"8"
]
},
{
"athlete": {
"id": "236611",
"uid": "s:20~l:23~a:236611",
"guid": "06ca2aaa577e44f6c6539a744e3c8ced",
"firstName": "Terrell",
"lastName": "Jackson",
"displayName": "Terrell Jackson",
"links": [
{
"rel": [
"playercard",
"desktop",
"athlete"
],
"href": "http://www.espn.com/college-football/player/_/id/236611/terrell-jackson",
"text": "Player Card"
},
{
"rel": [
"stats",
"desktop",
"athlete"
],
"href": "http://www.espn.com/college-football/player/stats/_/id/236611/terrell-jackson",
"text": "Stats"
},
{
"rel": [
"splits",
"desktop",
"athlete"
],
"href": "http://www.espn.com/college-football/player/splits/_/id/236611/terrell-jackson",
"text": "Splits"
},
{
"rel": [
"gamelog",
"desktop",
"athlete"
],
"href": "http://www.espn.com/college-football/player/gamelog/_/id/236611/terrell-jackson",
"text": "Game Log"
},
{
"rel": [
"news",
"desktop",
"athlete"
],
"href": "http://www.espn.com/college-football/player/news/_/id/236611/terrell-jackson",
"text": "News"
},
{
"rel": [
"bio",
"desktop",
"athlete"
],
"href": "http://www.espn.com/college-football/player/bio/_/id/236611/terrell-jackson",
"text": "Bio"
},
{
"rel": [
"overview",
"desktop",
"athlete"
],
"href": "http://www.espn.com/college-football/player/_/id/236611/terrell-jackson",
"text": "Overview"
}
]
},
"stats": [
"1",
"12",
"12.0",
"0",
"12"
]
},
{
"athlete": {
"id": "170687",
"uid": "s:20~l:23~a:170687",
"guid": "e3b88f34e2307c95329576fa6ca0f86d",
"firstName": "Mario",
"lastName": "Henry",
"displayName": "Mario Henry",
"links": [
{
"rel": [
"playercard",
"desktop",
"athlete"
],
"href": "http://www.espn.com/college-football/player/_/id/170687/mario-henry",
"text": "Player Card"
},
{
"rel": [
"stats",
"desktop",
"athlete"
],
"href": "http://www.espn.com/college-football/player/stats/_/id/170687/mario-henry",
"text": "Stats"
},
{
"rel": [
"splits",
"desktop",
"athlete"
],
"href": "http://www.espn.com/college-football/player/splits/_/id/170687/mario-henry",
"text": "Splits"
},
{
"rel": [
"gamelog",
"desktop",
"athlete"
],
"href": "http://www.espn.com/college-football/player/gamelog/_/id/170687/mario-henry",
"text": "Game Log"
},
{
"rel": [
"news",
"desktop",
"athlete"
],
"href": "http://www.espn.com/college-football/player/news/_/id/170687/mario-henry",
"text": "News"
},
{
"rel": [
"bio",
"desktop",
"athlete"
],
"href": "http://www.espn.com/college-football/player/bio/_/id/170687/mario-henry",
"text": "Bio"
},
{
"rel": [
"overview",
"desktop",
"athlete"
],
"href": "http://www.espn.com/college-football/player/_/id/170687/mario-henry",
"text": "Overview"
}
]
},
"stats": [
"5",
"12",
"2.4",
"0",
"9"
]
},
{
"athlete": {
"id": "384118",
"uid": "s:20~l:23~a:384118",
"guid": "2ebe44fb3967004166da610578a10fe1",
"firstName": "Zach",
"lastName": "Maynard",
"displayName": "Zach Maynard",
"links": [
{
"rel": [
"playercard",
"desktop",
"athlete"
],
"href": "http://www.espn.com/college-football/player/_/id/384118/zach-maynard",
"text": "Player Card"
},
{
"rel": [
"stats",
"desktop",
"athlete"
],
"href": "http://www.espn.com/college-football/player/stats/_/id/384118/zach-maynard",
"text": "Stats"
},
{
"rel": [
"splits",
"desktop",
"athlete"
],
"href": "http://www.espn.com/college-football/player/splits/_/id/384118/zach-maynard",
"text": "Splits"
},
{
"rel": [
"gamelog",
"desktop",
"athlete"
],
"href": "http://www.espn.com/college-football/player/gamelog/_/id/384118/zach-maynard",
"text": "Game Log"
},
{
"rel": [
"news",
"desktop",
"athlete"
],
"href": "http://www.espn.com/college-football/player/news/_/id/384118/zach-maynard",
"text": "News"
},
{
"rel": [
"bio",
"desktop",
"athlete"
],
"href": "http://www.espn.com/college-football/player/bio/_/id/384118/zach-maynard",
"text": "Bio"
},
{
"rel": [
"overview",
"desktop",
"athlete"
],
"href": "http://www.espn.com/college-football/player/_/id/384118/zach-maynard",
"text": "Overview"
}
]
},
"stats": [
"3",
"7",
"2.3",
"0",
"5"
]
},
{
"athlete": {
"id": "383087",
"uid": "s:20~l:23~a:383087",
"guid": "012fe8a6fcfb5858b9a7b770acdd0b4e",
"firstName": "Jerry",
"lastName": "Davis",
"displayName": "Jerry Davis",
"links": [
{
"rel": [
"playercard",
"desktop",
"athlete"
],
"href": "http://www.espn.com/college-football/player/_/id/383087/jerry-davis",
"text": "Player Card"
},
{
"rel": [
"stats",
"desktop",
"athlete"
],
"href": "http://www.espn.com/college-football/player/stats/_/id/383087/jerry-davis",
"text": "Stats"
},
{
"rel": [
"splits",
"desktop",
"athlete"
],
"href": "http://www.espn.com/college-football/player/splits/_/id/383087/jerry-davis",
"text": "Splits"
},
{
"rel": [
"gamelog",
"desktop",
"athlete"
],
"href": "http://www.espn.com/college-football/player/gamelog/_/id/383087/jerry-davis",
"text": "Game Log"
},
{
"rel": [
"news",
"desktop",
"athlete"
],
"href": "http://www.espn.com/college-football/player/news/_/id/383087/jerry-davis",
"text": "News"
},
{
"rel": [
"bio",
"desktop",
"athlete"
],
"href": "http://www.espn.com/college-football/player/bio/_/id/383087/jerry-davis",
"text": "Bio"
},
{
"rel": [
"overview",
"desktop",
"athlete"
],
"href": "http://www.espn.com/college-football/player/_/id/383087/jerry-davis",
"text": "Overview"
}
]
},
"stats": [
"1",
"-11",
"-11.0",
"0",
"0"
]
}
],
"totals": [
"47",
"250",
"5.3",
"3",
"38"
]
},
{
"name": "receiving",
"keys": [
"receptions",
"receivingYards",
"yardsPerReception",
"receivingTouchdowns",
"longReception"
],
"text": "Buffalo Receiving",
"labels": [
"REC",
"YDS",
"AVG",
"TD",
"LONG"
],
"descriptions": [
"Receptions",
"Yards",
"Yards Per Reception",
"Touchdowns",
"Longest Reception"
],
"athletes": [
{
"athlete": {
"id": "170685",
"uid": "s:20~l:23~a:170685",
"guid": "7149c3c841130afa25429535e73799af",
"firstName": "Brett",
"lastName": "Hamlin",
"displayName": "Brett Hamlin",
"links": [
{
"rel": [
"playercard",
"desktop",
"athlete"
],
"href": "http://www.espn.com/college-football/player/_/id/170685/brett-hamlin",
"text": "Player Card"
},
{
"rel": [
"stats",
"desktop",
"athlete"
],
"href": "http://www.espn.com/college-football/player/stats/_/id/170685/brett-hamlin",
"text": "Stats"
},
{
"rel": [
"splits",
"desktop",
"athlete"
],
"href": "http://www.espn.com/college-football/player/splits/_/id/170685/brett-hamlin",
"text": "Splits"
},
{
"rel": [
"gamelog",
"desktop",
"athlete"
],
"href": "http://www.espn.com/college-football/player/gamelog/_/id/170685/brett-hamlin",
"text": "Game Log"
},
{
"rel": [
"news",
"desktop",
"athlete"
],
"href": "http://www.espn.com/college-football/player/news/_/id/170685/brett-hamlin",
"text": "News"
},
{
"rel": [
"bio",
"desktop",
"athlete"
],
"href": "http://www.espn.com/college-football/player/bio/_/id/170685/brett-hamlin",
"text": "Bio"
},
{
"rel": [
"overview",
"desktop",
"athlete"
],
"href": "http://www.espn.com/college-football/player/_/id/170685/brett-hamlin",
"text": "Overview"
}
]
},
"stats": [
"6",
"132",
"22.0",
"1",
"50"
]
},
{
"athlete": {
"id": "188873",
"uid": "s:20~l:23~a:188873",
"guid": "9605c106df17d14712be923ee93cdc5a",
"firstName": "Naaman",
"lastName": "Roosevelt",
"displayName": "Naaman Roosevelt",
"links": [
{
"rel": [
"playercard",
"desktop",
"athlete"
],
"href": "http://www.espn.com/college-football/player/_/id/188873/naaman-roosevelt",
"text": "Player Card"
},
{
"rel": [
"stats",
"desktop",
"athlete"
],
"href": "http://www.espn.com/college-football/player/stats/_/id/188873/naaman-roosevelt",
"text": "Stats"
},
{
"rel": [
"splits",
"desktop",
"athlete"
],
"href": "http://www.espn.com/college-football/player/splits/_/id/188873/naaman-roosevelt",
"text": "Splits"
},
{
"rel": [
"gamelog",
"desktop",
"athlete"
],
"href": "http://www.espn.com/college-football/player/gamelog/_/id/188873/naaman-roosevelt",
"text": "Game Log"
},
{
"rel": [
"news",
"desktop",
"athlete"
],
"href": "http://www.espn.com/college-football/player/news/_/id/188873/naaman-roosevelt",
"text": "News"
},
{
"rel": [
"bio",
"desktop",
"athlete"
],
"href": "http://www.espn.com/college-football/player/bio/_/id/188873/naaman-roosevelt",
"text": "Bio"
},
{
"rel": [
"overview",
"desktop",
"athlete"
],
"href": "http://www.espn.com/college-football/player/_/id/188873/naaman-roosevelt",
"text": "Overview"
}
]
},
"stats": [
"5",
"46",
"9.2",
"0",
"14"
]
},
{
"athlete": {
"id": "170694",
"uid": "s:20~l:23~a:170694",
"guid": "a2da29553c565ffec3e4bcffe4f00a55",
"firstName": "Jesse",
"lastName": "Rack",
"displayName": "Jesse Rack",
"links": [
{
"rel": [
"playercard",
"desktop",
"athlete"
],
"href": "http://www.espn.com/college-football/player/_/id/170694/jesse-rack",
"text": "Player Card"
},
{
"rel": [
"stats",
"desktop",
"athlete"
],
"href": "http://www.espn.com/college-football/player/stats/_/id/170694/jesse-rack",
"text": "Stats"
},
{
"rel": [
"splits",
"desktop",
"athlete"
],
"href": "http://www.espn.com/college-football/player/splits/_/id/170694/jesse-rack",
"text": "Splits"
},
{
"rel": [
"gamelog",
"desktop",
"athlete"
],
"href": "http://www.espn.com/college-football/player/gamelog/_/id/170694/jesse-rack",
"text": "Game Log"
},
{
"rel": [
"news",
"desktop",
"athlete"
],
"href": "http://www.espn.com/college-football/player/news/_/id/170694/jesse-rack",
"text": "News"
},
{
"rel": [
"bio",
"desktop",
"athlete"
],
"href": "http://www.espn.com/college-football/player/bio/_/id/170694/jesse-rack",
"text": "Bio"
},
{
"rel": [
"overview",
"desktop",
"athlete"
],
"href": "http://www.espn.com/college-football/player/_/id/170694/jesse-rack",
"text": "Overview"
}
]
},
"stats": [
"3",
"27",
"9.0",
"2",
"17"
]
},
{
"athlete": {
"id": "236611",
"uid": "s:20~l:23~a:236611",
"guid": "06ca2aaa577e44f6c6539a744e3c8ced",
"firstName": "Terrell",
"lastName": "Jackson",
"displayName": "Terrell Jackson",
"links": [
{
"rel": [
"playercard",
"desktop",
"athlete"
],
"href": "http://www.espn.com/college-football/player/_/id/236611/terrell-jackson",
"text": "Player Card"
},
{
"rel": [
"stats",
"desktop",
"athlete"
],
"href": "http://www.espn.com/college-football/player/stats/_/id/236611/terrell-jackson",
"text": "Stats"
},
{
"rel": [
"splits",
"desktop",
"athlete"
],
"href": "http://www.espn.com/college-football/player/splits/_/id/236611/terrell-jackson",
"text": "Splits"
},
{
"rel": [
"gamelog",
"desktop",
"athlete"
],
"href": "http://www.espn.com/college-football/player/gamelog/_/id/236611/terrell-jackson",
"text": "Game Log"
},
{
"rel": [
"news",
"desktop",
"athlete"
],
"href": "http://www.espn.com/college-football/player/news/_/id/236611/terrell-jackson",
"text": "News"
},
{
"rel": [
"bio",
"desktop",
"athlete"
],
"href": "http://www.espn.com/college-football/player/bio/_/id/236611/terrell-jackson",
"text": "Bio"
},
{
"rel": [
"overview",
"desktop",
"athlete"
],
"href": "http://www.espn.com/college-football/player/_/id/236611/terrell-jackson",
"text": "Overview"
}
]
},
"stats": [
"2",
"24",
"12.0",
"0",
"21"
]
},
{
"athlete": {
"id": "170687",
"uid": "s:20~l:23~a:170687",
"guid": "e3b88f34e2307c95329576fa6ca0f86d",
"firstName": "Mario",
"lastName": "Henry",
"displayName": "Mario Henry",
"links": [
{
"rel": [
"playercard",
"desktop",
"athlete"
],
"href": "http://www.espn.com/college-football/player/_/id/170687/mario-henry",
"text": "Player Card"
},
{
"rel": [
"stats",
"desktop",
"athlete"
],
"href": "http://www.espn.com/college-football/player/stats/_/id/170687/mario-henry",
"text": "Stats"
},
{
"rel": [
"splits",
"desktop",
"athlete"
],
"href": "http://www.espn.com/college-football/player/splits/_/id/170687/mario-henry",
"text": "Splits"
},
{
"rel": [
"gamelog",
"desktop",
"athlete"
],
"href": "http://www.espn.com/college-football/player/gamelog/_/id/170687/mario-henry",
"text": "Game Log"
},
{
"rel": [
"news",
"desktop",
"athlete"
],
"href": "http://www.espn.com/college-football/player/news/_/id/170687/mario-henry",
"text": "News"
},
{
"rel": [
"bio",
"desktop",
"athlete"
],
"href": "http://www.espn.com/college-football/player/bio/_/id/170687/mario-henry",
"text": "Bio"
},
{
"rel": [
"overview",
"desktop",
"athlete"
],
"href": "http://www.espn.com/college-football/player/_/id/170687/mario-henry",
"text": "Overview"
}
]
},
"stats": [
"1",
"11",
"11.0",
"0",
"11"
]
},
{
"athlete": {
"id": "236455",
"uid": "s:20~l:23~a:236455",
"guid": "2f2923aeedcd34f7e8d04c777be1b0a9",
"firstName": "Marcus",
"lastName": "Rivers",
"displayName": "Marcus Rivers",
"links": [
{
"rel": [
"playercard",
"desktop",
"athlete"
],
"href": "http://www.espn.com/college-football/player/_/id/236455/marcus-rivers",
"text": "Player Card"
},
{
"rel": [
"stats",
"desktop",
"athlete"
],
"href": "http://www.espn.com/college-football/player/stats/_/id/236455/marcus-rivers",
"text": "Stats"
},
{
"rel": [
"splits",
"desktop",
"athlete"
],
"href": "http://www.espn.com/college-football/player/splits/_/id/236455/marcus-rivers",
"text": "Splits"
},
{
"rel": [
"gamelog",
"desktop",
"athlete"
],
"href": "http://www.espn.com/college-football/player/gamelog/_/id/236455/marcus-rivers",
"text": "Game Log"
},
{
"rel": [
"news",
"desktop",
"athlete"
],
"href": "http://www.espn.com/college-football/player/news/_/id/236455/marcus-rivers",
"text": "News"
},
{
"rel": [
"bio",
"desktop",
"athlete"
],
"href": "http://www.espn.com/college-football/player/bio/_/id/236455/marcus-rivers",
"text": "Bio"
},
{
"rel": [
"overview",
"desktop",
"athlete"
],
"href": "http://www.espn.com/college-football/player/_/id/236455/marcus-rivers",
"text": "Overview"
}
]
},
"stats": [
"1",
"10",
"10.0",
"0",
"10"
]
},
{
"athlete": {
"id": "170690",
"uid": "s:20~l:23~a:170690",
"guid": "32e8479edd7a9b5890d41ec516e54bdd",
"firstName": "Ike",
"lastName": "Nduka",
"displayName": "Ike Nduka",
"links": [
{
"rel": [
"playercard",
"desktop",
"athlete"
],
"href": "http://www.espn.com/college-football/player/_/id/170690/ike-nduka",
"text": "Player Card"
},
{
"rel": [
"stats",
"desktop",
"athlete"
],
"href": "http://www.espn.com/college-football/player/stats/_/id/170690/ike-nduka",
"text": "Stats"
},
{
"rel": [
"splits",
"desktop",
"athlete"
],
"href": "http://www.espn.com/college-football/player/splits/_/id/170690/ike-nduka",
"text": "Splits"
},
{
"rel": [
"gamelog",
"desktop",
"athlete"
],
"href": "http://www.espn.com/college-football/player/gamelog/_/id/170690/ike-nduka",
"text": "Game Log"
},
{
"rel": [
"news",
"desktop",
"athlete"
],
"href": "http://www.espn.com/college-football/player/news/_/id/170690/ike-nduka",
"text": "News"
},
{
"rel": [
"bio",
"desktop",
"athlete"
],
"href": "http://www.espn.com/college-football/player/bio/_/id/170690/ike-nduka",
"text": "Bio"
},
{
"rel": [
"overview",
"desktop",
"athlete"
],
"href": "http://www.espn.com/college-football/player/_/id/170690/ike-nduka",
"text": "Overview"
}
]
},
"stats": [
"1",
"8",
"8.0",
"0",
"8"
]
}
],
"totals": [
"19",
"258",
"13.6",
"3",
"50"
]
},
{
"name": "interceptions",
"keys": [
"interceptions",
"interceptionYards",
"interceptionTouchdowns"
],
"text": "Buffalo Interceptions",
"labels": [
"INT",
"YDS",
"TD"
],
"descriptions": [
"Interceptions",
"Yards",
"Touchdowns"
],
"athletes": [],
"totals": []
},
{
"name": "kickReturns",
"keys": [
"kickReturns",
"kickReturnYards",
"yardsPerKickReturn",
"longKickReturn",
"kickReturnTouchdowns"
],
"text": "Buffalo Kick Returns",
"labels": [
"NO",
"YDS",
"AVG",
"LONG",
"TD"
],
"descriptions": [
"Kick Returns",
"Yards",
"Yards Per Kick Return",
"Longest Kick Return",
"Touchdowns"
],
"athletes": [
{
"athlete": {
"id": "236484",
"uid": "s:20~l:23~a:236484",
"guid": "6c03d3014bd7f70cada95686d5342f79",
"firstName": "Domonic",
"lastName": "Cook",
"displayName": "Domonic Cook",
"links": [
{
"rel": [
"playercard",
"desktop",
"athlete"
],
"href": "http://www.espn.com/college-football/player/_/id/236484/domonic-cook",
"text": "Player Card"
},
{
"rel": [
"stats",
"desktop",
"athlete"
],
"href": "http://www.espn.com/college-football/player/stats/_/id/236484/domonic-cook",
"text": "Stats"
},
{
"rel": [
"splits",
"desktop",
"athlete"
],
"href": "http://www.espn.com/college-football/player/splits/_/id/236484/domonic-cook",
"text": "Splits"
},
{
"rel": [
"gamelog",
"desktop",
"athlete"
],
"href": "http://www.espn.com/college-football/player/gamelog/_/id/236484/domonic-cook",
"text": "Game Log"
},
{
"rel": [
"news",
"desktop",
"athlete"
],
"href": "http://www.espn.com/college-football/player/news/_/id/236484/domonic-cook",
"text": "News"
},
{
"rel": [
"bio",
"desktop",
"athlete"
],
"href": "http://www.espn.com/college-football/player/bio/_/id/236484/domonic-cook",
"text": "Bio"
},
{
"rel": [
"overview",
"desktop",
"athlete"
],
"href": "http://www.espn.com/college-football/player/_/id/236484/domonic-cook",
"text": "Overview"
}
]
},
"stats": [
"1",
"30",
"30.0",
"30",
"0"
]
},
{
"athlete": {
"id": "188873",
"uid": "s:20~l:23~a:188873",
"guid": "9605c106df17d14712be923ee93cdc5a",
"firstName": "Naaman",
"lastName": "Roosevelt",
"displayName": "Naaman Roosevelt",
"links": [
{
"rel": [
"playercard",
"desktop",
"athlete"
],
"href": "http://www.espn.com/college-football/player/_/id/188873/naaman-roosevelt",
"text": "Player Card"
},
{
"rel": [
"stats",
"desktop",
"athlete"
],
"href": "http://www.espn.com/college-football/player/stats/_/id/188873/naaman-roosevelt",
"text": "Stats"
},
{
"rel": [
"splits",
"desktop",
"athlete"
],
"href": "http://www.espn.com/college-football/player/splits/_/id/188873/naaman-roosevelt",
"text": "Splits"
},
{
"rel": [
"gamelog",
"desktop",
"athlete"
],
"href": "http://www.espn.com/college-football/player/gamelog/_/id/188873/naaman-roosevelt",
"text": "Game Log"
},
{
"rel": [
"news",
"desktop",
"athlete"
],
"href": "http://www.espn.com/college-football/player/news/_/id/188873/naaman-roosevelt",
"text": "News"
},
{
"rel": [
"bio",
"desktop",
"athlete"
],
"href": "http://www.espn.com/college-football/player/bio/_/id/188873/naaman-roosevelt",
"text": "Bio"
},
{
"rel": [
"overview",
"desktop",
"athlete"
],
"href": "http://www.espn.com/college-football/player/_/id/188873/naaman-roosevelt",
"text": "Overview"
}
]
},
"stats": [
"1",
"22",
"22.0",
"22",
"0"
]
}
],
"totals": [
"2",
"52",
"26.0",
"30",
"0"
]
},
{
"name": "puntReturns",
"keys": [
"puntReturns",
"puntReturnYards",
"yardsPerPuntReturn",
"longPuntReturn",
"puntReturnTouchdowns"
],
"text": "Buffalo Punt Returns",
"labels": [
"NO",
"YDS",
"AVG",
"LONG",
"TD"
],
"descriptions": [
"Punt Returns",
"Yards",
"Yards Per Punt Return",
"Longest Punt Return",
"Touchdowns"
],
"athletes": [
{
"athlete": {
"id": "188873",
"uid": "s:20~l:23~a:188873",
"guid": "9605c106df17d14712be923ee93cdc5a",
"firstName": "Naaman",
"lastName": "Roosevelt",
"displayName": "Naaman Roosevelt",
"links": [
{
"rel": [
"playercard",
"desktop",
"athlete"
],
"href": "http://www.espn.com/college-football/player/_/id/188873/naaman-roosevelt",
"text": "Player Card"
},
{
"rel": [
"stats",
"desktop",
"athlete"
],
"href": "http://www.espn.com/college-football/player/stats/_/id/188873/naaman-roosevelt",
"text": "Stats"
},
{
"rel": [
"splits",
"desktop",
"athlete"
],
"href": "http://www.espn.com/college-football/player/splits/_/id/188873/naaman-roosevelt",
"text": "Splits"
},
{
"rel": [
"gamelog",
"desktop",
"athlete"
],
"href": "http://www.espn.com/college-football/player/gamelog/_/id/188873/naaman-roosevelt",
"text": "Game Log"
},
{
"rel": [
"news",
"desktop",
"athlete"
],
"href": "http://www.espn.com/college-football/player/news/_/id/188873/naaman-roosevelt",
"text": "News"
},
{
"rel": [
"bio",
"desktop",
"athlete"
],
"href": "http://www.espn.com/college-football/player/bio/_/id/188873/naaman-roosevelt",
"text": "Bio"
},
{
"rel": [
"overview",
"desktop",
"athlete"
],
"href": "http://www.espn.com/college-football/player/_/id/188873/naaman-roosevelt",
"text": "Overview"
}
]
},
"stats": [
"1",
"10",
"10.0",
"10",
"0"
]
},
{
"athlete": {
"id": "170685",
"uid": "s:20~l:23~a:170685",
"guid": "7149c3c841130afa25429535e73799af",
"firstName": "Brett",
"lastName": "Hamlin",
"displayName": "Brett Hamlin",
"links": [
{
"rel": [
"playercard",
"desktop",
"athlete"
],
"href": "http://www.espn.com/college-football/player/_/id/170685/brett-hamlin",
"text": "Player Card"
},
{
"rel": [
"stats",
"desktop",
"athlete"
],
"href": "http://www.espn.com/college-football/player/stats/_/id/170685/brett-hamlin",
"text": "Stats"
},
{
"rel": [
"splits",
"desktop",
"athlete"
],
"href": "http://www.espn.com/college-football/player/splits/_/id/170685/brett-hamlin",
"text": "Splits"
},
{
"rel": [
"gamelog",
"desktop",
"athlete"
],
"href": "http://www.espn.com/college-football/player/gamelog/_/id/170685/brett-hamlin",
"text": "Game Log"
},
{
"rel": [
"news",
"desktop",
"athlete"
],
"href": "http://www.espn.com/college-football/player/news/_/id/170685/brett-hamlin",
"text": "News"
},
{
"rel": [
"bio",
"desktop",
"athlete"
],
"href": "http://www.espn.com/college-football/player/bio/_/id/170685/brett-hamlin",
"text": "Bio"
},
{
"rel": [
"overview",
"desktop",
"athlete"
],
"href": "http://www.espn.com/college-football/player/_/id/170685/brett-hamlin",
"text": "Overview"
}
]
},
"stats": [
"2",
"4",
"2.0",
"4",
"0"
]
},
{
"athlete": {
"id": "236611",
"uid": "s:20~l:23~a:236611",
"guid": "06ca2aaa577e44f6c6539a744e3c8ced",
"firstName": "Terrell",
"lastName": "Jackson",
"displayName": "Terrell Jackson",
"links": [
{
"rel": [
"playercard",
"desktop",
"athlete"
],
"href": "http://www.espn.com/college-football/player/_/id/236611/terrell-jackson",
"text": "Player Card"
},
{
"rel": [
"stats",
"desktop",
"athlete"
],
"href": "http://www.espn.com/college-football/player/stats/_/id/236611/terrell-jackson",
"text": "Stats"
},
{
"rel": [
"splits",
"desktop",
"athlete"
],
"href": "http://www.espn.com/college-football/player/splits/_/id/236611/terrell-jackson",
"text": "Splits"
},
{
"rel": [
"gamelog",
"desktop",
"athlete"
],
"href": "http://www.espn.com/college-football/player/gamelog/_/id/236611/terrell-jackson",
"text": "Game Log"
},
{
"rel": [
"news",
"desktop",
"athlete"
],
"href": "http://www.espn.com/college-football/player/news/_/id/236611/terrell-jackson",
"text": "News"
},
{
"rel": [
"bio",
"desktop",
"athlete"
],
"href": "http://www.espn.com/college-football/player/bio/_/id/236611/terrell-jackson",
"text": "Bio"
},
{
"rel": [
"overview",
"desktop",
"athlete"
],
"href": "http://www.espn.com/college-football/player/_/id/236611/terrell-jackson",
"text": "Overview"
}
]
},
"stats": [
"2",
"-1",
"-0.5",
"0",
"0"
]
}
],
"totals": [
"3",
"13",
"4.3",
"10",
"0"
]
},
{
"name": "kicking",
"keys": [
"fieldGoalsMade/fieldGoalAttempts",
"fieldGoalPct",
"longFieldGoalMade",
"extraPointsMade/extraPointAttempts",
"totalKickingPoints"
],
"text": "Buffalo Kicking",
"labels": [
"FG",
"PCT",
"LONG",
"XP",
"PTS"
],
"descriptions": [
"Field Goals Made/Attempts",
"Field Goal Percentage",
"Longest Field Goal Made",
"Extra Points Made/Attempts",
"Kicking Points"
],
"athletes": [
{
"athlete": {
"id": "241738",
"uid": "s:20~l:23~a:241738",
"guid": "b43a36a90151991fe89af9b06ac33585",
"firstName": "A.J.",
"lastName": "Principe",
"displayName": "A.J. Principe",
"links": [
{
"rel": [
"playercard",
"desktop",
"athlete"
],
"href": "http://www.espn.com/college-football/player/_/id/241738/aj-principe",
"text": "Player Card"
},
{
"rel": [
"stats",
"desktop",
"athlete"
],
"href": "http://www.espn.com/college-football/player/stats/_/id/241738/aj-principe",
"text": "Stats"
},
{
"rel": [
"splits",
"desktop",
"athlete"
],
"href": "http://www.espn.com/college-football/player/splits/_/id/241738/aj-principe",
"text": "Splits"
},
{
"rel": [
"gamelog",
"desktop",
"athlete"
],
"href": "http://www.espn.com/college-football/player/gamelog/_/id/241738/aj-principe",
"text": "Game Log"
},
{
"rel": [
"news",
"desktop",
"athlete"
],
"href": "http://www.espn.com/college-football/player/news/_/id/241738/aj-principe",
"text": "News"
},
{
"rel": [
"bio",
"desktop",
"athlete"
],
"href": "http://www.espn.com/college-football/player/bio/_/id/241738/aj-principe",
"text": "Bio"
},
{
"rel": [
"overview",
"desktop",
"athlete"
],
"href": "http://www.espn.com/college-football/player/_/id/241738/aj-principe",
"text": "Overview"
}
]
},
"stats": [
"0/0",
"0.0",
"0",
"4/6",
"4"
]
}
],
"totals": [
"0/0",
"0.0",
"36",
"4/6",
"4"
]
},
{
"name": "punting",
"keys": [
"punts",
"puntYards",
"grossAvgPuntYards",
"touchbacks",
"puntsInside20",
"longPunt"
],
"text": "Buffalo Punting",
"labels": [
"NO",
"YDS",
"AVG",
"TB",
"In 20",
"LONG"
],
"descriptions": [
"Punts",
"Yards",
"Average Punt Yards",
"Touchbacks",
"Punts Inside 20",
"Longest Punt"
],
"athletes": [
{
"athlete": {
"id": "378457",
"uid": "s:20~l:23~a:378457",
"guid": "abe5ddc4d096156e1697ee868ff65d00",
"firstName": "Peter",
"lastName": "Fardon",
"displayName": "Peter Fardon",
"links": [
{
"rel": [
"playercard",
"desktop",
"athlete"
],
"href": "http://www.espn.com/college-football/player/_/id/378457/peter-fardon",
"text": "Player Card"
},
{
"rel": [
"stats",
"desktop",
"athlete"
],
"href": "http://www.espn.com/college-football/player/stats/_/id/378457/peter-fardon",
"text": "Stats"
},
{
"rel": [
"splits",
"desktop",
"athlete"
],
"href": "http://www.espn.com/college-football/player/splits/_/id/378457/peter-fardon",
"text": "Splits"
},
{
"rel": [
"gamelog",
"desktop",
"athlete"
],
"href": "http://www.espn.com/college-football/player/gamelog/_/id/378457/peter-fardon",
"text": "Game Log"
},
{
"rel": [
"news",
"desktop",
"athlete"
],
"href": "http://www.espn.com/college-football/player/news/_/id/378457/peter-fardon",
"text": "News"
},
{
"rel": [
"bio",
"desktop",
"athlete"
],
"href": "http://www.espn.com/college-football/player/bio/_/id/378457/peter-fardon",
"text": "Bio"
},
{
"rel": [
"overview",
"desktop",
"athlete"
],
"href": "http://www.espn.com/college-football/player/_/id/378457/peter-fardon",
"text": "Overview"
}
]
},
"stats": [
"2",
"66",
"33.0",
"0",
"0",
"35"
]
}
],
"totals": [
"2",
"66",
"33.0",
"0",
"0",
"35"
]
}
]
}
]
},
"format": {
"regulation": {
"periods": 4,
"displayName": "Quarter",
"slug": "quarter",
"clock": 900.0
}
},
"gameInfo": {
"venue": {
"id": "3965",
"fullName": "UB Stadium",
"address": {
"city": "Buffalo",
"state": "NY",
"zipCode": "14228"
},
"capacity": 25013,
"grass": false,
"images": [
{
"href": "https://a.espncdn.com/i/venues/college-football/day/interior/3965.jpg",
"width": 2000,
"height": 1125,
"alt": "",
"rel": [
"full",
"day",
"interior"
]
}
]
},
"attendance": 0
},
"drives": {},
"leaders": [
{
"team": {
"id": "2084",
"uid": "s:20~l:23~t:2084",
"displayName": "Buffalo Bulls",
"abbreviation": "BUFF",
"links": [
{
"href": "https://www.espn.com/college-football/team/_/id/2084/buffalo-bulls",
"text": "Clubhouse"
},
{
"href": "http://www.espn.com/college-football/team/schedule/_/id/2084",
"text": "Schedule"
}
],
"logo": "https://a.espncdn.com/i/teamlogos/ncaa/500/2084.png"
},
"leaders": [
{
"name": "passingYards",
"displayName": "Passing Yards",
"leaders": [
{
"displayValue": "16-20, 232 YDS, 3 TD",
"athlete": {
"id": "384118",
"uid": "s:20~l:23~a:384118",
"guid": "2ebe44fb3967004166da610578a10fe1",
"lastName": "Maynard",
"fullName": "Zach Maynard",
"displayName": "Zach Maynard",
"shortName": "Z. Maynard",
"links": [
{
"rel": [
"playercard",
"desktop",
"athlete"
],
"href": "http://www.espn.com/college-football/player/_/id/384118/zach-maynard",
"text": "Player Card"
}
],
"jersey": "15 ",
"position": {
"abbreviation": "QB"
}
}
}
]
},
{
"name": "rushingYards",
"displayName": "Rushing Yards",
"leaders": [
{
"displayValue": "24 CAR, 131 YDS, 2 TD",
"athlete": {
"id": "170690",
"uid": "s:20~l:23~a:170690",
"guid": "32e8479edd7a9b5890d41ec516e54bdd",
"lastName": "Nduka",
"fullName": "Ike Nduka",
"displayName": "Ike Nduka",
"shortName": "I. Nduka",
"links": [
{
"rel": [
"playercard",
"desktop",
"athlete"
],
"href": "http://www.espn.com/college-football/player/_/id/170690/ike-nduka",
"text": "Player Card"
}
],
"jersey": "36 ",
"position": {
"abbreviation": "RB"
}
}
}
]
},
{
"name": "receivingYards",
"displayName": "Receiving Yards",
"leaders": [
{
"displayValue": "6 REC, 132 YDS, 1 TD",
"athlete": {
"id": "170685",
"uid": "s:20~l:23~a:170685",
"guid": "7149c3c841130afa25429535e73799af",
"lastName": "Hamlin",
"fullName": "Brett Hamlin",
"displayName": "Brett Hamlin",
"shortName": "B. Hamlin",
"links": [
{
"rel": [
"playercard",
"desktop",
"athlete"
],
"href": "http://www.espn.com/college-football/player/_/id/170685/brett-hamlin",
"text": "Player Card"
}
],
"jersey": "88 ",
"position": {
"abbreviation": "WR"
}
}
}
]
}
]
},
{
"team": {
"id": "2241",
"uid": "s:20~l:23~t:2241",
"displayName": "Gardner-Webb Bulldogs",
"abbreviation": "WEBB",
"links": [
{
"href": "https://www.espn.com/college-football/team/_/id/2241/gardner-webb-bulldogs",
"text": "Clubhouse"
},
{
"href": "http://www.espn.com/college-football/team/schedule/_/id/2241",
"text": "Schedule"
}
],
"logo": "https://a.espncdn.com/i/teamlogos/ncaa/500/2241.png"
},
"leaders": [
{
"name": "passingYards",
"displayName": "Passing Yards",
"leaders": [
{
"displayValue": "16-29, 159 YDS",
"athlete": {
"id": "186410",
"uid": "s:20~l:23~a:186410",
"guid": "88e458a5745a7e264c1ae083705da423",
"lastName": "Doolittle",
"fullName": "Stan Doolittle",
"displayName": "Stan Doolittle",
"shortName": "S. Doolittle",
"links": [
{
"rel": [
"playercard",
"desktop",
"athlete"
],
"href": "http://www.espn.com/college-football/player/_/id/186410/stan-doolittle",
"text": "Player Card"
}
],
"jersey": "8  ",
"position": {
"abbreviation": "QB"
}
}
}
]
},
{
"name": "rushingYards",
"displayName": "Rushing Yards",
"leaders": [
{
"displayValue": "12 CAR, 18 YDS",
"athlete": {
"id": "186410",
"uid": "s:20~l:23~a:186410",
"guid": "88e458a5745a7e264c1ae083705da423",
"lastName": "Doolittle",
"fullName": "Stan Doolittle",
"displayName": "Stan Doolittle",
"shortName": "S. Doolittle",
"links": [
{
"rel": [
"playercard",
"desktop",
"athlete"
],
"href": "http://www.espn.com/college-football/player/_/id/186410/stan-doolittle",
"text": "Player Card"
}
],
"jersey": "8  ",
"position": {
"abbreviation": "QB"
}
}
}
]
},
{
"name": "receivingYards",
"displayName": "Receiving Yards",
"leaders": [
{
"displayValue": "5 REC, 74 YDS",
"athlete": {
"id": "233464",
"uid": "s:20~l:23~a:233464",
"guid": "9fde99a6026597f7b80a0baf7ff6fac3",
"lastName": "Sanders",
"fullName": "Marquis Sanders",
"displayName": "Marquis Sanders",
"shortName": "M. Sanders",
"links": [
{
"rel": [
"playercard",
"desktop",
"athlete"
],
"href": "http://www.espn.com/college-football/player/_/id/233464/marquis-sanders",
"text": "Player Card"
}
],
"position": {
"abbreviation": "-"
}
}
}
]
}
]
}
],
"broadcasts": [
{
"type": {
"id": "4",
"shortName": "Web",
"longName": "Web",
"slug": "web"
},
"market": {
"id": "2",
"type": "Home"
},
"media": {
"callLetters": "ESPN3",
"name": "ESPN3",
"shortName": "ESPN3"
},
"lang": "en",
"region": "us"
}
],
"predictor": {
"header": "Matchup Predictor",
"homeTeam": {
"id": "2084"
},
"awayTeam": {
"id": "2241"
}
},
"pickcenter": [],
"againstTheSpread": [
{
"team": {
"id": "2241",
"uid": "s:20~l:23~t:2241",
"displayName": "Gardner-Webb Bulldogs",
"abbreviation": "WEBB",
"links": [
{
"href": "https://www.espn.com/college-football/team/_/id/2241/gardner-webb-bulldogs",
"text": "Clubhouse"
},
{
"href": "http://www.espn.com/college-football/team/schedule/_/id/2241",
"text": "Schedule"
}
],
"logo": "https://a.espncdn.com/i/teamlogos/ncaa/500/2241.png"
},
"records": []
},
{
"team": {
"id": "2084",
"uid": "s:20~l:23~t:2084",
"displayName": "Buffalo Bulls",
"abbreviation": "BUFF",
"links": [
{
"href": "https://www.espn.com/college-football/team/_/id/2084/buffalo-bulls",
"text": "Clubhouse"
},
{
"href": "http://www.espn.com/college-football/team/schedule/_/id/2084",
"text": "Schedule"
}
],
"logo": "https://a.espncdn.com/i/teamlogos/ncaa/500/2084.png"
},
"records": []
}
],
"odds": [],
"winprobability": [],
"header": {
"id": "292832084",
"uid": "s:20~l:23~e:292832084",
"season": {
"year": 2009,
"type": 2
},
"timeValid": true,
"competitions": [
{
"id": "292832084",
"uid": "s:20~l:23~e:292832084~c:292832084",
"date": "2009-10-10T19:30Z",
"neutralSite": false,
"conferenceCompetition": false,
"boxscoreAvailable": true,
"commentaryAvailable": false,
"liveAvailable": false,
"onWatchESPN": true,
"recent": false,
"boxscoreSource": "full",
"playByPlaySource": "none",
"competitors": [
{
"id": "2084",
"uid": "s:20~l:23~t:2084",
"order": 0,
"homeAway": "home",
"winner": true,
"team": {
"id": "2084",
"uid": "s:20~l:23~t:2084",
"location": "Buffalo",
"name": "Bulls",
"nickname": "Buffalo",
"abbreviation": "BUFF",
"displayName": "Buffalo Bulls",
"color": "041A9B",
"alternateColor": "ebebeb",
"logos": [
{
"href": "https://a.espncdn.com/i/teamlogos/ncaa/500/2084.png",
"width": 500,
"height": 500,
"alt": "",
"rel": [
"full",
"default"
],
"lastUpdated": "2019-03-01T22:14Z"
},
{
"href": "https://a.espncdn.com/i/teamlogos/ncaa/500-dark/2084.png",
"width": 500,
"height": 500,
"alt": "",
"rel": [
"full",
"dark"
],
"lastUpdated": "2019-03-01T22:14Z"
}
],
"links": [
{
"rel": [
"clubhouse",
"desktop",
"team"
],
"href": "https://www.espn.com/college-football/team/_/id/2084/buffalo-bulls",
"text": "Clubhouse"
}
]
},
"score": "40",
"linescores": [
{
"displayValue": "13"
},
{
"displayValue": "20"
},
{
"displayValue": "7"
},
{
"displayValue": "0"
}
],
"record": [
{
"type": "total",
"summary": "2-4",
"displayValue": "2-4"
},
{
"type": "home",
"summary": "1-2",
"displayValue": "1-2"
},
{
"type": "vsconf",
"summary": "0-2",
"displayValue": "0-2"
}
],
"possession": false
},
{
"id": "2241",
"uid": "s:20~l:23~t:2241",
"order": 1,
"homeAway": "away",
"winner": false,
"team": {
"id": "2241",
"uid": "s:20~l:23~t:2241",
"location": "Gardner-Webb",
"name": "Bulldogs",
"nickname": "Gardner-Webb",
"abbreviation": "WEBB",
"displayName": "Gardner-Webb Bulldogs",
"color": "c12535",
"alternateColor": "909090",
"logos": [
{
"href": "https://a.espncdn.com/i/teamlogos/ncaa/500/2241.png",
"width": 500,
"height": 500,
"alt": "",
"rel": [
"full",
"default"
],
"lastUpdated": "2018-06-05T12:08Z"
},
{
"href": "https://a.espncdn.com/i/teamlogos/ncaa/500-dark/2241.png",
"width": 500,
"height": 500,
"alt": "",
"rel": [
"full",
"dark"
],
"lastUpdated": "2018-06-05T12:08Z"
}
],
"links": [
{
"rel": [
"clubhouse",
"desktop",
"team"
],
"href": "https://www.espn.com/college-football/team/_/id/2241/gardner-webb-bulldogs",
"text": "Clubhouse"
}
]
},
"score": "3",
"linescores": [
{
"displayValue": "3"
},
{
"displayValue": "0"
},
{
"displayValue": "0"
},
{
"displayValue": "0"
}
],
"record": [
{
"type": "total",
"summary": "3-2",
"displayValue": "3-2"
},
{
"type": "road",
"summary": "2-2",
"displayValue": "2-2"
},
{
"type": "vsconf",
"summary": "1-0",
"displayValue": "1-0"
}
],
"possession": false
}
],
"status": {
"type": {
"id": "3",
"name": "STATUS_FINAL",
"state": "post",
"completed": true,
"description": "Final",
"detail": "Final",
"shortDetail": "Final"
}
},
"broadcasts": [
{
"type": {
"id": "2",
"shortName": "PPV"
},
"market": {
"id": "2",
"type": "Home"
},
"media": {
"shortName": "ESGP"
},
"lang": "en",
"region": "us"
},
{
"type": {
"id": "4",
"shortName": "Web"
},
"market": {
"id": "2",
"type": "Home"
},
"media": {
"shortName": "ESPN3"
},
"lang": "en",
"region": "us"
}
]
}
],
"links": [
{
"rel": [
"summary",
"desktop",
"event"
],
"href": "https://www.espn.com/college-football/game/_/gameId/292832084",
"text": "Gamecast",
"shortText": "Summary",
"isExternal": false,
"isPremium": false
},
{
"rel": [
"recap",
"desktop",
"event"
],
"href": "https://www.espn.com/college-football/recap?gameId=292832084",
"text": "Recap",
"shortText": "Recap",
"isExternal": false,
"isPremium": false
},
{
"rel": [
"boxscore",
"desktop",
"event"
],
"href": "http://www.espn.com/college-football/boxscore/_/gameId/292832084",
"text": "Box Score",
"shortText": "Box Score",
"isExternal": false,
"isPremium": false
},
{
"rel": [
"teamstats",
"desktop",
"event"
],
"href": "https://www.espn.com/college-football/matchup?gameId=292832084",
"text": "Team Stats",
"shortText": "Team Stats",
"isExternal": false,
"isPremium": false
}
],
"week": 6,
"league": {
"id": "23",
"uid": "s:20~l:23",
"name": "NCAA - Football",
"abbreviation": "NCAAF",
"midsizeName": "NCAA Football",
"slug": "college-football",
"isTournament": false,
"links": [
{
"rel": [
"index",
"desktop",
"league"
],
"href": "https://www.espn.com/college-football/",
"text": "Index"
},
{
"rel": [
"index",
"sportscenter",
"app",
"league"
],
"href": "sportscenter://x-callback-url/showClubhouse?uid=s:20~l:23",
"text": "Index"
},
{
"rel": [
"schedule",
"desktop",
"league"
],
"href": "https://www.espn.com/college-football/schedule",
"text": "Schedule"
},
{
"rel": [
"schedule",
"sportscenter",
"app",
"league"
],
"href": "sportscenter://x-callback-url/showClubhouse?uid=s:20~l:23&section=scores",
"text": "Schedule"
},
{
"rel": [
"standings",
"desktop",
"league"
],
"href": "http://www.espn.com/college-football/standings",
"text": "Standings"
},
{
"rel": [
"standings",
"sportscenter",
"app",
"league"
],
"href": "sportscenter://x-callback-url/showClubhouse?uid=s:20~l:23&section=standings",
"text": "Standings"
},
{
"rel": [
"rankings",
"desktop",
"league"
],
"href": "https://www.espn.com/college-football/rankings",
"text": "Rankings"
},
{
"rel": [
"scores",
"desktop",
"league"
],
"href": "http://www.espn.com/college-football/scoreboard",
"text": "Scores"
},
{
"rel": [
"scores",
"sportscenter",
"app",
"league"
],
"href": "sportscenter://x-callback-url/showClubhouse?uid=s:20~l:23&section=scores",
"text": "Scores"
},
{
"rel": [
"stats",
"desktop",
"league"
],
"href": "http://www.espn.com/college-football/stats",
"text": "Stats"
},
{
"rel": [
"teams",
"desktop",
"league"
],
"href": "http://www.espn.com/college-football/teams",
"text": "Teams"
},
{
"rel": [
"athletes",
"desktop",
"league"
],
"href": "http://www.espn.com/college-football/players",
"text": "Players"
},
{
"rel": [
"injuries",
"desktop",
"league"
],
"href": "https://www.espn.com/college-football/injuries",
"text": "Injuries"
}
]
}
},
"scoringPlays": [],
"videos": [],
"standings": {
"fullViewLink": {
"text": "Full Standings",
"href": "http://www.espn.com/college-football/standings"
},
"groups": [
{
"standings": {
"entries": [
{
"team": "Kennesaw State",
"link": "https://www.espn.com/college-football/team/_/id/338/kennesaw-state-owls",
"id": "338",
"uid": "s:20~l:23~t:338",
"stats": [
{
"id": "0",
"name": "overall",
"abbreviation": "overall",
"displayName": "Overall",
"shortDisplayName": "OVER",
"description": "Overall Record",
"type": "total",
"summary": "11-2",
"displayValue": "11-2"
},
{
"id": "9",
"name": "vsConf",
"abbreviation": "CONF",
"displayName": "vs. Conference",
"shortDisplayName": "CONF",
"description": "Conference Record",
"type": "vsconf",
"summary": "7-0",
"displayValue": "7-0"
}
],
"logo": [
{
"href": "https://a.espncdn.com/i/teamlogos/ncaa/500/338.png",
"width": 500,
"height": 500,
"alt": "",
"rel": [
"full",
"default"
],
"lastUpdated": "2018-06-05T12:08Z"
}
]
},
{
"team": "Monmouth",
"link": "https://www.espn.com/college-football/team/_/id/2405/monmouth-hawks",
"id": "2405",
"uid": "s:20~l:23~t:2405",
"stats": [
{
"id": "0",
"name": "overall",
"abbreviation": "overall",
"displayName": "Overall",
"shortDisplayName": "OVER",
"description": "Overall Record",
"type": "total",
"summary": "7-4",
"displayValue": "7-4"
},
{
"id": "9",
"name": "vsConf",
"abbreviation": "CONF",
"displayName": "vs. Conference",
"shortDisplayName": "CONF",
"description": "Conference Record",
"type": "vsconf",
"summary": "6-1",
"displayValue": "6-1"
}
],
"logo": [
{
"href": "https://a.espncdn.com/i/teamlogos/ncaa/500/2405.png",
"width": 500,
"height": 500,
"alt": "",
"rel": [
"full",
"default"
],
"lastUpdated": "2018-06-05T12:08Z"
}
]
},
{
"team": "North Carolina A&T",
"link": "https://www.espn.com/college-football/team/_/id/2448/north-carolina-at-aggies",
"id": "2448",
"uid": "s:20~l:23~t:2448",
"stats": [
{
"id": "0",
"name": "overall",
"abbreviation": "overall",
"displayName": "Overall",
"shortDisplayName": "OVER",
"description": "Overall Record",
"type": "total",
"summary": "5-6",
"displayValue": "5-6"
},
{
"id": "9",
"name": "vsConf",
"abbreviation": "CONF",
"displayName": "vs. Conference",
"shortDisplayName": "CONF",
"description": "Conference Record",
"type": "vsconf",
"summary": "3-4",
"displayValue": "3-4"
}
],
"logo": [
{
"href": "https://a.espncdn.com/i/teamlogos/ncaa/500/2448.png",
"width": 500,
"height": 500,
"alt": "",
"rel": [
"full",
"default"
],
"lastUpdated": "2018-06-05T12:08Z"
}
]
},
{
"team": "Robert Morris",
"link": "https://www.espn.com/college-football/team/_/id/2523/robert-morris-colonials",
"id": "2523",
"uid": "s:20~l:23~t:2523",
"stats": [
{
"id": "0",
"name": "overall",
"abbreviation": "overall",
"displayName": "Overall",
"shortDisplayName": "OVER",
"description": "Overall Record",
"type": "total",
"summary": "4-6",
"displayValue": "4-6"
},
{
"id": "9",
"name": "vsConf",
"abbreviation": "CONF",
"displayName": "vs. Conference",
"shortDisplayName": "CONF",
"description": "Conference Record",
"type": "vsconf",
"summary": "3-4",
"displayValue": "3-4"
}
],
"logo": [
{
"href": "https://a.espncdn.com/i/teamlogos/ncaa/500/2523.png",
"width": 500,
"height": 500,
"alt": "",
"rel": [
"full",
"default"
],
"lastUpdated": "2020-12-16T15:18Z"
}
]
},
{
"team": "Charleston Southern",
"link": "https://www.espn.com/college-football/team/_/id/2127/charleston-southern-buccaneers",
"id": "2127",
"uid": "s:20~l:23~t:2127",
"stats": [
{
"id": "0",
"name": "overall",
"abbreviation": "overall",
"displayName": "Overall",
"shortDisplayName": "OVER",
"description": "Overall Record",
"type": "total",
"summary": "4-6",
"displayValue": "4-6"
},
{
"id": "9",
"name": "vsConf",
"abbreviation": "CONF",
"displayName": "vs. Conference",
"shortDisplayName": "CONF",
"description": "Conference Record",
"type": "vsconf",
"summary": "3-4",
"displayValue": "3-4"
}
],
"logo": [
{
"href": "https://a.espncdn.com/i/teamlogos/ncaa/500/2127.png",
"width": 500,
"height": 500,
"alt": "",
"rel": [
"full",
"default"
],
"lastUpdated": "2021-06-30T22:04Z"
}
]
},
{
"team": "Hampton",
"link": "https://www.espn.com/college-football/team/_/id/2261/hampton-pirates",
"id": "2261",
"uid": "s:20~l:23~t:2261",
"stats": [
{
"id": "0",
"name": "overall",
"abbreviation": "overall",
"displayName": "Overall",
"shortDisplayName": "OVER",
"description": "Overall Record",
"type": "total",
"summary": "5-6",
"displayValue": "5-6"
},
{
"id": "9",
"name": "vsConf",
"abbreviation": "CONF",
"displayName": "vs. Conference",
"shortDisplayName": "CONF",
"description": "Conference Record",
"type": "vsconf",
"summary": "3-4",
"displayValue": "3-4"
}
],
"logo": [
{
"href": "https://a.espncdn.com/i/teamlogos/ncaa/500/2261.png",
"width": 500,
"height": 500,
"alt": "",
"rel": [
"full",
"default"
],
"lastUpdated": "2018-06-05T12:08Z"
}
]
},
{
"team": "North Alabama",
"link": "https://www.espn.com/college-football/team/_/id/2453/north-alabama-lions",
"id": "2453",
"uid": "s:20~l:23~t:2453",
"stats": [
{
"id": "0",
"name": "overall",
"abbreviation": "overall",
"displayName": "Overall",
"shortDisplayName": "OVER",
"description": "Overall Record",
"type": "total",
"summary": "3-8",
"displayValue": "3-8"
},
{
"id": "9",
"name": "vsConf",
"abbreviation": "CONF",
"displayName": "vs. Conference",
"shortDisplayName": "CONF",
"description": "Conference Record",
"type": "vsconf",
"summary": "2-4",
"displayValue": "2-4"
}
],
"logo": [
{
"href": "https://a.espncdn.com/i/teamlogos/ncaa/500/2453.png",
"width": 500,
"height": 500,
"alt": "",
"rel": [
"full",
"default"
],
"lastUpdated": "2018-11-05T11:33Z"
}
]
},
{
"team": "Campbell",
"link": "https://www.espn.com/college-football/team/_/id/2097/campbell-fighting-camels",
"id": "2097",
"uid": "s:20~l:23~t:2097",
"stats": [
{
"id": "0",
"name": "overall",
"abbreviation": "overall",
"displayName": "Overall",
"shortDisplayName": "OVER",
"description": "Overall Record",
"type": "total",
"summary": "3-8",
"displayValue": "3-8"
},
{
"id": "9",
"name": "vsConf",
"abbreviation": "CONF",
"displayName": "vs. Conference",
"shortDisplayName": "CONF",
"description": "Conference Record",
"type": "vsconf",
"summary": "2-5",
"displayValue": "2-5"
}
],
"logo": [
{
"href": "https://a.espncdn.com/i/teamlogos/ncaa/500/2097.png",
"width": 500,
"height": 500,
"alt": "",
"rel": [
"full",
"default"
],
"lastUpdated": "2018-06-05T12:08Z"
}
]
},
{
"team": "Gardner-Webb",
"link": "https://www.espn.com/college-football/team/_/id/2241/gardner-webb-bulldogs",
"id": "2241",
"uid": "s:20~l:23~t:2241",
"stats": [
{
"id": "0",
"name": "overall",
"abbreviation": "overall",
"displayName": "Overall",
"shortDisplayName": "OVER",
"description": "Overall Record",
"type": "total",
"summary": "4-7",
"displayValue": "4-7"
},
{
"id": "9",
"name": "vsConf",
"abbreviation": "CONF",
"displayName": "vs. Conference",
"shortDisplayName": "CONF",
"description": "Conference Record",
"type": "vsconf",
"summary": "2-5",
"displayValue": "2-5"
}
],
"logo": [
{
"href": "https://a.espncdn.com/i/teamlogos/ncaa/500/2241.png",
"width": 500,
"height": 500,
"alt": "",
"rel": [
"full",
"default"
],
"lastUpdated": "2018-06-05T12:08Z"
}
]
}
]
},
"header": "2021 Big South Conference Standings"
},
{
"divisions": [
{
"header": "Mid-American - East",
"standings": {
"entries": [
{
"team": "Kent State",
"link": "https://www.espn.com/college-football/team/_/id/2309/kent-state-golden-flashes",
"id": "2309",
"uid": "s:20~l:23~t:2309",
"stats": [
{
"id": "0",
"name": "overall",
"abbreviation": "overall",
"displayName": "Overall",
"shortDisplayName": "OVER",
"description": "Overall Record",
"type": "total",
"summary": "7-7",
"displayValue": "7-7"
},
{
"id": "9",
"name": "vsConf",
"abbreviation": "CONF",
"displayName": "vs. Conference",
"shortDisplayName": "CONF",
"description": "Conference Record",
"type": "vsconf",
"summary": "6-2",
"displayValue": "6-2"
}
],
"logo": [
{
"href": "https://a.espncdn.com/i/teamlogos/ncaa/500/2309.png",
"width": 500,
"height": 500,
"alt": "",
"rel": [
"full",
"default"
],
"lastUpdated": "2018-06-05T12:08Z"
}
]
},
{
"team": "Miami (OH)",
"link": "https://www.espn.com/college-football/team/_/id/193/miami-oh-redhawks",
"id": "193",
"uid": "s:20~l:23~t:193",
"stats": [
{
"id": "0",
"name": "overall",
"abbreviation": "overall",
"displayName": "Overall",
"shortDisplayName": "OVER",
"description": "Overall Record",
"type": "total",
"summary": "7-6",
"displayValue": "7-6"
},
{
"id": "9",
"name": "vsConf",
"abbreviation": "CONF",
"displayName": "vs. Conference",
"shortDisplayName": "CONF",
"description": "Conference Record",
"type": "vsconf",
"summary": "5-3",
"displayValue": "5-3"
}
],
"logo": [
{
"href": "https://a.espncdn.com/i/teamlogos/ncaa/500/193.png",
"width": 500,
"height": 500,
"alt": "",
"rel": [
"full",
"default"
],
"lastUpdated": "2018-06-05T12:08Z"
}
]
},
{
"team": "Ohio",
"link": "https://www.espn.com/college-football/team/_/id/195/ohio-bobcats",
"id": "195",
"uid": "s:20~l:23~t:195",
"stats": [
{
"id": "0",
"name": "overall",
"abbreviation": "overall",
"displayName": "Overall",
"shortDisplayName": "OVER",
"description": "Overall Record",
"type": "total",
"summary": "3-9",
"displayValue": "3-9"
},
{
"id": "9",
"name": "vsConf",
"abbreviation": "CONF",
"displayName": "vs. Conference",
"shortDisplayName": "CONF",
"description": "Conference Record",
"type": "vsconf",
"summary": "3-5",
"displayValue": "3-5"
}
],
"logo": [
{
"href": "https://a.espncdn.com/i/teamlogos/ncaa/500/195.png",
"width": 500,
"height": 500,
"alt": "",
"rel": [
"full",
"default"
],
"lastUpdated": "2021-06-10T21:28Z"
}
]
},
{
"team": "Bowling Green",
"link": "https://www.espn.com/college-football/team/_/id/189/bowling-green-falcons",
"id": "189",
"uid": "s:20~l:23~t:189",
"stats": [
{
"id": "0",
"name": "overall",
"abbreviation": "overall",
"displayName": "Overall",
"shortDisplayName": "OVER",
"description": "Overall Record",
"type": "total",
"summary": "4-8",
"displayValue": "4-8"
},
{
"id": "9",
"name": "vsConf",
"abbreviation": "CONF",
"displayName": "vs. Conference",
"shortDisplayName": "CONF",
"description": "Conference Record",
"type": "vsconf",
"summary": "2-6",
"displayValue": "2-6"
}
],
"logo": [
{
"href": "https://a.espncdn.com/i/teamlogos/ncaa/500/189.png",
"width": 500,
"height": 500,
"alt": "",
"rel": [
"full",
"default"
],
"lastUpdated": "2018-06-05T12:08Z"
}
]
},
{
"team": "Buffalo",
"link": "https://www.espn.com/college-football/team/_/id/2084/buffalo-bulls",
"id": "2084",
"uid": "s:20~l:23~t:2084",
"stats": [
{
"id": "0",
"name": "overall",
"abbreviation": "overall",
"displayName": "Overall",
"shortDisplayName": "OVER",
"description": "Overall Record",
"type": "total",
"summary": "4-8",
"displayValue": "4-8"
},
{
"id": "9",
"name": "vsConf",
"abbreviation": "CONF",
"displayName": "vs. Conference",
"shortDisplayName": "CONF",
"description": "Conference Record",
"type": "vsconf",
"summary": "2-6",
"displayValue": "2-6"
}
],
"logo": [
{
"href": "https://a.espncdn.com/i/teamlogos/ncaa/500/2084.png",
"width": 500,
"height": 500,
"alt": "",
"rel": [
"full",
"default"
],
"lastUpdated": "2019-03-01T22:14Z"
}
]
},
{
"team": "Akron",
"link": "https://www.espn.com/college-football/team/_/id/2006/akron-zips",
"id": "2006",
"uid": "s:20~l:23~t:2006",
"stats": [
{
"id": "0",
"name": "overall",
"abbreviation": "overall",
"displayName": "Overall",
"shortDisplayName": "OVER",
"description": "Overall Record",
"type": "total",
"summary": "2-10",
"displayValue": "2-10"
},
{
"id": "9",
"name": "vsConf",
"abbreviation": "CONF",
"displayName": "vs. Conference",
"shortDisplayName": "CONF",
"description": "Conference Record",
"type": "vsconf",
"summary": "1-7",
"displayValue": "1-7"
}
],
"logo": [
{
"href": "https://a.espncdn.com/i/teamlogos/ncaa/500/2006.png",
"width": 500,
"height": 500,
"alt": "",
"rel": [
"full",
"default"
],
"lastUpdated": "2021-06-25T15:05Z"
}
]
}
]
}
},
{
"header": "Mid-American - West",
"standings": {
"entries": [
{
"team": "Northern Illinois",
"link": "https://www.espn.com/college-football/team/_/id/2459/northern-illinois-huskies",
"id": "2459",
"uid": "s:20~l:23~t:2459",
"stats": [
{
"id": "0",
"name": "overall",
"abbreviation": "overall",
"displayName": "Overall",
"shortDisplayName": "OVER",
"description": "Overall Record",
"type": "total",
"summary": "9-5",
"displayValue": "9-5"
},
{
"id": "9",
"name": "vsConf",
"abbreviation": "CONF",
"displayName": "vs. Conference",
"shortDisplayName": "CONF",
"description": "Conference Record",
"type": "vsconf",
"summary": "6-2",
"displayValue": "6-2"
}
],
"logo": [
{
"href": "https://a.espncdn.com/i/teamlogos/ncaa/500/2459.png",
"width": 500,
"height": 500,
"alt": "",
"rel": [
"full",
"default"
],
"lastUpdated": "2018-06-05T12:08Z"
}
]
},
{
"team": "Central Michigan",
"link": "https://www.espn.com/college-football/team/_/id/2117/central-michigan-chippewas",
"id": "2117",
"uid": "s:20~l:23~t:2117",
"stats": [
{
"id": "0",
"name": "overall",
"abbreviation": "overall",
"displayName": "Overall",
"shortDisplayName": "OVER",
"description": "Overall Record",
"type": "total",
"summary": "9-4",
"displayValue": "9-4"
},
{
"id": "9",
"name": "vsConf",
"abbreviation": "CONF",
"displayName": "vs. Conference",
"shortDisplayName": "CONF",
"description": "Conference Record",
"type": "vsconf",
"summary": "6-2",
"displayValue": "6-2"
}
],
"logo": [
{
"href": "https://a.espncdn.com/i/teamlogos/ncaa/500/2117.png",
"width": 500,
"height": 500,
"alt": "",
"rel": [
"full",
"default"
],
"lastUpdated": "2018-06-05T12:08Z"
}
]
},
{
"team": "Toledo",
"link": "https://www.espn.com/college-football/team/_/id/2649/toledo-rockets",
"id": "2649",
"uid": "s:20~l:23~t:2649",
"stats": [
{
"id": "0",
"name": "overall",
"abbreviation": "overall",
"displayName": "Overall",
"shortDisplayName": "OVER",
"description": "Overall Record",
"type": "total",
"summary": "7-6",
"displayValue": "7-6"
},
{
"id": "9",
"name": "vsConf",
"abbreviation": "CONF",
"displayName": "vs. Conference",
"shortDisplayName": "CONF",
"description": "Conference Record",
"type": "vsconf",
"summary": "5-3",
"displayValue": "5-3"
}
],
"logo": [
{
"href": "https://a.espncdn.com/i/teamlogos/ncaa/500/2649.png",
"width": 500,
"height": 500,
"alt": "",
"rel": [
"full",
"default"
],
"lastUpdated": "2018-10-16T18:59Z"
}
]
},
{
"team": "Ball State",
"link": "https://www.espn.com/college-football/team/_/id/2050/ball-state-cardinals",
"id": "2050",
"uid": "s:20~l:23~t:2050",
"stats": [
{
"id": "0",
"name": "overall",
"abbreviation": "overall",
"displayName": "Overall",
"shortDisplayName": "OVER",
"description": "Overall Record",
"type": "total",
"summary": "6-7",
"displayValue": "6-7"
},
{
"id": "9",
"name": "vsConf",
"abbreviation": "CONF",
"displayName": "vs. Conference",
"shortDisplayName": "CONF",
"description": "Conference Record",
"type": "vsconf",
"summary": "4-4",
"displayValue": "4-4"
}
],
"logo": [
{
"href": "https://a.espncdn.com/i/teamlogos/ncaa/500/2050.png",
"width": 500,
"height": 500,
"alt": "",
"rel": [
"full",
"default"
],
"lastUpdated": "2018-06-05T12:08Z"
}
]
},
{
"team": "Eastern Michigan",
"link": "https://www.espn.com/college-football/team/_/id/2199/eastern-michigan-eagles",
"id": "2199",
"uid": "s:20~l:23~t:2199",
"stats": [
{
"id": "0",
"name": "overall",
"abbreviation": "overall",
"displayName": "Overall",
"shortDisplayName": "OVER",
"description": "Overall Record",
"type": "total",
"summary": "7-6",
"displayValue": "7-6"
},
{
"id": "9",
"name": "vsConf",
"abbreviation": "CONF",
"displayName": "vs. Conference",
"shortDisplayName": "CONF",
"description": "Conference Record",
"type": "vsconf",
"summary": "4-4",
"displayValue": "4-4"
}
],
"logo": [
{
"href": "https://a.espncdn.com/i/teamlogos/ncaa/500/2199.png",
"width": 500,
"height": 500,
"alt": "",
"rel": [
"full",
"default"
],
"lastUpdated": "2018-06-05T12:08Z"
}
]
},
{
"team": "Western Michigan",
"link": "https://www.espn.com/college-football/team/_/id/2711/western-michigan-broncos",
"id": "2711",
"uid": "s:20~l:23~t:2711",
"stats": [
{
"id": "0",
"name": "overall",
"abbreviation": "overall",
"displayName": "Overall",
"shortDisplayName": "OVER",
"description": "Overall Record",
"type": "total",
"summary": "8-5",
"displayValue": "8-5"
},
{
"id": "9",
"name": "vsConf",
"abbreviation": "CONF",
"displayName": "vs. Conference",
"shortDisplayName": "CONF",
"description": "Conference Record",
"type": "vsconf",
"summary": "4-4",
"displayValue": "4-4"
}
],
"logo": [
{
"href": "https://a.espncdn.com/i/teamlogos/ncaa/500/2711.png",
"width": 500,
"height": 500,
"alt": "",
"rel": [
"full",
"default"
],
"lastUpdated": "2021-06-15T22:27Z"
}
]
}
]
}
}
],
"header": "2021 Mid-American Conference Standings",
"href": "https://www.espn.com/college-football/standings/_/group/15/view/fbs-i-a"
}
]
}
}